Workbook

Sheet Instruções
A1: MATRIZ SWOT DO PERFIL ECONÔMICO-PRODUTIVO SETORIAL MUNICIPAL (PESM) — PANTANAL NORTE
A2: Projeto DSIP-MT | Convênio 984799/2025-SUDECO-UNEMAT | Meta 1 — Análise Diagnóstica Estratégica do PESM
A4: LÓGICA | B4: Estrutura adaptada da Matriz ICS-MP: indicador → limiares → classificação automática → síntese. Forças e Fraquezas vêm de indicadores INTERNOS (aba 'Indicadores (F-W)'), classificados automaticamente. Oportunidades e Ameaças vêm de fatores EXTERNOS (aba 'Fatores Externos (O-A)'), pontuados pela equipe com base nas pesquisas secundária, web-based e de campo.
A5: PASSO 1 | B5: Na aba 'Parâmetros', revise as bandas de tolerância e o corte de relevância dos fatores externos.
A6: PASSO 2 | B6: Na aba 'Indicadores (F-W)', preencha a coluna 'Valor ref. MT' (valor do estado no mesmo ano) e, para cada município, a coluna 'Dado bruto'. Células com fundo AMARELO e texto AZUL são de entrada manual. A coluna 'Classificação' é automática — não editar.
A7: CRITÉRIOS | B7: Absoluto: usa os limiares manuais (colunas J e K). Razão MT: limiares = ref. MT × (1 ± banda relativa). Dif. MT (p.p.): limiares = ref. MT ± banda em pontos percentuais (usar para taxas de variação e percentuais). Sentido '+': valor acima do limiar superior = Força; abaixo do inferior = Fraqueza. Sentido '-': o inverso. Entre os limiares = Neutro.
A8: PASSO 3 | B8: Na aba 'Fatores Externos (O-A)', atribua a cada fator a intensidade para cada município: 0 = não se aplica, 1 = baixa, 2 = média, 3 = alta. Registre a evidência que sustenta a nota (notícia, dado, observação de campo). Recomenda-se nota por consenso de dois pesquisadores.
A9: PASSO 4 | B9: Cada município tem sua própria aba 'SWOT - <município>', pronta para impressão em A4 paisagem e atualizada automaticamente. A aba 'Matriz SWOT (seletor)' permite alternar entre municípios na célula C3. A aba 'Painel' mostra a síntese dos 13 municípios e a frequência de cada item na região (base para a SWOT regional do Relatório Parcial).
A10: ÁREAS-CHAVE | B10: Quatro áreas-chave, dentro do intervalo de 3 a 6 previsto no Plano de Trabalho: Agropecuária; Indústria; Comércio e Serviços; Estrutura Econômica e Fiscal. Indicadores e fatores podem ser incluídos ao final das tabelas, desde que as fórmulas sejam estendidas.
A11: DADO AUSENTE | B11: Deixe a célula em branco. O indicador é contado como 'sem dado' e não entra em nenhum quadrante.
A12: CUIDADOS | B12: (1) Use o mesmo ano-base para todos os municípios em cada indicador. (2) RAIS capta apenas emprego formal e subestima a agropecuária; confrontar com VAB e Censo Agro. (3) Em municípios pequenos, QL e variações percentuais são instáveis; conferir valores absolutos. (4) Rondonópolis tem escala muito superior aos demais; em comparações regionais, apresentar resultados com e sem o município.
A13: LIMIARES | B13: Os limiares absolutos dos quocientes locacionais (0,8 e 1,2) e as bandas padrão (±10% e ±2 p.p.) são propostas iniciais, a validar com a coordenação e o orientador antes da análise final.
A14: RANKINGS | B14: 'Ranking Locacional': QLs, coeficiente de especialização e diversificação, calculados e ordenados automaticamente. 'Ranking SWOT (provisório)': índice (F−W)/n combinado com (O−T)/n; marcado como provisório até 75% de cobertura interna e externa.

Sheet Matriz SWOT (seletor)
B1: MATRIZ SWOT — PERFIL ECONÔMICO-PRODUTIVO SETORIAL MUNICIPAL (PESM) | PANTANAL NORTE
B3: Município: | C3: Cáceres | F3: ="Indicadores: "&COUNTIF(Aux!$C$6:$C$21,"Neutro")&" neutros | "&(COUNTA(Aux!$A$6:$A$21)-COUNTIF(Aux!$C$6:$C$21,"Força")-COUNTIF(Aux!$C$6:$C$21,"Fraqueza")-COUNTIF(Aux!$C$6:$C$21,"Neutro"))&" sem dado" -> Indicadores: 3 neutros | 2 sem dado
B5: FAVORÁVEL | F5: DESFAVORÁVEL
B6: ="FORÇAS (S) — "&COUNTIF(Aux!$C$6:$C$21,"Força")&" item(ns)" -> FORÇAS (S) — 3 item(ns) | F6: ="FRAQUEZAS (W) — "&COUNTIF(Aux!$C$6:$C$21,"Fraqueza")&" item(ns)" -> FRAQUEZAS (W) — 8 item(ns)
B7: Nº | C7: Item (área-chave, código e descrição) | D7: Valor | F7: Nº | G7: Item (área-chave, código e descrição) | H7: Valor
A8: AMBIENTE INTERNO | B8: =IF(C8="","",1) -> 1 | C8: =IFERROR(INDEX(Aux!$B$6:$B$21,MATCH(1,Aux!$E$6:$E$21,0)),"") -> [Agropecuária] AGR-03 – Variação do efetivo bovino em 5 anos (%) | D8: =IFERROR(INDEX(Aux!$D$6:$D$21,MATCH(1,Aux!$E$6:$E$21,0)),"") -> 22.65 | F8: =IF(G8="","",1) -> 1 | G8: =IFERROR(INDEX(Aux!$B$6:$B$21,MATCH(1,Aux!$F$6:$F$21,0)),"") -> [Agropecuária] AGR-01 – Quociente locacional do VAB agropecuário (base MT) (índice) | H8: =IFERROR(INDEX(Aux!$D$6:$D$21,MATCH(1,Aux!$F$6:$F$21,0)),"") -> 0.3713
B9: =IF(C9="","",2) -> 2 | C9: =IFERROR(INDEX(Aux!$B$6:$B$21,MATCH(2,Aux!$E$6:$E$21,0)),"") -> [Indústria] IND-02 – Variação do emprego formal na indústria em 5 anos (%) | D9: =IFERROR(INDEX(Aux!$D$6:$D$21,MATCH(2,Aux!$E$6:$E$21,0)),"") -> 58.91 | F9: =IF(G9="","",2) -> 2 | G9: =IFERROR(INDEX(Aux!$B$6:$B$21,MATCH(2,Aux!$F$6:$F$21,0)),"") -> [Indústria] IND-01 – Quociente locacional do VAB industrial (base MT) (índice) | H9: =IFERROR(INDEX(Aux!$D$6:$D$21,MATCH(2,Aux!$F$6:$F$21,0)),"") -> 0.6374
B10: =IF(C10="","",3) -> 3 | C10: =IFERROR(INDEX(Aux!$B$6:$B$21,MATCH(3,Aux!$E$6:$E$21,0)),"") -> [Comércio e Serviços] CS-01 – Quociente locacional do VAB de serviços, exceto adm. pública (base MT) (índice) | D10: =IFERROR(INDEX(Aux!$D$6:$D$21,MATCH(3,Aux!$E$6:$E$21,0)),"") -> 1.3013 | F10: =IF(G10="","",3) -> 3 | G10: =IFERROR(INDEX(Aux!$B$6:$B$21,MATCH(3,Aux!$F$6:$F$21,0)),"") -> [Indústria] IND-03 – Remuneração média do emprego formal industrial (R$) | H10: =IFERROR(INDEX(Aux!$D$6:$D$21,MATCH(3,Aux!$F$6:$F$21,0)),"") -> 2345.65
B11: =IF(C11="","",4) | C11: =IFERROR(INDEX(Aux!$B$6:$B$21,MATCH(4,Aux!$E$6:$E$21,0)),"") | D11: =IFERROR(INDEX(Aux!$D$6:$D$21,MATCH(4,Aux!$E$6:$E$21,0)),"") | F11: =IF(G11="","",4) -> 4 | G11: =IFERROR(INDEX(Aux!$B$6:$B$21,MATCH(4,Aux!$F$6:$F$21,0)),"") -> [Comércio e Serviços] CS-02 – Variação do emprego formal em comércio e serviços em 5 anos (%) | H11: =IFERROR(INDEX(Aux!$D$6:$D$21,MATCH(4,Aux!$F$6:$F$21,0)),"") -> 13.05
B12: =IF(C12="","",5) | C12: =IFERROR(INDEX(Aux!$B$6:$B$21,MATCH(5,Aux!$E$6:$E$21,0)),"") | D12: =IFERROR(INDEX(Aux!$D$6:$D$21,MATCH(5,Aux!$E$6:$E$21,0)),"") | F12: =IF(G12="","",5) -> 5 | G12: =IFERROR(INDEX(Aux!$B$6:$B$21,MATCH(5,Aux!$F$6:$F$21,0)),"") -> [Comércio e Serviços] CS-03 – Empresas e outras organizações ativas por mil habitantes (un./mil hab.) | H12: =IFERROR(INDEX(Aux!$D$6:$D$21,MATCH(5,Aux!$F$6:$F$21,0)),"") -> 19.41
B13: =IF(C13="","",6) | C13: =IFERROR(INDEX(Aux!$B$6:$B$21,MATCH(6,Aux!$E$6:$E$21,0)),"") | D13: =IFERROR(INDEX(Aux!$D$6:$D$21,MATCH(6,Aux!$E$6:$E$21,0)),"") | F13: =IF(G13="","",6) -> 6 | G13: =IFERROR(INDEX(Aux!$B$6:$B$21,MATCH(6,Aux!$F$6:$F$21,0)),"") -> [Estrutura Econômica e Fiscal] EST-01 – PIB per capita (R$) | H13: =IFERROR(INDEX(Aux!$D$6:$D$21,MATCH(6,Aux!$F$6:$F$21,0)),"") -> 31174.15
B14: =IF(C14="","",7) | C14: =IFERROR(INDEX(Aux!$B$6:$B$21,MATCH(7,Aux!$E$6:$E$21,0)),"") | D14: =IFERROR(INDEX(Aux!$D$6:$D$21,MATCH(7,Aux!$E$6:$E$21,0)),"") | F14: =IF(G14="","",7) -> 7 | G14: =IFERROR(INDEX(Aux!$B$6:$B$21,MATCH(7,Aux!$F$6:$F$21,0)),"") -> [Estrutura Econômica e Fiscal] EST-02 – Participação da administração pública no VAB total (%) | H14: =IFERROR(INDEX(Aux!$D$6:$D$21,MATCH(7,Aux!$F$6:$F$21,0)),"") -> 30.82
B15: =IF(C15="","",8) | C15: =IFERROR(INDEX(Aux!$B$6:$B$21,MATCH(8,Aux!$E$6:$E$21,0)),"") | D15: =IFERROR(INDEX(Aux!$D$6:$D$21,MATCH(8,Aux!$E$6:$E$21,0)),"") | F15: =IF(G15="","",8) -> 8 | G15: =IFERROR(INDEX(Aux!$B$6:$B$21,MATCH(8,Aux!$F$6:$F$21,0)),"") -> [Estrutura Econômica e Fiscal] EST-03 – Vínculos formais por 100 habitantes (vínculos/100 hab.) | H15: =IFERROR(INDEX(Aux!$D$6:$D$21,MATCH(8,Aux!$F$6:$F$21,0)),"") -> 18.4
B16: =IF(C16="","",9) | C16: =IFERROR(INDEX(Aux!$B$6:$B$21,MATCH(9,Aux!$E$6:$E$21,0)),"") | D16: =IFERROR(INDEX(Aux!$D$6:$D$21,MATCH(9,Aux!$E$6:$E$21,0)),"") | F16: =IF(G16="","",9) | G16: =IFERROR(INDEX(Aux!$B$6:$B$21,MATCH(9,Aux!$F$6:$F$21,0)),"") | H16: =IFERROR(INDEX(Aux!$D$6:$D$21,MATCH(9,Aux!$F$6:$F$21,0)),"")
B17: =IF(C17="","",10) | C17: =IFERROR(INDEX(Aux!$B$6:$B$21,MATCH(10,Aux!$E$6:$E$21,0)),"") | D17: =IFERROR(INDEX(Aux!$D$6:$D$21,MATCH(10,Aux!$E$6:$E$21,0)),"") | F17: =IF(G17="","",10) | G17: =IFERROR(INDEX(Aux!$B$6:$B$21,MATCH(10,Aux!$F$6:$F$21,0)),"") | H17: =IFERROR(INDEX(Aux!$D$6:$D$21,MATCH(10,Aux!$F$6:$F$21,0)),"")
B18: =IF(C18="","",11) | C18: =IFERROR(INDEX(Aux!$B$6:$B$21,MATCH(11,Aux!$E$6:$E$21,0)),"") | D18: =IFERROR(INDEX(Aux!$D$6:$D$21,MATCH(11,Aux!$E$6:$E$21,0)),"") | F18: =IF(G18="","",11) | G18: =IFERROR(INDEX(Aux!$B$6:$B$21,MATCH(11,Aux!$F$6:$F$21,0)),"") | H18: =IFERROR(INDEX(Aux!$D$6:$D$21,MATCH(11,Aux!$F$6:$F$21,0)),"")
B19: =IF(C19="","",12) | C19: =IFERROR(INDEX(Aux!$B$6:$B$21,MATCH(12,Aux!$E$6:$E$21,0)),"") | D19: =IFERROR(INDEX(Aux!$D$6:$D$21,MATCH(12,Aux!$E$6:$E$21,0)),"") | F19: =IF(G19="","",12) | G19: =IFERROR(INDEX(Aux!$B$6:$B$21,MATCH(12,Aux!$F$6:$F$21,0)),"") | H19: =IFERROR(INDEX(Aux!$D$6:$D$21,MATCH(12,Aux!$F$6:$F$21,0)),"")
C20: =IF(COUNTIF(Aux!$C$6:$C$21,"Força")>12,"+ "&(COUNTIF(Aux!$C$6:$C$21,"Força")-12)&" item(ns) não exibido(s) — ver abas de dados","") | G20: =IF(COUNTIF(Aux!$C$6:$C$21,"Fraqueza")>12,"+ "&(COUNTIF(Aux!$C$6:$C$21,"Fraqueza")-12)&" item(ns) não exibido(s) — ver abas de dados","")
B22: ="OPORTUNIDADES (O) — "&SUM(Aux!$L$6:$L$16)&" item(ns)" -> OPORTUNIDADES (O) — 6 item(ns) | F22: ="AMEAÇAS (T) — "&SUM(Aux!$N$6:$N$16)&" item(ns)" -> AMEAÇAS (T) — 4 item(ns)
B23: Nº | C23: Item (área-chave, código e descrição) | D23: Intensidade | F23: Nº | G23: Item (área-chave, código e descrição) | H23: Intensidade
A24: AMBIENTE EXTERNO | B24: =IF(C24="","",1) -> 1 | C24: =IFERROR(INDEX(Aux!$I$6:$I$16,MATCH(1,Aux!$M$6:$M$16,0)),"") -> [Agropecuária] OP-01 – Demanda externa por carne bovina e proteína animal | D24: =IFERROR(INDEX(Aux!$K$6:$K$16,MATCH(1,Aux!$M$6:$M$16,0)),"") -> 3 | F24: =IF(G24="","",1) -> 1 | G24: =IFERROR(INDEX(Aux!$I$6:$I$16,MATCH(1,Aux!$O$6:$O$16,0)),"") -> [Agropecuária] AM-01 – Eventos climáticos extremos: secas prolongadas e incêndios no Pantanal | H24: =IFERROR(INDEX(Aux!$K$6:$K$16,MATCH(1,Aux!$O$6:$O$16,0)),"") -> 3
B25: =IF(C25="","",2) -> 2 | C25: =IFERROR(INDEX(Aux!$I$6:$I$16,MATCH(2,Aux!$M$6:$M$16,0)),"") -> [Agropecuária] OP-02 – Mercados para produtos diferenciados e certificados (carne sustentável/orgânica, origem Pantanal) | D25: =IFERROR(INDEX(Aux!$K$6:$K$16,MATCH(2,Aux!$M$6:$M$16,0)),"") -> 3 | F25: =IF(G25="","",2) -> 2 | G25: =IFERROR(INDEX(Aux!$I$6:$I$16,MATCH(2,Aux!$O$6:$O$16,0)),"") -> [Agropecuária] AM-02 – Volatilidade de preços de commodities (boi gordo, soja, milho) | H25: =IFERROR(INDEX(Aux!$K$6:$K$16,MATCH(2,Aux!$O$6:$O$16,0)),"") -> 3
B26: =IF(C26="","",3) -> 3 | C26: =IFERROR(INDEX(Aux!$I$6:$I$16,MATCH(3,Aux!$M$6:$M$16,0)),"") -> [Comércio e Serviços] OP-03 – Expansão do turismo de natureza, pesca esportiva e ecoturismo | D26: =IFERROR(INDEX(Aux!$K$6:$K$16,MATCH(3,Aux!$M$6:$M$16,0)),"") -> 3 | F26: =IF(G26="","",3) -> 3 | G26: =IFERROR(INDEX(Aux!$I$6:$I$16,MATCH(3,Aux!$O$6:$O$16,0)),"") -> [Agropecuária] AM-03 – Exigências ambientais de mercados importadores e barreiras ligadas a desmatamento (ex.: EUDR) | H26: =IFERROR(INDEX(Aux!$K$6:$K$16,MATCH(3,Aux!$O$6:$O$16,0)),"") -> 3
B27: =IF(C27="","",4) -> 4 | C27: =IFERROR(INDEX(Aux!$I$6:$I$16,MATCH(4,Aux!$M$6:$M$16,0)),"") -> [Indústria] OP-04 – Agroindustrialização e verticalização (frigoríficos, laticínios, sucroenergético) | D27: =IFERROR(INDEX(Aux!$K$6:$K$16,MATCH(4,Aux!$M$6:$M$16,0)),"") -> 2 | F27: =IF(G27="","",4) -> 4 | G27: =IFERROR(INDEX(Aux!$I$6:$I$16,MATCH(4,Aux!$O$6:$O$16,0)),"") -> [Estrutura Econômica e Fiscal] AM-04 – Transição da Reforma Tributária (IBS/CBS) e efeitos sobre a repartição de receitas municipais | H27: =IFERROR(INDEX(Aux!$K$6:$K$16,MATCH(4,Aux!$O$6:$O$16,0)),"") -> 2
B28: =IF(C28="","",5) -> 5 | C28: =IFERROR(INDEX(Aux!$I$6:$I$16,MATCH(5,Aux!$M$6:$M$16,0)),"") -> [Estrutura Econômica e Fiscal] OP-05 – Corredores logísticos (rodovias federais, ferrovia, hidrovia do Paraguai) | D28: =IFERROR(INDEX(Aux!$K$6:$K$16,MATCH(5,Aux!$M$6:$M$16,0)),"") -> 3 | F28: =IF(G28="","",5) | G28: =IFERROR(INDEX(Aux!$I$6:$I$16,MATCH(5,Aux!$O$6:$O$16,0)),"") | H28: =IFERROR(INDEX(Aux!$K$6:$K$16,MATCH(5,Aux!$O$6:$O$16,0)),"")
B29: =IF(C29="","",6) -> 6 | C29: =IFERROR(INDEX(Aux!$I$6:$I$16,MATCH(6,Aux!$M$6:$M$16,0)),"") -> [Estrutura Econômica e Fiscal] OP-06 – Instrumentos de fomento e financiamento (FCO, crédito rural, PSA, mercado de carbono) | D29: =IFERROR(INDEX(Aux!$K$6:$K$16,MATCH(6,Aux!$M$6:$M$16,0)),"") -> 3 | F29: =IF(G29="","",6) | G29: =IFERROR(INDEX(Aux!$I$6:$I$16,MATCH(6,Aux!$O$6:$O$16,0)),"") | H29: =IFERROR(INDEX(Aux!$K$6:$K$16,MATCH(6,Aux!$O$6:$O$16,0)),"")
B30: =IF(C30="","",7) | C30: =IFERROR(INDEX(Aux!$I$6:$I$16,MATCH(7,Aux!$M$6:$M$16,0)),"") | D30: =IFERROR(INDEX(Aux!$K$6:$K$16,MATCH(7,Aux!$M$6:$M$16,0)),"") | F30: =IF(G30="","",7) | G30: =IFERROR(INDEX(Aux!$I$6:$I$16,MATCH(7,Aux!$O$6:$O$16,0)),"") | H30: =IFERROR(INDEX(Aux!$K$6:$K$16,MATCH(7,Aux!$O$6:$O$16,0)),"")
B31: =IF(C31="","",8) | C31: =IFERROR(INDEX(Aux!$I$6:$I$16,MATCH(8,Aux!$M$6:$M$16,0)),"") | D31: =IFERROR(INDEX(Aux!$K$6:$K$16,MATCH(8,Aux!$M$6:$M$16,0)),"") | F31: =IF(G31="","",8) | G31: =IFERROR(INDEX(Aux!$I$6:$I$16,MATCH(8,Aux!$O$6:$O$16,0)),"") | H31: =IFERROR(INDEX(Aux!$K$6:$K$16,MATCH(8,Aux!$O$6:$O$16,0)),"")
B32: =IF(C32="","",9) | C32: =IFERROR(INDEX(Aux!$I$6:$I$16,MATCH(9,Aux!$M$6:$M$16,0)),"") | D32: =IFERROR(INDEX(Aux!$K$6:$K$16,MATCH(9,Aux!$M$6:$M$16,0)),"") | F32: =IF(G32="","",9) | G32: =IFERROR(INDEX(Aux!$I$6:$I$16,MATCH(9,Aux!$O$6:$O$16,0)),"") | H32: =IFERROR(INDEX(Aux!$K$6:$K$16,MATCH(9,Aux!$O$6:$O$16,0)),"")
B33: =IF(C33="","",10) | C33: =IFERROR(INDEX(Aux!$I$6:$I$16,MATCH(10,Aux!$M$6:$M$16,0)),"") | D33: =IFERROR(INDEX(Aux!$K$6:$K$16,MATCH(10,Aux!$M$6:$M$16,0)),"") | F33: =IF(G33="","",10) | G33: =IFERROR(INDEX(Aux!$I$6:$I$16,MATCH(10,Aux!$O$6:$O$16,0)),"") | H33: =IFERROR(INDEX(Aux!$K$6:$K$16,MATCH(10,Aux!$O$6:$O$16,0)),"")
B34: =IF(C34="","",11) | C34: =IFERROR(INDEX(Aux!$I$6:$I$16,MATCH(11,Aux!$M$6:$M$16,0)),"") | D34: =IFERROR(INDEX(Aux!$K$6:$K$16,MATCH(11,Aux!$M$6:$M$16,0)),"") | F34: =IF(G34="","",11) | G34: =IFERROR(INDEX(Aux!$I$6:$I$16,MATCH(11,Aux!$O$6:$O$16,0)),"") | H34: =IFERROR(INDEX(Aux!$K$6:$K$16,MATCH(11,Aux!$O$6:$O$16,0)),"")
B35: =IF(C35="","",12) | C35: =IFERROR(INDEX(Aux!$I$6:$I$16,MATCH(12,Aux!$M$6:$M$16,0)),"") | D35: =IFERROR(INDEX(Aux!$K$6:$K$16,MATCH(12,Aux!$M$6:$M$16,0)),"") | F35: =IF(G35="","",12) | G35: =IFERROR(INDEX(Aux!$I$6:$I$16,MATCH(12,Aux!$O$6:$O$16,0)),"") | H35: =IFERROR(INDEX(Aux!$K$6:$K$16,MATCH(12,Aux!$O$6:$O$16,0)),"")
C36: =IF(SUM(Aux!$L$6:$L$16)>12,"+ "&(SUM(Aux!$L$6:$L$16)-12)&" item(ns) não exibido(s) — ver abas de dados","") | G36: =IF(SUM(Aux!$N$6:$N$16)>12,"+ "&(SUM(Aux!$N$6:$N$16)-12)&" item(ns) não exibido(s) — ver abas de dados","")
B38: Forças/Fraquezas: classificação automática dos indicadores internos segundo os limiares da aba 'Indicadores (F-W)'. Oportunidades/Ameaças: fatores externos com intensidade ≥ corte definido em 'Parâmetros'.

Sheet Painel
A1: PAINEL REGIONAL — SÍNTESE DOS 13 MUNICÍPIOS
A3: Município | B3: Forças | C3: Fraquezas | D3: Neutros | E3: Sem dado | F3: Saldo interno (F − W) | G3: Oportunidades | H3: Ameaças | I3: Saldo externo (O − T)
A4: Barão de Melgaço | B4: =COUNTIF('Indicadores (F-W)'!O$6:O$21,"Força") -> 3 | C4: =COUNTIF('Indicadores (F-W)'!O$6:O$21,"Fraqueza") -> 10 | D4: =COUNTIF('Indicadores (F-W)'!O$6:O$21,"Neutro") -> 1 | E4: =COUNTBLANK('Indicadores (F-W)'!N$6:N$21) -> 2 | F4: =B4-C4 -> -7 | G4: =COUNTIFS('Fatores Externos (O-A)'!$B$6:$B$16,"Oportunidade",'Fatores Externos (O-A)'!F$6:F$16,">="&Parâmetros!$B$5) -> 3 | H4: =COUNTIFS('Fatores Externos (O-A)'!$B$6:$B$16,"Ameaça",'Fatores Externos (O-A)'!F$6:F$16,">="&Parâmetros!$B$5) -> 4 | I4: =G4-H4 -> -1
A5: Cáceres | B5: =COUNTIF('Indicadores (F-W)'!Q$6:Q$21,"Força") -> 3 | C5: =COUNTIF('Indicadores (F-W)'!Q$6:Q$21,"Fraqueza") -> 8 | D5: =COUNTIF('Indicadores (F-W)'!Q$6:Q$21,"Neutro") -> 3 | E5: =COUNTBLANK('Indicadores (F-W)'!P$6:P$21) -> 2 | F5: =B5-C5 -> -5 | G5: =COUNTIFS('Fatores Externos (O-A)'!$B$6:$B$16,"Oportunidade",'Fatores Externos (O-A)'!G$6:G$16,">="&Parâmetros!$B$5) -> 6 | H5: =COUNTIFS('Fatores Externos (O-A)'!$B$6:$B$16,"Ameaça",'Fatores Externos (O-A)'!G$6:G$16,">="&Parâmetros!$B$5) -> 4 | I5: =G5-H5 -> 2
A6: Curvelândia | B6: =COUNTIF('Indicadores (F-W)'!S$6:S$21,"Força") -> 3 | C6: =COUNTIF('Indicadores (F-W)'!S$6:S$21,"Fraqueza") -> 10 | D6: =COUNTIF('Indicadores (F-W)'!S$6:S$21,"Neutro") -> 1 | E6: =COUNTBLANK('Indicadores (F-W)'!R$6:R$21) -> 2 | F6: =B6-C6 -> -7 | G6: =COUNTIFS('Fatores Externos (O-A)'!$B$6:$B$16,"Oportunidade",'Fatores Externos (O-A)'!H$6:H$16,">="&Parâmetros!$B$5) -> 2 | H6: =COUNTIFS('Fatores Externos (O-A)'!$B$6:$B$16,"Ameaça",'Fatores Externos (O-A)'!H$6:H$16,">="&Parâmetros!$B$5) -> 3 | I6: =G6-H6 -> -1
A7: Glória D'Oeste | B7: =COUNTIF('Indicadores (F-W)'!U$6:U$21,"Força") -> 3 | C7: =COUNTIF('Indicadores (F-W)'!U$6:U$21,"Fraqueza") -> 10 | D7: =COUNTIF('Indicadores (F-W)'!U$6:U$21,"Neutro") -> 1 | E7: =COUNTBLANK('Indicadores (F-W)'!T$6:T$21) -> 2 | F7: =B7-C7 -> -7 | G7: =COUNTIFS('Fatores Externos (O-A)'!$B$6:$B$16,"Oportunidade",'Fatores Externos (O-A)'!I$6:I$16,">="&Parâmetros!$B$5) -> 2 | H7: =COUNTIFS('Fatores Externos (O-A)'!$B$6:$B$16,"Ameaça",'Fatores Externos (O-A)'!I$6:I$16,">="&Parâmetros!$B$5) -> 3 | I7: =G7-H7 -> -1
A8: Itiquira | B8: =COUNTIF('Indicadores (F-W)'!W$6:W$21,"Força") -> 7 | C8: =COUNTIF('Indicadores (F-W)'!W$6:W$21,"Fraqueza") -> 6 | D8: =COUNTIF('Indicadores (F-W)'!W$6:W$21,"Neutro") -> 1 | E8: =COUNTBLANK('Indicadores (F-W)'!V$6:V$21) -> 2 | F8: =B8-C8 -> 1 | G8: =COUNTIFS('Fatores Externos (O-A)'!$B$6:$B$16,"Oportunidade",'Fatores Externos (O-A)'!J$6:J$16,">="&Parâmetros!$B$5) -> 5 | H8: =COUNTIFS('Fatores Externos (O-A)'!$B$6:$B$16,"Ameaça",'Fatores Externos (O-A)'!J$6:J$16,">="&Parâmetros!$B$5) -> 5 | I8: =G8-H8 -> 0
A9: Juscimeira | B9: =COUNTIF('Indicadores (F-W)'!Y$6:Y$21,"Força") -> 3 | C9: =COUNTIF('Indicadores (F-W)'!Y$6:Y$21,"Fraqueza") -> 7 | D9: =COUNTIF('Indicadores (F-W)'!Y$6:Y$21,"Neutro") -> 4 | E9: =COUNTBLANK('Indicadores (F-W)'!X$6:X$21) -> 2 | F9: =B9-C9 -> -4 | G9: =COUNTIFS('Fatores Externos (O-A)'!$B$6:$B$16,"Oportunidade",'Fatores Externos (O-A)'!K$6:K$16,">="&Parâmetros!$B$5) -> 5 | H9: =COUNTIFS('Fatores Externos (O-A)'!$B$6:$B$16,"Ameaça",'Fatores Externos (O-A)'!K$6:K$16,">="&Parâmetros!$B$5) -> 4 | I9: =G9-H9 -> 1
A10: Lambari D'Oeste | B10: =COUNTIF('Indicadores (F-W)'!AA$6:AA$21,"Força") -> 2 | C10: =COUNTIF('Indicadores (F-W)'!AA$6:AA$21,"Fraqueza") -> 9 | D10: =COUNTIF('Indicadores (F-W)'!AA$6:AA$21,"Neutro") -> 3 | E10: =COUNTBLANK('Indicadores (F-W)'!Z$6:Z$21) -> 2 | F10: =B10-C10 -> -7 | G10: =COUNTIFS('Fatores Externos (O-A)'!$B$6:$B$16,"Oportunidade",'Fatores Externos (O-A)'!L$6:L$16,">="&Parâmetros!$B$5) -> 3 | H10: =COUNTIFS('Fatores Externos (O-A)'!$B$6:$B$16,"Ameaça",'Fatores Externos (O-A)'!L$6:L$16,">="&Parâmetros!$B$5) -> 4 | I10: =G10-H10 -> -1
A11: Mirassol D'Oeste | B11: =COUNTIF('Indicadores (F-W)'!AC$6:AC$21,"Força") -> 2 | C11: =COUNTIF('Indicadores (F-W)'!AC$6:AC$21,"Fraqueza") -> 8 | D11: =COUNTIF('Indicadores (F-W)'!AC$6:AC$21,"Neutro") -> 4 | E11: =COUNTBLANK('Indicadores (F-W)'!AB$6:AB$21) -> 2 | F11: =B11-C11 -> -6 | G11: =COUNTIFS('Fatores Externos (O-A)'!$B$6:$B$16,"Oportunidade",'Fatores Externos (O-A)'!M$6:M$16,">="&Parâmetros!$B$5) -> 4 | H11: =COUNTIFS('Fatores Externos (O-A)'!$B$6:$B$16,"Ameaça",'Fatores Externos (O-A)'!M$6:M$16,">="&Parâmetros!$B$5) -> 1 | I11: =G11-H11 -> 3
A12: Nossa Senhora do Livramento | B12: =COUNTIF('Indicadores (F-W)'!AE$6:AE$21,"Força") -> 4 | C12: =COUNTIF('Indicadores (F-W)'!AE$6:AE$21,"Fraqueza") -> 8 | D12: =COUNTIF('Indicadores (F-W)'!AE$6:AE$21,"Neutro") -> 2 | E12: =COUNTBLANK('Indicadores (F-W)'!AD$6:AD$21) -> 2 | F12: =B12-C12 -> -4 | G12: =COUNTIFS('Fatores Externos (O-A)'!$B$6:$B$16,"Oportunidade",'Fatores Externos (O-A)'!N$6:N$16,">="&Parâmetros!$B$5) -> 4 | H12: =COUNTIFS('Fatores Externos (O-A)'!$B$6:$B$16,"Ameaça",'Fatores Externos (O-A)'!N$6:N$16,">="&Parâmetros!$B$5) -> 3 | I12: =G12-H12 -> 1
A13: Poconé | B13: =COUNTIF('Indicadores (F-W)'!AG$6:AG$21,"Força") -> 1 | C13: =COUNTIF('Indicadores (F-W)'!AG$6:AG$21,"Fraqueza") -> 11 | D13: =COUNTIF('Indicadores (F-W)'!AG$6:AG$21,"Neutro") -> 2 | E13: =COUNTBLANK('Indicadores (F-W)'!AF$6:AF$21) -> 2 | F13: =B13-C13 -> -10 | G13: =COUNTIFS('Fatores Externos (O-A)'!$B$6:$B$16,"Oportunidade",'Fatores Externos (O-A)'!O$6:O$16,">="&Parâmetros!$B$5) -> 4 | H13: =COUNTIFS('Fatores Externos (O-A)'!$B$6:$B$16,"Ameaça",'Fatores Externos (O-A)'!O$6:O$16,">="&Parâmetros!$B$5) -> 4 | I13: =G13-H13 -> 0
A14: Porto Esperidião | B14: =COUNTIF('Indicadores (F-W)'!AI$6:AI$21,"Força") -> 3 | C14: =COUNTIF('Indicadores (F-W)'!AI$6:AI$21,"Fraqueza") -> 9 | D14: =COUNTIF('Indicadores (F-W)'!AI$6:AI$21,"Neutro") -> 2 | E14: =COUNTBLANK('Indicadores (F-W)'!AH$6:AH$21) -> 2 | F14: =B14-C14 -> -6 | G14: =COUNTIFS('Fatores Externos (O-A)'!$B$6:$B$16,"Oportunidade",'Fatores Externos (O-A)'!P$6:P$16,">="&Parâmetros!$B$5) -> 3 | H14: =COUNTIFS('Fatores Externos (O-A)'!$B$6:$B$16,"Ameaça",'Fatores Externos (O-A)'!P$6:P$16,">="&Parâmetros!$B$5) -> 4 | I14: =G14-H14 -> -1
A15: Rondonópolis | B15: =COUNTIF('Indicadores (F-W)'!AK$6:AK$21,"Força") -> 4 | C15: =COUNTIF('Indicadores (F-W)'!AK$6:AK$21,"Fraqueza") -> 3 | D15: =COUNTIF('Indicadores (F-W)'!AK$6:AK$21,"Neutro") -> 7 | E15: =COUNTBLANK('Indicadores (F-W)'!AJ$6:AJ$21) -> 2 | F15: =B15-C15 -> 1 | G15: =COUNTIFS('Fatores Externos (O-A)'!$B$6:$B$16,"Oportunidade",'Fatores Externos (O-A)'!Q$6:Q$16,">="&Parâmetros!$B$5) -> 5 | H15: =COUNTIFS('Fatores Externos (O-A)'!$B$6:$B$16,"Ameaça",'Fatores Externos (O-A)'!Q$6:Q$16,">="&Parâmetros!$B$5) -> 3 | I15: =G15-H15 -> 2
A16: Santo Antônio do Leverger | B16: =COUNTIF('Indicadores (F-W)'!AM$6:AM$21,"Força") -> 2 | C16: =COUNTIF('Indicadores (F-W)'!AM$6:AM$21,"Fraqueza") -> 11 | D16: =COUNTIF('Indicadores (F-W)'!AM$6:AM$21,"Neutro") -> 1 | E16: =COUNTBLANK('Indicadores (F-W)'!AL$6:AL$21) -> 2 | F16: =B16-C16 -> -9 | G16: =COUNTIFS('Fatores Externos (O-A)'!$B$6:$B$16,"Oportunidade",'Fatores Externos (O-A)'!R$6:R$16,">="&Parâmetros!$B$5) -> 5 | H16: =COUNTIFS('Fatores Externos (O-A)'!$B$6:$B$16,"Ameaça",'Fatores Externos (O-A)'!R$6:R$16,">="&Parâmetros!$B$5) -> 5 | I16: =G16-H16 -> 0
A19: Frequência regional dos indicadores internos (nº de municípios)
A20: Cód. | B20: Indicador | C20: Força | D20: Neutro | E20: Fraqueza | F20: Sem dado | G20: Leitura regional
A21: ='Indicadores (F-W)'!A6 -> AGR-01 | B21: ='Indicadores (F-W)'!C6 -> Quociente locacional do VAB agropecuário (base MT) | C21: =COUNTIF('Indicadores (F-W)'!$N6:$AM6,"Força") -> 6 | D21: =COUNTIF('Indicadores (F-W)'!$N6:$AM6,"Neutro") -> 2 | E21: =COUNTIF('Indicadores (F-W)'!$N6:$AM6,"Fraqueza") -> 5 | F21: =13-C21-D21-E21 -> 0 | G21: =IF(C21+D21+E21=0,"sem dados",IF(C21>=13/2,"Força regional",IF(E21>=13/2,"Fraqueza regional","Heterogêneo"))) -> Heterogêneo
A22: ='Indicadores (F-W)'!A7 -> AGR-02 | B22: ='Indicadores (F-W)'!C7 -> Valor da produção das lavouras por área colhida | C22: =COUNTIF('Indicadores (F-W)'!$N7:$AM7,"Força") -> 6 | D22: =COUNTIF('Indicadores (F-W)'!$N7:$AM7,"Neutro") -> 6 | E22: =COUNTIF('Indicadores (F-W)'!$N7:$AM7,"Fraqueza") -> 1 | F22: =13-C22-D22-E22 -> 0 | G22: =IF(C22+D22+E22=0,"sem dados",IF(C22>=13/2,"Força regional",IF(E22>=13/2,"Fraqueza regional","Heterogêneo"))) -> Heterogêneo
A23: ='Indicadores (F-W)'!A8 -> AGR-03 | B23: ='Indicadores (F-W)'!C8 -> Variação do efetivo bovino em 5 anos | C23: =COUNTIF('Indicadores (F-W)'!$N8:$AM8,"Força") -> 6 | D23: =COUNTIF('Indicadores (F-W)'!$N8:$AM8,"Neutro") -> 4 | E23: =COUNTIF('Indicadores (F-W)'!$N8:$AM8,"Fraqueza") -> 3 | F23: =13-C23-D23-E23 -> 0 | G23: =IF(C23+D23+E23=0,"sem dados",IF(C23>=13/2,"Força regional",IF(E23>=13/2,"Fraqueza regional","Heterogêneo"))) -> Heterogêneo
A24: ='Indicadores (F-W)'!A9 -> AGR-04 | B24: ='Indicadores (F-W)'!C9 -> Estabelecimentos agropecuários que receberam assistência técnica | C24: =COUNTIF('Indicadores (F-W)'!$N9:$AM9,"Força") -> 0 | D24: =COUNTIF('Indicadores (F-W)'!$N9:$AM9,"Neutro") -> 0 | E24: =COUNTIF('Indicadores (F-W)'!$N9:$AM9,"Fraqueza") -> 0 | F24: =13-C24-D24-E24 -> 13 | G24: =IF(C24+D24+E24=0,"sem dados",IF(C24>=13/2,"Força regional",IF(E24>=13/2,"Fraqueza regional","Heterogêneo"))) -> sem dados
A25: ='Indicadores (F-W)'!A10 -> AGR-05 | B25: ='Indicadores (F-W)'!C10 -> Diversificação agrícola (1 − HHI do valor da produção das lavouras) | C25: =COUNTIF('Indicadores (F-W)'!$N10:$AM10,"Força") -> 0 | D25: =COUNTIF('Indicadores (F-W)'!$N10:$AM10,"Neutro") -> 0 | E25: =COUNTIF('Indicadores (F-W)'!$N10:$AM10,"Fraqueza") -> 0 | F25: =13-C25-D25-E25 -> 13 | G25: =IF(C25+D25+E25=0,"sem dados",IF(C25>=13/2,"Força regional",IF(E25>=13/2,"Fraqueza regional","Heterogêneo"))) -> sem dados
A26: ='Indicadores (F-W)'!A11 -> IND-01 | B26: ='Indicadores (F-W)'!C11 -> Quociente locacional do VAB industrial (base MT) | C26: =COUNTIF('Indicadores (F-W)'!$N11:$AM11,"Força") -> 4 | D26: =COUNTIF('Indicadores (F-W)'!$N11:$AM11,"Neutro") -> 3 | E26: =COUNTIF('Indicadores (F-W)'!$N11:$AM11,"Fraqueza") -> 6 | F26: =13-C26-D26-E26 -> 0 | G26: =IF(C26+D26+E26=0,"sem dados",IF(C26>=13/2,"Força regional",IF(E26>=13/2,"Fraqueza regional","Heterogêneo"))) -> Heterogêneo
A27: ='Indicadores (F-W)'!A12 -> IND-02 | B27: ='Indicadores (F-W)'!C12 -> Variação do emprego formal na indústria em 5 anos | C27: =COUNTIF('Indicadores (F-W)'!$N12:$AM12,"Força") -> 8 | D27: =COUNTIF('Indicadores (F-W)'!$N12:$AM12,"Neutro") -> 0 | E27: =COUNTIF('Indicadores (F-W)'!$N12:$AM12,"Fraqueza") -> 5 | F27: =13-C27-D27-E27 -> 0 | G27: =IF(C27+D27+E27=0,"sem dados",IF(C27>=13/2,"Força regional",IF(E27>=13/2,"Fraqueza regional","Heterogêneo"))) -> Força regional
A28: ='Indicadores (F-W)'!A13 -> IND-03 | B28: ='Indicadores (F-W)'!C13 -> Remuneração média do emprego formal industrial | C28: =COUNTIF('Indicadores (F-W)'!$N13:$AM13,"Força") -> 0 | D28: =COUNTIF('Indicadores (F-W)'!$N13:$AM13,"Neutro") -> 5 | E28: =COUNTIF('Indicadores (F-W)'!$N13:$AM13,"Fraqueza") -> 8 | F28: =13-C28-D28-E28 -> 0 | G28: =IF(C28+D28+E28=0,"sem dados",IF(C28>=13/2,"Força regional",IF(E28>=13/2,"Fraqueza regional","Heterogêneo"))) -> Fraqueza regional
A29: ='Indicadores (F-W)'!A14 -> CS-01 | B29: ='Indicadores (F-W)'!C14 -> Quociente locacional do VAB de serviços, exceto adm. pública (base MT) | C29: =COUNTIF('Indicadores (F-W)'!$N14:$AM14,"Força") -> 2 | D29: =COUNTIF('Indicadores (F-W)'!$N14:$AM14,"Neutro") -> 2 | E29: =COUNTIF('Indicadores (F-W)'!$N14:$AM14,"Fraqueza") -> 9 | F29: =13-C29-D29-E29 -> 0 | G29: =IF(C29+D29+E29=0,"sem dados",IF(C29>=13/2,"Força regional",IF(E29>=13/2,"Fraqueza regional","Heterogêneo"))) -> Fraqueza regional
A30: ='Indicadores (F-W)'!A15 -> CS-02 | B30: ='Indicadores (F-W)'!C15 -> Variação do emprego formal em comércio e serviços em 5 anos | C30: =COUNTIF('Indicadores (F-W)'!$N15:$AM15,"Força") -> 3 | D30: =COUNTIF('Indicadores (F-W)'!$N15:$AM15,"Neutro") -> 1 | E30: =COUNTIF('Indicadores (F-W)'!$N15:$AM15,"Fraqueza") -> 9 | F30: =13-C30-D30-E30 -> 0 | G30: =IF(C30+D30+E30=0,"sem dados",IF(C30>=13/2,"Força regional",IF(E30>=13/2,"Fraqueza regional","Heterogêneo"))) -> Fraqueza regional
A31: ='Indicadores (F-W)'!A16 -> CS-03 | B31: ='Indicadores (F-W)'!C16 -> Empresas e outras organizações ativas por mil habitantes | C31: =COUNTIF('Indicadores (F-W)'!$N16:$AM16,"Força") -> 1 | D31: =COUNTIF('Indicadores (F-W)'!$N16:$AM16,"Neutro") -> 1 | E31: =COUNTIF('Indicadores (F-W)'!$N16:$AM16,"Fraqueza") -> 11 | F31: =13-C31-D31-E31 -> 0 | G31: =IF(C31+D31+E31=0,"sem dados",IF(C31>=13/2,"Força regional",IF(E31>=13/2,"Fraqueza regional","Heterogêneo"))) -> Fraqueza regional
A32: ='Indicadores (F-W)'!A17 -> EST-01 | B32: ='Indicadores (F-W)'!C17 -> PIB per capita | C32: =COUNTIF('Indicadores (F-W)'!$N17:$AM17,"Força") -> 1 | D32: =COUNTIF('Indicadores (F-W)'!$N17:$AM17,"Neutro") -> 1 | E32: =COUNTIF('Indicadores (F-W)'!$N17:$AM17,"Fraqueza") -> 11 | F32: =13-C32-D32-E32 -> 0 | G32: =IF(C32+D32+E32=0,"sem dados",IF(C32>=13/2,"Força regional",IF(E32>=13/2,"Fraqueza regional","Heterogêneo"))) -> Fraqueza regional
... A36: ='Indicadores (F-W)'!A21 -> EST-05 | B36: ='Indicadores (F-W)'!C21 -> Receitas próprias / receita corrente | C36: =COUNTIF('Indicadores (F-W)'!$N21:$AM21,"Força") -> 1 | D36: =COUNTIF('Indicadores (F-W)'!$N21:$AM21,"Neutro") -> 1 | E36: =COUNTIF('Indicadores (F-W)'!$N21:$AM21,"Fraqueza") -> 11 | F36: =13-C36-D36-E36 -> 0 | G36: =IF(C36+D36+E36=0,"sem dados",IF(C36>=13/2,"Força regional",IF(E36>=13/2,"Fraqueza regional","Heterogêneo"))) -> Fraqueza regional
A38: Frequência regional dos fatores externos (nº de municípios com intensidade ≥ corte)
A39: Cód. | B39: Fator externo | C39: Tipo | D39: Nº municípios | E39: Intensidade média
A40: ='Fatores Externos (O-A)'!A6 -> OP-01 | B40: ='Fatores Externos (O-A)'!D6 -> Demanda externa por carne bovina e proteína animal | C40: ='Fatores Externos (O-A)'!B6 -> Oportunidade | D40: =COUNTIF('Fatores Externos (O-A)'!$F6:$R6,">="&Parâmetros!$B$5) -> 12 | E40: =IF(COUNT('Fatores Externos (O-A)'!$F6:$R6)=0,"",AVERAGE('Fatores Externos (O-A)'!$F6:$R6)) -> 2.1538462
A41: ='Fatores Externos (O-A)'!A7 -> OP-02 | B41: ='Fatores Externos (O-A)'!D7 -> Mercados para produtos diferenciados e certificados (carne sustentável/orgânica, origem Pantanal) | C41: ='Fatores Externos (O-A)'!B7 -> Oportunidade | D41: =COUNTIF('Fatores Externos (O-A)'!$F7:$R7,">="&Parâmetros!$B$5) -> 6 | E41: =IF(COUNT('Fatores Externos (O-A)'!$F7:$R7)=0,"",AVERAGE('Fatores Externos (O-A)'!$F7:$R7)) -> 1.7692308
A42: ='Fatores Externos (O-A)'!A8 -> OP-03 | B42: ='Fatores Externos (O-A)'!D8 -> Expansão do turismo de natureza, pesca esportiva e ecoturismo | C42: ='Fatores Externos (O-A)'!B8 -> Oportunidade | D42: =COUNTIF('Fatores Externos (O-A)'!$F8:$R8,">="&Parâmetros!$B$5) -> 6 | E42: =IF(COUNT('Fatores Externos (O-A)'!$F8:$R8)=0,"",AVERAGE('Fatores Externos (O-A)'!$F8:$R8)) -> 1.6153846
A43: ='Fatores Externos (O-A)'!A9 -> OP-04 | B43: ='Fatores Externos (O-A)'!D9 -> Agroindustrialização e verticalização (frigoríficos, laticínios, sucroenergético) | C43: ='Fatores Externos (O-A)'!B9 -> Oportunidade | D43: =COUNTIF('Fatores Externos (O-A)'!$F9:$R9,">="&Parâmetros!$B$5) -> 6 | E43: =IF(COUNT('Fatores Externos (O-A)'!$F9:$R9)=0,"",AVERAGE('Fatores Externos (O-A)'!$F9:$R9)) -> 1.6153846
A44: ='Fatores Externos (O-A)'!A10 -> OP-05 | B44: ='Fatores Externos (O-A)'!D10 -> Corredores logísticos (rodovias federais, ferrovia, hidrovia do Paraguai) | C44: ='Fatores Externos (O-A)'!B10 -> Oportunidade | D44: =COUNTIF('Fatores Externos (O-A)'!$F10:$R10,">="&Parâmetros!$B$5) -> 8 | E44: =IF(COUNT('Fatores Externos (O-A)'!$F10:$R10)=0,"",AVERAGE('Fatores Externos (O-A)'!$F10:$R10)) -> 1.7692308
A45: ='Fatores Externos (O-A)'!A11 -> OP-06 | B45: ='Fatores Externos (O-A)'!D11 -> Instrumentos de fomento e financiamento (FCO, crédito rural, PSA, mercado de carbono) | C45: ='Fatores Externos (O-A)'!B11 -> Oportunidade | D45: =COUNTIF('Fatores Externos (O-A)'!$F11:$R11,">="&Parâmetros!$B$5) -> 13 | E45: =IF(COUNT('Fatores Externos (O-A)'!$F11:$R11)=0,"",AVERAGE('Fatores Externos (O-A)'!$F11:$R11)) -> 2.3076923
A46: ='Fatores Externos (O-A)'!A12 -> AM-01 | B46: ='Fatores Externos (O-A)'!D12 -> Eventos climáticos extremos: secas prolongadas e incêndios no Pantanal | C46: ='Fatores Externos (O-A)'!B12 -> Ameaça | D46: =COUNTIF('Fatores Externos (O-A)'!$F12:$R12,">="&Parâmetros!$B$5) -> 7 | E46: =IF(COUNT('Fatores Externos (O-A)'!$F12:$R12)=0,"",AVERAGE('Fatores Externos (O-A)'!$F12:$R12)) -> 1.8461538
A47: ='Fatores Externos (O-A)'!A13 -> AM-02 | B47: ='Fatores Externos (O-A)'!D13 -> Volatilidade de preços de commodities (boi gordo, soja, milho) | C47: ='Fatores Externos (O-A)'!B13 -> Ameaça | D47: =COUNTIF('Fatores Externos (O-A)'!$F13:$R13,">="&Parâmetros!$B$5) -> 12 | E47: =IF(COUNT('Fatores Externos (O-A)'!$F13:$R13)=0,"",AVERAGE('Fatores Externos (O-A)'!$F13:$R13)) -> 2.2307692
A48: ='Fatores Externos (O-A)'!A14 -> AM-03 | B48: ='Fatores Externos (O-A)'!D14 -> Exigências ambientais de mercados importadores e barreiras ligadas a desmatamento (ex.: EUDR) | C48: ='Fatores Externos (O-A)'!B14 -> Ameaça | D48: =COUNTIF('Fatores Externos (O-A)'!$F14:$R14,">="&Parâmetros!$B$5) -> 11 | E48: =IF(COUNT('Fatores Externos (O-A)'!$F14:$R14)=0,"",AVERAGE('Fatores Externos (O-A)'!$F14:$R14)) -> 2.1538462
A49: ='Fatores Externos (O-A)'!A15 -> AM-04 | B49: ='Fatores Externos (O-A)'!D15 -> Transição da Reforma Tributária (IBS/CBS) e efeitos sobre a repartição de receitas municipais | C49: ='Fatores Externos (O-A)'!B15 -> Ameaça | D49: =COUNTIF('Fatores Externos (O-A)'!$F15:$R15,">="&Parâmetros!$B$5) -> 7 | E49: =IF(COUNT('Fatores Externos (O-A)'!$F15:$R15)=0,"",AVERAGE('Fatores Externos (O-A)'!$F15:$R15)) -> 1.6923077
A50: ='Fatores Externos (O-A)'!A16 -> AM-05 | B50: ='Fatores Externos (O-A)'!D16 -> Polarização regional por centros maiores (evasão de consumo, serviços e mão de obra) | C50: ='Fatores Externos (O-A)'!B16 -> Ameaça | D50: =COUNTIF('Fatores Externos (O-A)'!$F16:$R16,">="&Parâmetros!$B$5) -> 10 | E50: =IF(COUNT('Fatores Externos (O-A)'!$F16:$R16)=0,"",AVERAGE('Fatores Externos (O-A)'!$F16:$R16)) -> 2.1538462
A52: Leitura regional: 'Força/Fraqueza regional' quando ao menos metade dos 13 municípios apresenta a classificação. Recomenda-se repetir a leitura sem Rondonópolis.

Sheet Ranking Locacional
A1: RANKING LOCACIONAL — ESPECIALIZAÇÃO E DIVERSIFICAÇÃO PRODUTIVA (VAB 2021, base MT)
A2: Calculado a partir dos QLs e da participação da administração pública na aba 'Indicadores (F-W)'. Atualiza automaticamente quando esses dados mudarem.
A4: Participação setorial de MT no VAB total (2021)
A5: Agropecuária | B5: 0.379769 | C5: Fonte: IBGE, SIDRA Tabela 5938 — soma dos 141 municípios de MT (ver 'Fontes e Notas').
A6: Indústria | B6: 0.152977
A7: Serviços (exceto adm. pública) | B7: 0.348365
A8: Administração pública | B8: 0.118888
E10: Participação no VAB municipal
A11: Município | B11: QL agropecuária | C11: QL indústria | D11: QL serviços | E11: Agropecuária | F11: Indústria | G11: Serviços | H11: Adm. pública | I11: Soma (conferência) | J11: Coef. de especialização (0–1) | K11: Posição especialização | L11: HHI setorial | M11: Índice de diversificação (0–1) | N11: Posição diversificação | O11: Setor dominante | P11: Part. do setor dominante | Q11: Posição QL agro | R11: Posição QL indústria | S11: Posição QL serviços
A12: Barão de Melgaço | B12: ='Indicadores (F-W)'!N6 -> 0.9631 | C12: ='Indicadores (F-W)'!N11 -> 0.169 | D12: ='Indicadores (F-W)'!N14 -> 0.4274 | E12: =B12*$B$5 -> 0.36575552 | F12: =C12*$B$6 -> 0.025853113 | G12: =D12*$B$7 -> 0.1488912 | H12: ='Indicadores (F-W)'!N18/100 -> 0.4595 | I12: =SUM(E12:H12) -> 0.99999984 | J12: =0.5*(ABS(E12-$B$5)+ABS(F12-$B$6)+ABS(G12-$B$7)+ABS(H12-$B$8)) -> 0.34061158 | K12: =RANK(J12,$J$12:$J$24,0) -> 2 | L12: =SUMSQ(E12:H12) -> 0.36775433 | M12: =1-(L12-0.25)/0.75 -> 0.84299423 | N12: =RANK(M12,$M$12:$M$24,0) -> 9 | O12: =INDEX($E$11:$H$11,MATCH(MAX(E12:H12),E12:H12,0)) -> Adm. pública | P12: =MAX(E12:H12) -> 0.4595 | Q12: =RANK(B12,$B$12:$B$24,0) -> 8 | R12: =RANK(C12,$C$12:$C$24,0) -> 13 | S12: =RANK(D12,$D$12:$D$24,0) -> 10 | V12: =B12-ROW()*0.000000001 -> 0.96309999 | W12: =C12-ROW()*0.000000001 -> 0.16899999 | X12: =D12-ROW()*0.000000001 -> 0.42739999 | Y12: =J12-ROW()*0.000000001 -> 0.34061157 | Z12: =M12-ROW()*0.000000001 -> 0.84299422
A13: Cáceres | B13: ='Indicadores (F-W)'!P6 -> 0.3713 | C13: ='Indicadores (F-W)'!P11 -> 0.6374 | D13: ='Indicadores (F-W)'!P14 -> 1.3013 | E13: =B13*$B$5 -> 0.14100823 | F13: =C13*$B$6 -> 0.09750754 | G13: =D13*$B$7 -> 0.45332737 | H13: ='Indicadores (F-W)'!P18/100 -> 0.3082 | I13: =SUM(E13:H13) -> 1.0000431 | J13: =0.5*(ABS(E13-$B$5)+ABS(F13-$B$6)+ABS(G13-$B$7)+ABS(H13-$B$8)) -> 0.2942523 | K13: =RANK(J13,$J$12:$J$24,0) -> 5 | L13: =SUMSQ(E13:H13) -> 0.32988399 | M13: =1-(L13-0.25)/0.75 -> 0.89348801 | N13: =RANK(M13,$M$12:$M$24,0) -> 5 | O13: =INDEX($E$11:$H$11,MATCH(MAX(E13:H13),E13:H13,0)) -> Serviços | P13: =MAX(E13:H13) -> 0.45332737 | Q13: =RANK(B13,$B$12:$B$24,0) -> 12 | R13: =RANK(C13,$C$12:$C$24,0) -> 8 | S13: =RANK(D13,$D$12:$D$24,0) -> 2 | V13: =B13-ROW()*0.000000001 -> 0.37129999 | W13: =C13-ROW()*0.000000001 -> 0.63739999 | X13: =D13-ROW()*0.000000001 -> 1.3013 | Y13: =J13-ROW()*0.000000001 -> 0.29425229 | Z13: =M13-ROW()*0.000000001 -> 0.893488
A14: Curvelândia | B14: ='Indicadores (F-W)'!R6 -> 1.2022 | C14: ='Indicadores (F-W)'!R11 -> 0.4717 | D14: ='Indicadores (F-W)'!R14 -> 0.5029 | E14: =B14*$B$5 -> 0.45655829 | F14: =C14*$B$6 -> 0.072159251 | G14: =D14*$B$7 -> 0.17519276 | H14: ='Indicadores (F-W)'!R18/100 -> 0.2961 | I14: =SUM(E14:H14) -> 1.0000103 | J14: =0.5*(ABS(E14-$B$5)+ABS(F14-$B$6)+ABS(G14-$B$7)+ABS(H14-$B$8)) -> 0.25399564 | K14: =RANK(J14,$J$12:$J$24,0) -> 8 | L14: =SUMSQ(E14:H14) -> 0.33202014 | M14: =1-(L14-0.25)/0.75 -> 0.89063981 | N14: =RANK(M14,$M$12:$M$24,0) -> 6 | O14: =INDEX($E$11:$H$11,MATCH(MAX(E14:H14),E14:H14,0)) -> Agropecuária | P14: =MAX(E14:H14) -> 0.45655829 | Q14: =RANK(B14,$B$12:$B$24,0) -> 6 | R14: =RANK(C14,$C$12:$C$24,0) -> 11 | S14: =RANK(D14,$D$12:$D$24,0) -> 7 | V14: =B14-ROW()*0.000000001 -> 1.2022 | W14: =C14-ROW()*0.000000001 -> 0.47169999 | X14: =D14-ROW()*0.000000001 -> 0.50289999 | Y14: =J14-ROW()*0.000000001 -> 0.25399563 | Z14: =M14-ROW()*0.000000001 -> 0.89063979
A15: Glória D'Oeste | B15: ='Indicadores (F-W)'!T6 -> 1.3866 | C15: ='Indicadores (F-W)'!T11 -> 0.2854 | D15: ='Indicadores (F-W)'!T14 -> 0.4636 | E15: =B15*$B$5 -> 0.5265877 | F15: =C15*$B$6 -> 0.043659636 | G15: =D15*$B$7 -> 0.16150201 | H15: ='Indicadores (F-W)'!T18/100 -> 0.2683 | I15: =SUM(E15:H15) -> 1.0000493 | J15: =0.5*(ABS(E15-$B$5)+ABS(F15-$B$6)+ABS(G15-$B$7)+ABS(H15-$B$8)) -> 0.29620552 | K15: =RANK(J15,$J$12:$J$24,0) -> 4 | L15: =SUMSQ(E15:H15) -> 0.37726856 | M15: =1-(L15-0.25)/0.75 -> 0.83030859 | N15: =RANK(M15,$M$12:$M$24,0) -> 10 | O15: =INDEX($E$11:$H$11,MATCH(MAX(E15:H15),E15:H15,0)) -> Agropecuária | P15: =MAX(E15:H15) -> 0.5265877 | Q15: =RANK(B15,$B$12:$B$24,0) -> 3 | R15: =RANK(C15,$C$12:$C$24,0) -> 12 | S15: =RANK(D15,$D$12:$D$24,0) -> 8 | V15: =B15-ROW()*0.000000001 -> 1.3866 | W15: =C15-ROW()*0.000000001 -> 0.28539999 | X15: =D15-ROW()*0.000000001 -> 0.46359998 | Y15: =J15-ROW()*0.000000001 -> 0.29620551 | Z15: =M15-ROW()*0.000000001 -> 0.83030858
A16: Itiquira | B16: ='Indicadores (F-W)'!V6 -> 1.6266 | C16: ='Indicadores (F-W)'!V11 -> 1.2891 | D16: ='Indicadores (F-W)'!V14 -> 0.3623 | E16: =B16*$B$5 -> 0.61773226 | F16: =C16*$B$6 -> 0.19720265 | G16: =D16*$B$7 -> 0.12621264 | H16: ='Indicadores (F-W)'!V18/100 -> 0.0588 | I16: =SUM(E16:H16) -> 0.99994755 | J16: =0.5*(ABS(E16-$B$5)+ABS(F16-$B$6)+ABS(G16-$B$7)+ABS(H16-$B$8)) -> 0.28221463 | K16: =RANK(J16,$J$12:$J$24,0) -> 7 | L16: =SUMSQ(E16:H16) -> 0.4398691 | M16: =1-(L16-0.25)/0.75 -> 0.74684121 | N16: =RANK(M16,$M$12:$M$24,0) -> 12 | O16: =INDEX($E$11:$H$11,MATCH(MAX(E16:H16),E16:H16,0)) -> Agropecuária | P16: =MAX(E16:H16) -> 0.61773226 | Q16: =RANK(B16,$B$12:$B$24,0) -> 2 | R16: =RANK(C16,$C$12:$C$24,0) -> 3 | S16: =RANK(D16,$D$12:$D$24,0) -> 11 | V16: =B16-ROW()*0.000000001 -> 1.6266 | W16: =C16-ROW()*0.000000001 -> 1.2891 | X16: =D16-ROW()*0.000000001 -> 0.36229998 | Y16: =J16-ROW()*0.000000001 -> 0.28221462 | Z16: =M16-ROW()*0.000000001 -> 0.74684119
A17: Juscimeira | B17: ='Indicadores (F-W)'!X6 -> 1.319 | C17: ='Indicadores (F-W)'!X11 -> 1.1671 | D17: ='Indicadores (F-W)'!X14 -> 0.4388 | E17: =B17*$B$5 -> 0.50091531 | F17: =C17*$B$6 -> 0.17853946 | G17: =D17*$B$7 -> 0.15286256 | H17: ='Indicadores (F-W)'!X18/100 -> 0.1677 | I17: =SUM(E17:H17) -> 1.0000173 | J17: =0.5*(ABS(E17-$B$5)+ABS(F17-$B$6)+ABS(G17-$B$7)+ABS(H17-$B$8)) -> 0.1955116 | K17: =RANK(J17,$J$12:$J$24,0) -> 12 | L17: =SUMSQ(E17:H17) -> 0.33428274 | M17: =1-(L17-0.25)/0.75 -> 0.88762301 | N17: =RANK(M17,$M$12:$M$24,0) -> 7 | O17: =INDEX($E$11:$H$11,MATCH(MAX(E17:H17),E17:H17,0)) -> Agropecuária | P17: =MAX(E17:H17) -> 0.50091531 | Q17: =RANK(B17,$B$12:$B$24,0) -> 5 | R17: =RANK(C17,$C$12:$C$24,0) -> 6 | S17: =RANK(D17,$D$12:$D$24,0) -> 9 | V17: =B17-ROW()*0.000000001 -> 1.319 | W17: =C17-ROW()*0.000000001 -> 1.1671 | X17: =D17-ROW()*0.000000001 -> 0.43879998 | Y17: =J17-ROW()*0.000000001 -> 0.19551159 | Z17: =M17-ROW()*0.000000001 -> 0.887623
A18: Lambari D'Oeste | B18: ='Indicadores (F-W)'!Z6 -> 1.364 | C18: ='Indicadores (F-W)'!Z11 -> 1.1956 | D18: ='Indicadores (F-W)'!Z14 -> 0.3227 | E18: =B18*$B$5 -> 0.51800492 | F18: =C18*$B$6 -> 0.1828993 | G18: =D18*$B$7 -> 0.11241739 | H18: ='Indicadores (F-W)'!Z18/100 -> 0.1867 | I18: =SUM(E18:H18) -> 1.0000216 | J18: =0.5*(ABS(E18-$B$5)+ABS(F18-$B$6)+ABS(G18-$B$7)+ABS(H18-$B$8)) -> 0.23595892 | K18: =RANK(J18,$J$12:$J$24,0) -> 10 | L18: =SUMSQ(E18:H18) -> 0.34927581 | M18: =1-(L18-0.25)/0.75 -> 0.86763226 | N18: =RANK(M18,$M$12:$M$24,0) -> 8 | O18: =INDEX($E$11:$H$11,MATCH(MAX(E18:H18),E18:H18,0)) -> Agropecuária | P18: =MAX(E18:H18) -> 0.51800492 | Q18: =RANK(B18,$B$12:$B$24,0) -> 4 | R18: =RANK(C18,$C$12:$C$24,0) -> 5 | S18: =RANK(D18,$D$12:$D$24,0) -> 13 | V18: =B18-ROW()*0.000000001 -> 1.364 | W18: =C18-ROW()*0.000000001 -> 1.1956 | X18: =D18-ROW()*0.000000001 -> 0.32269998 | Y18: =J18-ROW()*0.000000001 -> 0.2359589 | Z18: =M18-ROW()*0.000000001 -> 0.86763224
A19: Mirassol D'Oeste | B19: ='Indicadores (F-W)'!AB6 -> 0.416 | C19: ='Indicadores (F-W)'!AB11 -> 1.2112 | D19: ='Indicadores (F-W)'!AB14 -> 1.1498 | E19: =B19*$B$5 -> 0.1579839 | F19: =C19*$B$6 -> 0.18528574 | G19: =D19*$B$7 -> 0.40055008 | H19: ='Indicadores (F-W)'!AB18/100 -> 0.2562 | I19: =SUM(E19:H19) -> 1.0000197 | J19: =0.5*(ABS(E19-$B$5)+ABS(F19-$B$6)+ABS(G19-$B$7)+ABS(H19-$B$8)) -> 0.22179546 | K19: =RANK(J19,$J$12:$J$24,0) -> 11 | L19: =SUMSQ(E19:H19) -> 0.28536852 | M19: =1-(L19-0.25)/0.75 -> 0.95284197 | N19: =RANK(M19,$M$12:$M$24,0) -> 3 | O19: =INDEX($E$11:$H$11,MATCH(MAX(E19:H19),E19:H19,0)) -> Serviços | P19: =MAX(E19:H19) -> 0.40055008 | Q19: =RANK(B19,$B$12:$B$24,0) -> 11 | R19: =RANK(C19,$C$12:$C$24,0) -> 4 | S19: =RANK(D19,$D$12:$D$24,0) -> 3 | V19: =B19-ROW()*0.000000001 -> 0.41599998 | W19: =C19-ROW()*0.000000001 -> 1.2112 | X19: =D19-ROW()*0.000000001 -> 1.1498 | Y19: =J19-ROW()*0.000000001 -> 0.22179544 | Z19: =M19-ROW()*0.000000001 -> 0.95284195
A20: Nossa Senhora do Livramento | B20: ='Indicadores (F-W)'!AD6 -> 0.5183 | C20: ='Indicadores (F-W)'!AD11 -> 2.0033 | D20: ='Indicadores (F-W)'!AD14 -> 0.7089 | E20: =B20*$B$5 -> 0.19683427 | F20: =C20*$B$6 -> 0.30645882 | G20: =D20*$B$7 -> 0.24695595 | H20: ='Indicadores (F-W)'!AD18/100 -> 0.2497 | I20: =SUM(E20:H20) -> 0.99994905 | J20: =0.5*(ABS(E20-$B$5)+ABS(F20-$B$6)+ABS(G20-$B$7)+ABS(H20-$B$8)) -> 0.2843188 | K20: =RANK(J20,$J$12:$J$24,0) -> 6 | L20: =SUMSQ(E20:H20) -> 0.25599807 | M20: =1-(L20-0.25)/0.75 -> 0.99200257 | N20: =RANK(M20,$M$12:$M$24,0) -> 1 | O20: =INDEX($E$11:$H$11,MATCH(MAX(E20:H20),E20:H20,0)) -> Indústria | P20: =MAX(E20:H20) -> 0.30645882 | Q20: =RANK(B20,$B$12:$B$24,0) -> 9 | R20: =RANK(C20,$C$12:$C$24,0) -> 1 | S20: =RANK(D20,$D$12:$D$24,0) -> 5 | V20: =B20-ROW()*0.000000001 -> 0.51829998 | W20: =C20-ROW()*0.000000001 -> 2.0033 | X20: =D20-ROW()*0.000000001 -> 0.70889998 | Y20: =J20-ROW()*0.000000001 -> 0.28431878 | Z20: =M20-ROW()*0.000000001 -> 0.99200255
A21: Poconé | B21: ='Indicadores (F-W)'!AF6 -> 0.5066 | C21: ='Indicadores (F-W)'!AF11 -> 0.5947 | D21: ='Indicadores (F-W)'!AF14 -> 1.1034 | E21: =B21*$B$5 -> 0.19239098 | F21: =C21*$B$6 -> 0.090975422 | G21: =D21*$B$7 -> 0.38438594 | H21: ='Indicadores (F-W)'!AF18/100 -> 0.3323 | I21: =SUM(E21:H21) -> 1.0000523 | J21: =0.5*(ABS(E21-$B$5)+ABS(F21-$B$6)+ABS(G21-$B$7)+ABS(H21-$B$8)) -> 0.24940627 | K21: =RANK(J21,$J$12:$J$24,0) -> 9 | L21: =SUMSQ(E21:H21) -> 0.30346666 | M21: =1-(L21-0.25)/0.75 -> 0.92871112 | N21: =RANK(M21,$M$12:$M$24,0) -> 4 | O21: =INDEX($E$11:$H$11,MATCH(MAX(E21:H21),E21:H21,0)) -> Serviços | P21: =MAX(E21:H21) -> 0.38438594 | Q21: =RANK(B21,$B$12:$B$24,0) -> 10 | R21: =RANK(C21,$C$12:$C$24,0) -> 9 | S21: =RANK(D21,$D$12:$D$24,0) -> 4 | V21: =B21-ROW()*0.000000001 -> 0.50659998 | W21: =C21-ROW()*0.000000001 -> 0.59469998 | X21: =D21-ROW()*0.000000001 -> 1.1034 | Y21: =J21-ROW()*0.000000001 -> 0.24940625 | Z21: =M21-ROW()*0.000000001 -> 0.9287111
A22: Porto Esperidião | B22: ='Indicadores (F-W)'!AH6 -> 1.0048 | C22: ='Indicadores (F-W)'!AH11 -> 1.0107 | D22: ='Indicadores (F-W)'!AH14 -> 0.505 | E22: =B22*$B$5 -> 0.38159189 | F22: =C22*$B$6 -> 0.15461385 | G22: =D22*$B$7 -> 0.17592432 | H22: ='Indicadores (F-W)'!AH18/100 -> 0.2879 | I22: =SUM(E22:H22) -> 1.0000301 | J22: =0.5*(ABS(E22-$B$5)+ABS(F22-$B$6)+ABS(G22-$B$7)+ABS(H22-$B$8)) -> 0.17245621 | K22: =RANK(J22,$J$12:$J$24,0) -> 13 | L22: =SUMSQ(E22:H22) -> 0.28335359 | M22: =1-(L22-0.25)/0.75 -> 0.95552854 | N22: =RANK(M22,$M$12:$M$24,0) -> 2 | O22: =INDEX($E$11:$H$11,MATCH(MAX(E22:H22),E22:H22,0)) -> Agropecuária | P22: =MAX(E22:H22) -> 0.38159189 | Q22: =RANK(B22,$B$12:$B$24,0) -> 7 | R22: =RANK(C22,$C$12:$C$24,0) -> 7 | S22: =RANK(D22,$D$12:$D$24,0) -> 6 | V22: =B22-ROW()*0.000000001 -> 1.0048 | W22: =C22-ROW()*0.000000001 -> 1.0107 | X22: =D22-ROW()*0.000000001 -> 0.50499998 | Y22: =J22-ROW()*0.000000001 -> 0.17245619 | Z22: =M22-ROW()*0.000000001 -> 0.95552852
A23: Rondonópolis | B23: ='Indicadores (F-W)'!AJ6 -> 0.1067 | C23: ='Indicadores (F-W)'!AJ11 -> 1.8691 | D23: ='Indicadores (F-W)'!AJ14 -> 1.5988 | E23: =B23*$B$5 -> 0.040521352 | F23: =C23*$B$6 -> 0.28592931 | G23: =D23*$B$7 -> 0.55696596 | H23: ='Indicadores (F-W)'!AJ18/100 -> 0.1166 | I23: =SUM(E23:H23) -> 1.0000166 | J23: =0.5*(ABS(E23-$B$5)+ABS(F23-$B$6)+ABS(G23-$B$7)+ABS(H23-$B$8)) -> 0.34154446 | K23: =RANK(J23,$J$12:$J$24,0) -> 1 | L23: =SUMSQ(E23:H23) -> 0.40720419 | M23: =1-(L23-0.25)/0.75 -> 0.79039441 | N23: =RANK(M23,$M$12:$M$24,0) -> 11 | O23: =INDEX($E$11:$H$11,MATCH(MAX(E23:H23),E23:H23,0)) -> Serviços | P23: =MAX(E23:H23) -> 0.55696596 | Q23: =RANK(B23,$B$12:$B$24,0) -> 13 | R23: =RANK(C23,$C$12:$C$24,0) -> 2 | S23: =RANK(D23,$D$12:$D$24,0) -> 1 | V23: =B23-ROW()*0.000000001 -> 0.10669998 | W23: =C23-ROW()*0.000000001 -> 1.8691 | X23: =D23-ROW()*0.000000001 -> 1.5988 | Y23: =J23-ROW()*0.000000001 -> 0.34154444 | Z23: =M23-ROW()*0.000000001 -> 0.79039439
A24: Santo Antônio do Leverger | B24: ='Indicadores (F-W)'!AL6 -> 1.714 | C24: ='Indicadores (F-W)'!AL11 -> 0.4719 | D24: ='Indicadores (F-W)'!AL14 -> 0.3417 | E24: =B24*$B$5 -> 0.65092407 | F24: =C24*$B$6 -> 0.072189846 | G24: =D24*$B$7 -> 0.11903632 | H24: ='Indicadores (F-W)'!AL18/100 -> 0.1578 | I24: =SUM(E24:H24) -> 0.99995023 | J24: =0.5*(ABS(E24-$B$5)+ABS(F24-$B$6)+ABS(G24-$B$7)+ABS(H24-$B$8)) -> 0.31009145 | K24: =RANK(J24,$J$12:$J$24,0) -> 3 | L24: =SUMSQ(E24:H24) -> 0.467984 | M24: =1-(L24-0.25)/0.75 -> 0.70935467 | N24: =RANK(M24,$M$12:$M$24,0) -> 13 | O24: =INDEX($E$11:$H$11,MATCH(MAX(E24:H24),E24:H24,0)) -> Agropecuária | P24: =MAX(E24:H24) -> 0.65092407 | Q24: =RANK(B24,$B$12:$B$24,0) -> 1 | R24: =RANK(C24,$C$12:$C$24,0) -> 10 | S24: =RANK(D24,$D$12:$D$24,0) -> 12 | V24: =B24-ROW()*0.000000001 -> 1.714 | W24: =C24-ROW()*0.000000001 -> 0.47189998 | X24: =D24-ROW()*0.000000001 -> 0.34169998 | Y24: =J24-ROW()*0.000000001 -> 0.31009143 | Z24: =M24-ROW()*0.000000001 -> 0.70935464
A27: RANKING DE ESPECIALIZAÇÃO POR SETOR (ordenado pelo QL)
A28: AGROPECUÁRIA | F28: INDÚSTRIA | K28: SERVIÇOS (exceto adm. pública)
A29: Pos. | B29: Município | C29: QL | D29: Classificação | F29: Pos. | G29: Município | H29: QL | I29: Classificação | K29: Pos. | L29: Município | M29: QL | N29: Classificação
A30: 1 | B30: =INDEX($A$12:$A$24,MATCH(LARGE($V$12:$V$24,1),$V$12:$V$24,0)) -> Santo Antônio do Leverger | C30: =INDEX($B$12:$B$24,MATCH(LARGE($V$12:$V$24,1),$V$12:$V$24,0)) -> 1.714 | D30: =IF(C30>'Indicadores (F-W)'!$M$6,"Especializado",IF(C30<'Indicadores (F-W)'!$L$6,"Sub-representado","Intermediário")) -> Especializado | F30: 1 | G30: =INDEX($A$12:$A$24,MATCH(LARGE($W$12:$W$24,1),$W$12:$W$24,0)) -> Nossa Senhora do Livramento | H30: =INDEX($C$12:$C$24,MATCH(LARGE($W$12:$W$24,1),$W$12:$W$24,0)) -> 2.0033 | I30: =IF(H30>'Indicadores (F-W)'!$M$11,"Especializado",IF(H30<'Indicadores (F-W)'!$L$11,"Sub-representado","Intermediário")) -> Especializado | K30: 1 | L30: =INDEX($A$12:$A$24,MATCH(LARGE($X$12:$X$24,1),$X$12:$X$24,0)) -> Rondonópolis | M30: =INDEX($D$12:$D$24,MATCH(LARGE($X$12:$X$24,1),$X$12:$X$24,0)) -> 1.5988 | N30: =IF(M30>'Indicadores (F-W)'!$M$14,"Especializado",IF(M30<'Indicadores (F-W)'!$L$14,"Sub-representado","Intermediário")) -> Especializado
A31: 2 | B31: =INDEX($A$12:$A$24,MATCH(LARGE($V$12:$V$24,2),$V$12:$V$24,0)) -> Itiquira | C31: =INDEX($B$12:$B$24,MATCH(LARGE($V$12:$V$24,2),$V$12:$V$24,0)) -> 1.6266 | D31: =IF(C31>'Indicadores (F-W)'!$M$6,"Especializado",IF(C31<'Indicadores (F-W)'!$L$6,"Sub-representado","Intermediário")) -> Especializado | F31: 2 | G31: =INDEX($A$12:$A$24,MATCH(LARGE($W$12:$W$24,2),$W$12:$W$24,0)) -> Rondonópolis | H31: =INDEX($C$12:$C$24,MATCH(LARGE($W$12:$W$24,2),$W$12:$W$24,0)) -> 1.8691 | I31: =IF(H31>'Indicadores (F-W)'!$M$11,"Especializado",IF(H31<'Indicadores (F-W)'!$L$11,"Sub-representado","Intermediário")) -> Especializado | K31: 2 | L31: =INDEX($A$12:$A$24,MATCH(LARGE($X$12:$X$24,2),$X$12:$X$24,0)) -> Cáceres | M31: =INDEX($D$12:$D$24,MATCH(LARGE($X$12:$X$24,2),$X$12:$X$24,0)) -> 1.3013 | N31: =IF(M31>'Indicadores (F-W)'!$M$14,"Especializado",IF(M31<'Indicadores (F-W)'!$L$14,"Sub-representado","Intermediário")) -> Especializado
A32: 3 | B32: =INDEX($A$12:$A$24,MATCH(LARGE($V$12:$V$24,3),$V$12:$V$24,0)) -> Glória D'Oeste | C32: =INDEX($B$12:$B$24,MATCH(LARGE($V$12:$V$24,3),$V$12:$V$24,0)) -> 1.3866 | D32: =IF(C32>'Indicadores (F-W)'!$M$6,"Especializado",IF(C32<'Indicadores (F-W)'!$L$6,"Sub-representado","Intermediário")) -> Especializado | F32: 3 | G32: =INDEX($A$12:$A$24,MATCH(LARGE($W$12:$W$24,3),$W$12:$W$24,0)) -> Itiquira | H32: =INDEX($C$12:$C$24,MATCH(LARGE($W$12:$W$24,3),$W$12:$W$24,0)) -> 1.2891 | I32: =IF(H32>'Indicadores (F-W)'!$M$11,"Especializado",IF(H32<'Indicadores (F-W)'!$L$11,"Sub-representado","Intermediário")) -> Especializado | K32: 3 | L32: =INDEX($A$12:$A$24,MATCH(LARGE($X$12:$X$24,3),$X$12:$X$24,0)) -> Mirassol D'Oeste | M32: =INDEX($D$12:$D$24,MATCH(LARGE($X$12:$X$24,3),$X$12:$X$24,0)) -> 1.1498 | N32: =IF(M32>'Indicadores (F-W)'!$M$14,"Especializado",IF(M32<'Indicadores (F-W)'!$L$14,"Sub-representado","Intermediário")) -> Intermediário
A33: 4 | B33: =INDEX($A$12:$A$24,MATCH(LARGE($V$12:$V$24,4),$V$12:$V$24,0)) -> Lambari D'Oeste | C33: =INDEX($B$12:$B$24,MATCH(LARGE($V$12:$V$24,4),$V$12:$V$24,0)) -> 1.364 | D33: =IF(C33>'Indicadores (F-W)'!$M$6,"Especializado",IF(C33<'Indicadores (F-W)'!$L$6,"Sub-representado","Intermediário")) -> Especializado | F33: 4 | G33: =INDEX($A$12:$A$24,MATCH(LARGE($W$12:$W$24,4),$W$12:$W$24,0)) -> Mirassol D'Oeste | H33: =INDEX($C$12:$C$24,MATCH(LARGE($W$12:$W$24,4),$W$12:$W$24,0)) -> 1.2112 | I33: =IF(H33>'Indicadores (F-W)'!$M$11,"Especializado",IF(H33<'Indicadores (F-W)'!$L$11,"Sub-representado","Intermediário")) -> Especializado | K33: 4 | L33: =INDEX($A$12:$A$24,MATCH(LARGE($X$12:$X$24,4),$X$12:$X$24,0)) -> Poconé | M33: =INDEX($D$12:$D$24,MATCH(LARGE($X$12:$X$24,4),$X$12:$X$24,0)) -> 1.1034 | N33: =IF(M33>'Indicadores (F-W)'!$M$14,"Especializado",IF(M33<'Indicadores (F-W)'!$L$14,"Sub-representado","Intermediário")) -> Intermediário
A34: 5 | B34: =INDEX($A$12:$A$24,MATCH(LARGE($V$12:$V$24,5),$V$12:$V$24,0)) -> Juscimeira | C34: =INDEX($B$12:$B$24,MATCH(LARGE($V$12:$V$24,5),$V$12:$V$24,0)) -> 1.319 | D34: =IF(C34>'Indicadores (F-W)'!$M$6,"Especializado",IF(C34<'Indicadores (F-W)'!$L$6,"Sub-representado","Intermediário")) -> Especializado | F34: 5 | G34: =INDEX($A$12:$A$24,MATCH(LARGE($W$12:$W$24,5),$W$12:$W$24,0)) -> Lambari D'Oeste | H34: =INDEX($C$12:$C$24,MATCH(LARGE($W$12:$W$24,5),$W$12:$W$24,0)) -> 1.1956 | I34: =IF(H34>'Indicadores (F-W)'!$M$11,"Especializado",IF(H34<'Indicadores (F-W)'!$L$11,"Sub-representado","Intermediário")) -> Intermediário | K34: 5 | L34: =INDEX($A$12:$A$24,MATCH(LARGE($X$12:$X$24,5),$X$12:$X$24,0)) -> Nossa Senhora do Livramento | M34: =INDEX($D$12:$D$24,MATCH(LARGE($X$12:$X$24,5),$X$12:$X$24,0)) -> 0.7089 | N34: =IF(M34>'Indicadores (F-W)'!$M$14,"Especializado",IF(M34<'Indicadores (F-W)'!$L$14,"Sub-representado","Intermediário")) -> Sub-representado
A35: 6 | B35: =INDEX($A$12:$A$24,MATCH(LARGE($V$12:$V$24,6),$V$12:$V$24,0)) -> Curvelândia | C35: =INDEX($B$12:$B$24,MATCH(LARGE($V$12:$V$24,6),$V$12:$V$24,0)) -> 1.2022 | D35: =IF(C35>'Indicadores (F-W)'!$M$6,"Especializado",IF(C35<'Indicadores (F-W)'!$L$6,"Sub-representado","Intermediário")) -> Especializado | F35: 6 | G35: =INDEX($A$12:$A$24,MATCH(LARGE($W$12:$W$24,6),$W$12:$W$24,0)) -> Juscimeira | H35: =INDEX($C$12:$C$24,MATCH(LARGE($W$12:$W$24,6),$W$12:$W$24,0)) -> 1.1671 | I35: =IF(H35>'Indicadores (F-W)'!$M$11,"Especializado",IF(H35<'Indicadores (F-W)'!$L$11,"Sub-representado","Intermediário")) -> Intermediário | K35: 6 | L35: =INDEX($A$12:$A$24,MATCH(LARGE($X$12:$X$24,6),$X$12:$X$24,0)) -> Porto Esperidião | M35: =INDEX($D$12:$D$24,MATCH(LARGE($X$12:$X$24,6),$X$12:$X$24,0)) -> 0.505 | N35: =IF(M35>'Indicadores (F-W)'!$M$14,"Especializado",IF(M35<'Indicadores (F-W)'!$L$14,"Sub-representado","Intermediário")) -> Sub-representado
A36: 7 | B36: =INDEX($A$12:$A$24,MATCH(LARGE($V$12:$V$24,7),$V$12:$V$24,0)) -> Porto Esperidião | C36: =INDEX($B$12:$B$24,MATCH(LARGE($V$12:$V$24,7),$V$12:$V$24,0)) -> 1.0048 | D36: =IF(C36>'Indicadores (F-W)'!$M$6,"Especializado",IF(C36<'Indicadores (F-W)'!$L$6,"Sub-representado","Intermediário")) -> Intermediário | F36: 7 | G36: =INDEX($A$12:$A$24,MATCH(LARGE($W$12:$W$24,7),$W$12:$W$24,0)) -> Porto Esperidião | H36: =INDEX($C$12:$C$24,MATCH(LARGE($W$12:$W$24,7),$W$12:$W$24,0)) -> 1.0107 | I36: =IF(H36>'Indicadores (F-W)'!$M$11,"Especializado",IF(H36<'Indicadores (F-W)'!$L$11,"Sub-representado","Intermediário")) -> Intermediário | K36: 7 | L36: =INDEX($A$12:$A$24,MATCH(LARGE($X$12:$X$24,7),$X$12:$X$24,0)) -> Curvelândia | M36: =INDEX($D$12:$D$24,MATCH(LARGE($X$12:$X$24,7),$X$12:$X$24,0)) -> 0.5029 | N36: =IF(M36>'Indicadores (F-W)'!$M$14,"Especializado",IF(M36<'Indicadores (F-W)'!$L$14,"Sub-representado","Intermediário")) -> Sub-representado
A37: 8 | B37: =INDEX($A$12:$A$24,MATCH(LARGE($V$12:$V$24,8),$V$12:$V$24,0)) -> Barão de Melgaço | C37: =INDEX($B$12:$B$24,MATCH(LARGE($V$12:$V$24,8),$V$12:$V$24,0)) -> 0.9631 | D37: =IF(C37>'Indicadores (F-W)'!$M$6,"Especializado",IF(C37<'Indicadores (F-W)'!$L$6,"Sub-representado","Intermediário")) -> Intermediário | F37: 8 | G37: =INDEX($A$12:$A$24,MATCH(LARGE($W$12:$W$24,8),$W$12:$W$24,0)) -> Cáceres | H37: =INDEX($C$12:$C$24,MATCH(LARGE($W$12:$W$24,8),$W$12:$W$24,0)) -> 0.6374 | I37: =IF(H37>'Indicadores (F-W)'!$M$11,"Especializado",IF(H37<'Indicadores (F-W)'!$L$11,"Sub-representado","Intermediário")) -> Sub-representado | K37: 8 | L37: =INDEX($A$12:$A$24,MATCH(LARGE($X$12:$X$24,8),$X$12:$X$24,0)) -> Glória D'Oeste | M37: =INDEX($D$12:$D$24,MATCH(LARGE($X$12:$X$24,8),$X$12:$X$24,0)) -> 0.4636 | N37: =IF(M37>'Indicadores (F-W)'!$M$14,"Especializado",IF(M37<'Indicadores (F-W)'!$L$14,"Sub-representado","Intermediário")) -> Sub-representado
A38: 9 | B38: =INDEX($A$12:$A$24,MATCH(LARGE($V$12:$V$24,9),$V$12:$V$24,0)) -> Nossa Senhora do Livramento | C38: =INDEX($B$12:$B$24,MATCH(LARGE($V$12:$V$24,9),$V$12:$V$24,0)) -> 0.5183 | D38: =IF(C38>'Indicadores (F-W)'!$M$6,"Especializado",IF(C38<'Indicadores (F-W)'!$L$6,"Sub-representado","Intermediário")) -> Sub-representado | F38: 9 | G38: =INDEX($A$12:$A$24,MATCH(LARGE($W$12:$W$24,9),$W$12:$W$24,0)) -> Poconé | H38: =INDEX($C$12:$C$24,MATCH(LARGE($W$12:$W$24,9),$W$12:$W$24,0)) -> 0.5947 | I38: =IF(H38>'Indicadores (F-W)'!$M$11,"Especializado",IF(H38<'Indicadores (F-W)'!$L$11,"Sub-representado","Intermediário")) -> Sub-representado | K38: 9 | L38: =INDEX($A$12:$A$24,MATCH(LARGE($X$12:$X$24,9),$X$12:$X$24,0)) -> Juscimeira | M38: =INDEX($D$12:$D$24,MATCH(LARGE($X$12:$X$24,9),$X$12:$X$24,0)) -> 0.4388 | N38: =IF(M38>'Indicadores (F-W)'!$M$14,"Especializado",IF(M38<'Indicadores (F-W)'!$L$14,"Sub-representado","Intermediário")) -> Sub-representado
A39: 10 | B39: =INDEX($A$12:$A$24,MATCH(LARGE($V$12:$V$24,10),$V$12:$V$24,0)) -> Poconé | C39: =INDEX($B$12:$B$24,MATCH(LARGE($V$12:$V$24,10),$V$12:$V$24,0)) -> 0.5066 | D39: =IF(C39>'Indicadores (F-W)'!$M$6,"Especializado",IF(C39<'Indicadores (F-W)'!$L$6,"Sub-representado","Intermediário")) -> Sub-representado | F39: 10 | G39: =INDEX($A$12:$A$24,MATCH(LARGE($W$12:$W$24,10),$W$12:$W$24,0)) -> Santo Antônio do Leverger | H39: =INDEX($C$12:$C$24,MATCH(LARGE($W$12:$W$24,10),$W$12:$W$24,0)) -> 0.4719 | I39: =IF(H39>'Indicadores (F-W)'!$M$11,"Especializado",IF(H39<'Indicadores (F-W)'!$L$11,"Sub-representado","Intermediário")) -> Sub-representado | K39: 10 | L39: =INDEX($A$12:$A$24,MATCH(LARGE($X$12:$X$24,10),$X$12:$X$24,0)) -> Barão de Melgaço | M39: =INDEX($D$12:$D$24,MATCH(LARGE($X$12:$X$24,10),$X$12:$X$24,0)) -> 0.4274 | N39: =IF(M39>'Indicadores (F-W)'!$M$14,"Especializado",IF(M39<'Indicadores (F-W)'!$L$14,"Sub-representado","Intermediário")) -> Sub-representado
A40: 11 | B40: =INDEX($A$12:$A$24,MATCH(LARGE($V$12:$V$24,11),$V$12:$V$24,0)) -> Mirassol D'Oeste | C40: =INDEX($B$12:$B$24,MATCH(LARGE($V$12:$V$24,11),$V$12:$V$24,0)) -> 0.416 | D40: =IF(C40>'Indicadores (F-W)'!$M$6,"Especializado",IF(C40<'Indicadores (F-W)'!$L$6,"Sub-representado","Intermediário")) -> Sub-representado | F40: 11 | G40: =INDEX($A$12:$A$24,MATCH(LARGE($W$12:$W$24,11),$W$12:$W$24,0)) -> Curvelândia | H40: =INDEX($C$12:$C$24,MATCH(LARGE($W$12:$W$24,11),$W$12:$W$24,0)) -> 0.4717 | I40: =IF(H40>'Indicadores (F-W)'!$M$11,"Especializado",IF(H40<'Indicadores (F-W)'!$L$11,"Sub-representado","Intermediário")) -> Sub-representado | K40: 11 | L40: =INDEX($A$12:$A$24,MATCH(LARGE($X$12:$X$24,11),$X$12:$X$24,0)) -> Itiquira | M40: =INDEX($D$12:$D$24,MATCH(LARGE($X$12:$X$24,11),$X$12:$X$24,0)) -> 0.3623 | N40: =IF(M40>'Indicadores (F-W)'!$M$14,"Especializado",IF(M40<'Indicadores (F-W)'!$L$14,"Sub-representado","Intermediário")) -> Sub-representado
A41: 12 | B41: =INDEX($A$12:$A$24,MATCH(LARGE($V$12:$V$24,12),$V$12:$V$24,0)) -> Cáceres | C41: =INDEX($B$12:$B$24,MATCH(LARGE($V$12:$V$24,12),$V$12:$V$24,0)) -> 0.3713 | D41: =IF(C41>'Indicadores (F-W)'!$M$6,"Especializado",IF(C41<'Indicadores (F-W)'!$L$6,"Sub-representado","Intermediário")) -> Sub-representado | F41: 12 | G41: =INDEX($A$12:$A$24,MATCH(LARGE($W$12:$W$24,12),$W$12:$W$24,0)) -> Glória D'Oeste | H41: =INDEX($C$12:$C$24,MATCH(LARGE($W$12:$W$24,12),$W$12:$W$24,0)) -> 0.2854 | I41: =IF(H41>'Indicadores (F-W)'!$M$11,"Especializado",IF(H41<'Indicadores (F-W)'!$L$11,"Sub-representado","Intermediário")) -> Sub-representado | K41: 12 | L41: =INDEX($A$12:$A$24,MATCH(LARGE($X$12:$X$24,12),$X$12:$X$24,0)) -> Santo Antônio do Leverger | M41: =INDEX($D$12:$D$24,MATCH(LARGE($X$12:$X$24,12),$X$12:$X$24,0)) -> 0.3417 | N41: =IF(M41>'Indicadores (F-W)'!$M$14,"Especializado",IF(M41<'Indicadores (F-W)'!$L$14,"Sub-representado","Intermediário")) -> Sub-representado
A42: 13 | B42: =INDEX($A$12:$A$24,MATCH(LARGE($V$12:$V$24,13),$V$12:$V$24,0)) -> Rondonópolis | C42: =INDEX($B$12:$B$24,MATCH(LARGE($V$12:$V$24,13),$V$12:$V$24,0)) -> 0.1067 | D42: =IF(C42>'Indicadores (F-W)'!$M$6,"Especializado",IF(C42<'Indicadores (F-W)'!$L$6,"Sub-representado","Intermediário")) -> Sub-representado | F42: 13 | G42: =INDEX($A$12:$A$24,MATCH(LARGE($W$12:$W$24,13),$W$12:$W$24,0)) -> Barão de Melgaço | H42: =INDEX($C$12:$C$24,MATCH(LARGE($W$12:$W$24,13),$W$12:$W$24,0)) -> 0.169 | I42: =IF(H42>'Indicadores (F-W)'!$M$11,"Especializado",IF(H42<'Indicadores (F-W)'!$L$11,"Sub-representado","Intermediário")) -> Sub-representado | K42: 13 | L42: =INDEX($A$12:$A$24,MATCH(LARGE($X$12:$X$24,13),$X$12:$X$24,0)) -> Lambari D'Oeste | M42: =INDEX($D$12:$D$24,MATCH(LARGE($X$12:$X$24,13),$X$12:$X$24,0)) -> 0.3227 | N42: =IF(M42>'Indicadores (F-W)'!$M$14,"Especializado",IF(M42<'Indicadores (F-W)'!$L$14,"Sub-representado","Intermediário")) -> Sub-representado
A45: RANKING DE ESPECIALIZAÇÃO GERAL E DE DIVERSIFICAÇÃO
A46: COEFICIENTE DE ESPECIALIZAÇÃO (maior = estrutura mais distante de MT) | F46: DIVERSIFICAÇÃO (maior = menos dependente de um setor)
A47: Pos. | B47: Município | C47: Coef. | D47: Setor dominante | F47: Pos. | G47: Município | H47: Índice | I47: Setor dominante | J47: Part. dominante
A48: 1 | B48: =INDEX($A$12:$A$24,MATCH(LARGE($Y$12:$Y$24,1),$Y$12:$Y$24,0)) -> Rondonópolis | C48: =INDEX($J$12:$J$24,MATCH(LARGE($Y$12:$Y$24,1),$Y$12:$Y$24,0)) -> 0.34154446 | D48: =INDEX($O$12:$O$24,MATCH(LARGE($Y$12:$Y$24,1),$Y$12:$Y$24,0)) -> Serviços | F48: 1 | G48: =INDEX($A$12:$A$24,MATCH(LARGE($Z$12:$Z$24,1),$Z$12:$Z$24,0)) -> Nossa Senhora do Livramento | H48: =INDEX($M$12:$M$24,MATCH(LARGE($Z$12:$Z$24,1),$Z$12:$Z$24,0)) -> 0.99200257 | I48: =INDEX($O$12:$O$24,MATCH(LARGE($Z$12:$Z$24,1),$Z$12:$Z$24,0)) -> Indústria | J48: =INDEX($P$12:$P$24,MATCH(LARGE($Z$12:$Z$24,1),$Z$12:$Z$24,0)) -> 0.30645882
A49: 2 | B49: =INDEX($A$12:$A$24,MATCH(LARGE($Y$12:$Y$24,2),$Y$12:$Y$24,0)) -> Barão de Melgaço | C49: =INDEX($J$12:$J$24,MATCH(LARGE($Y$12:$Y$24,2),$Y$12:$Y$24,0)) -> 0.34061158 | D49: =INDEX($O$12:$O$24,MATCH(LARGE($Y$12:$Y$24,2),$Y$12:$Y$24,0)) -> Adm. pública | F49: 2 | G49: =INDEX($A$12:$A$24,MATCH(LARGE($Z$12:$Z$24,2),$Z$12:$Z$24,0)) -> Porto Esperidião | H49: =INDEX($M$12:$M$24,MATCH(LARGE($Z$12:$Z$24,2),$Z$12:$Z$24,0)) -> 0.95552854 | I49: =INDEX($O$12:$O$24,MATCH(LARGE($Z$12:$Z$24,2),$Z$12:$Z$24,0)) -> Agropecuária | J49: =INDEX($P$12:$P$24,MATCH(LARGE($Z$12:$Z$24,2),$Z$12:$Z$24,0)) -> 0.38159189
A50: 3 | B50: =INDEX($A$12:$A$24,MATCH(LARGE($Y$12:$Y$24,3),$Y$12:$Y$24,0)) -> Santo Antônio do Leverger | C50: =INDEX($J$12:$J$24,MATCH(LARGE($Y$12:$Y$24,3),$Y$12:$Y$24,0)) -> 0.31009145 | D50: =INDEX($O$12:$O$24,MATCH(LARGE($Y$12:$Y$24,3),$Y$12:$Y$24,0)) -> Agropecuária | F50: 3 | G50: =INDEX($A$12:$A$24,MATCH(LARGE($Z$12:$Z$24,3),$Z$12:$Z$24,0)) -> Mirassol D'Oeste | H50: =INDEX($M$12:$M$24,MATCH(LARGE($Z$12:$Z$24,3),$Z$12:$Z$24,0)) -> 0.95284197 | I50: =INDEX($O$12:$O$24,MATCH(LARGE($Z$12:$Z$24,3),$Z$12:$Z$24,0)) -> Serviços | J50: =INDEX($P$12:$P$24,MATCH(LARGE($Z$12:$Z$24,3),$Z$12:$Z$24,0)) -> 0.40055008
A51: 4 | B51: =INDEX($A$12:$A$24,MATCH(LARGE($Y$12:$Y$24,4),$Y$12:$Y$24,0)) -> Glória D'Oeste | C51: =INDEX($J$12:$J$24,MATCH(LARGE($Y$12:$Y$24,4),$Y$12:$Y$24,0)) -> 0.29620552 | D51: =INDEX($O$12:$O$24,MATCH(LARGE($Y$12:$Y$24,4),$Y$12:$Y$24,0)) -> Agropecuária | F51: 4 | G51: =INDEX($A$12:$A$24,MATCH(LARGE($Z$12:$Z$24,4),$Z$12:$Z$24,0)) -> Poconé | H51: =INDEX($M$12:$M$24,MATCH(LARGE($Z$12:$Z$24,4),$Z$12:$Z$24,0)) -> 0.92871112 | I51: =INDEX($O$12:$O$24,MATCH(LARGE($Z$12:$Z$24,4),$Z$12:$Z$24,0)) -> Serviços | J51: =INDEX($P$12:$P$24,MATCH(LARGE($Z$12:$Z$24,4),$Z$12:$Z$24,0)) -> 0.38438594
A52: 5 | B52: =INDEX($A$12:$A$24,MATCH(LARGE($Y$12:$Y$24,5),$Y$12:$Y$24,0)) -> Cáceres | C52: =INDEX($J$12:$J$24,MATCH(LARGE($Y$12:$Y$24,5),$Y$12:$Y$24,0)) -> 0.2942523 | D52: =INDEX($O$12:$O$24,MATCH(LARGE($Y$12:$Y$24,5),$Y$12:$Y$24,0)) -> Serviços | F52: 5 | G52: =INDEX($A$12:$A$24,MATCH(LARGE($Z$12:$Z$24,5),$Z$12:$Z$24,0)) -> Cáceres | H52: =INDEX($M$12:$M$24,MATCH(LARGE($Z$12:$Z$24,5),$Z$12:$Z$24,0)) -> 0.89348801 | I52: =INDEX($O$12:$O$24,MATCH(LARGE($Z$12:$Z$24,5),$Z$12:$Z$24,0)) -> Serviços | J52: =INDEX($P$12:$P$24,MATCH(LARGE($Z$12:$Z$24,5),$Z$12:$Z$24,0)) -> 0.45332737
A53: 6 | B53: =INDEX($A$12:$A$24,MATCH(LARGE($Y$12:$Y$24,6),$Y$12:$Y$24,0)) -> Nossa Senhora do Livramento | C53: =INDEX($J$12:$J$24,MATCH(LARGE($Y$12:$Y$24,6),$Y$12:$Y$24,0)) -> 0.2843188 | D53: =INDEX($O$12:$O$24,MATCH(LARGE($Y$12:$Y$24,6),$Y$12:$Y$24,0)) -> Indústria | F53: 6 | G53: =INDEX($A$12:$A$24,MATCH(LARGE($Z$12:$Z$24,6),$Z$12:$Z$24,0)) -> Curvelândia | H53: =INDEX($M$12:$M$24,MATCH(LARGE($Z$12:$Z$24,6),$Z$12:$Z$24,0)) -> 0.89063981 | I53: =INDEX($O$12:$O$24,MATCH(LARGE($Z$12:$Z$24,6),$Z$12:$Z$24,0)) -> Agropecuária | J53: =INDEX($P$12:$P$24,MATCH(LARGE($Z$12:$Z$24,6),$Z$12:$Z$24,0)) -> 0.45655829
A54: 7 | B54: =INDEX($A$12:$A$24,MATCH(LARGE($Y$12:$Y$24,7),$Y$12:$Y$24,0)) -> Itiquira | C54: =INDEX($J$12:$J$24,MATCH(LARGE($Y$12:$Y$24,7),$Y$12:$Y$24,0)) -> 0.28221463 | D54: =INDEX($O$12:$O$24,MATCH(LARGE($Y$12:$Y$24,7),$Y$12:$Y$24,0)) -> Agropecuária | F54: 7 | G54: =INDEX($A$12:$A$24,MATCH(LARGE($Z$12:$Z$24,7),$Z$12:$Z$24,0)) -> Juscimeira | H54: =INDEX($M$12:$M$24,MATCH(LARGE($Z$12:$Z$24,7),$Z$12:$Z$24,0)) -> 0.88762301 | I54: =INDEX($O$12:$O$24,MATCH(LARGE($Z$12:$Z$24,7),$Z$12:$Z$24,0)) -> Agropecuária | J54: =INDEX($P$12:$P$24,MATCH(LARGE($Z$12:$Z$24,7),$Z$12:$Z$24,0)) -> 0.50091531
A55: 8 | B55: =INDEX($A$12:$A$24,MATCH(LARGE($Y$12:$Y$24,8),$Y$12:$Y$24,0)) -> Curvelândia | C55: =INDEX($J$12:$J$24,MATCH(LARGE($Y$12:$Y$24,8),$Y$12:$Y$24,0)) -> 0.25399564 | D55: =INDEX($O$12:$O$24,MATCH(LARGE($Y$12:$Y$24,8),$Y$12:$Y$24,0)) -> Agropecuária | F55: 8 | G55: =INDEX($A$12:$A$24,MATCH(LARGE($Z$12:$Z$24,8),$Z$12:$Z$24,0)) -> Lambari D'Oeste | H55: =INDEX($M$12:$M$24,MATCH(LARGE($Z$12:$Z$24,8),$Z$12:$Z$24,0)) -> 0.86763226 | I55: =INDEX($O$12:$O$24,MATCH(LARGE($Z$12:$Z$24,8),$Z$12:$Z$24,0)) -> Agropecuária | J55: =INDEX($P$12:$P$24,MATCH(LARGE($Z$12:$Z$24,8),$Z$12:$Z$24,0)) -> 0.51800492
A56: 9 | B56: =INDEX($A$12:$A$24,MATCH(LARGE($Y$12:$Y$24,9),$Y$12:$Y$24,0)) -> Poconé | C56: =INDEX($J$12:$J$24,MATCH(LARGE($Y$12:$Y$24,9),$Y$12:$Y$24,0)) -> 0.24940627 | D56: =INDEX($O$12:$O$24,MATCH(LARGE($Y$12:$Y$24,9),$Y$12:$Y$24,0)) -> Serviços | F56: 9 | G56: =INDEX($A$12:$A$24,MATCH(LARGE($Z$12:$Z$24,9),$Z$12:$Z$24,0)) -> Barão de Melgaço | H56: =INDEX($M$12:$M$24,MATCH(LARGE($Z$12:$Z$24,9),$Z$12:$Z$24,0)) -> 0.84299423 | I56: =INDEX($O$12:$O$24,MATCH(LARGE($Z$12:$Z$24,9),$Z$12:$Z$24,0)) -> Adm. pública | J56: =INDEX($P$12:$P$24,MATCH(LARGE($Z$12:$Z$24,9),$Z$12:$Z$24,0)) -> 0.4595
A57: 10 | B57: =INDEX($A$12:$A$24,MATCH(LARGE($Y$12:$Y$24,10),$Y$12:$Y$24,0)) -> Lambari D'Oeste | C57: =INDEX($J$12:$J$24,MATCH(LARGE($Y$12:$Y$24,10),$Y$12:$Y$24,0)) -> 0.23595892 | D57: =INDEX($O$12:$O$24,MATCH(LARGE($Y$12:$Y$24,10),$Y$12:$Y$24,0)) -> Agropecuária | F57: 10 | G57: =INDEX($A$12:$A$24,MATCH(LARGE($Z$12:$Z$24,10),$Z$12:$Z$24,0)) -> Glória D'Oeste | H57: =INDEX($M$12:$M$24,MATCH(LARGE($Z$12:$Z$24,10),$Z$12:$Z$24,0)) -> 0.83030859 | I57: =INDEX($O$12:$O$24,MATCH(LARGE($Z$12:$Z$24,10),$Z$12:$Z$24,0)) -> Agropecuária | J57: =INDEX($P$12:$P$24,MATCH(LARGE($Z$12:$Z$24,10),$Z$12:$Z$24,0)) -> 0.5265877
A58: 11 | B58: =INDEX($A$12:$A$24,MATCH(LARGE($Y$12:$Y$24,11),$Y$12:$Y$24,0)) -> Mirassol D'Oeste | C58: =INDEX($J$12:$J$24,MATCH(LARGE($Y$12:$Y$24,11),$Y$12:$Y$24,0)) -> 0.22179546 | D58: =INDEX($O$12:$O$24,MATCH(LARGE($Y$12:$Y$24,11),$Y$12:$Y$24,0)) -> Serviços | F58: 11 | G58: =INDEX($A$12:$A$24,MATCH(LARGE($Z$12:$Z$24,11),$Z$12:$Z$24,0)) -> Rondonópolis | H58: =INDEX($M$12:$M$24,MATCH(LARGE($Z$12:$Z$24,11),$Z$12:$Z$24,0)) -> 0.79039441 | I58: =INDEX($O$12:$O$24,MATCH(LARGE($Z$12:$Z$24,11),$Z$12:$Z$24,0)) -> Serviços | J58: =INDEX($P$12:$P$24,MATCH(LARGE($Z$12:$Z$24,11),$Z$12:$Z$24,0)) -> 0.55696596
A59: 12 | B59: =INDEX($A$12:$A$24,MATCH(LARGE($Y$12:$Y$24,12),$Y$12:$Y$24,0)) -> Juscimeira | C59: =INDEX($J$12:$J$24,MATCH(LARGE($Y$12:$Y$24,12),$Y$12:$Y$24,0)) -> 0.1955116 | D59: =INDEX($O$12:$O$24,MATCH(LARGE($Y$12:$Y$24,12),$Y$12:$Y$24,0)) -> Agropecuária | F59: 12 | G59: =INDEX($A$12:$A$24,MATCH(LARGE($Z$12:$Z$24,12),$Z$12:$Z$24,0)) -> Itiquira | H59: =INDEX($M$12:$M$24,MATCH(LARGE($Z$12:$Z$24,12),$Z$12:$Z$24,0)) -> 0.74684121 | I59: =INDEX($O$12:$O$24,MATCH(LARGE($Z$12:$Z$24,12),$Z$12:$Z$24,0)) -> Agropecuária | J59: =INDEX($P$12:$P$24,MATCH(LARGE($Z$12:$Z$24,12),$Z$12:$Z$24,0)) -> 0.61773226
A60: 13 | B60: =INDEX($A$12:$A$24,MATCH(LARGE($Y$12:$Y$24,13),$Y$12:$Y$24,0)) -> Porto Esperidião | C60: =INDEX($J$12:$J$24,MATCH(LARGE($Y$12:$Y$24,13),$Y$12:$Y$24,0)) -> 0.17245621 | D60: =INDEX($O$12:$O$24,MATCH(LARGE($Y$12:$Y$24,13),$Y$12:$Y$24,0)) -> Agropecuária | F60: 13 | G60: =INDEX($A$12:$A$24,MATCH(LARGE($Z$12:$Z$24,13),$Z$12:$Z$24,0)) -> Santo Antônio do Leverger | H60: =INDEX($M$12:$M$24,MATCH(LARGE($Z$12:$Z$24,13),$Z$12:$Z$24,0)) -> 0.70935467 | I60: =INDEX($O$12:$O$24,MATCH(LARGE($Z$12:$Z$24,13),$Z$12:$Z$24,0)) -> Agropecuária | J60: =INDEX($P$12:$P$24,MATCH(LARGE($Z$12:$Z$24,13),$Z$12:$Z$24,0)) -> 0.65092407
A62: Coeficiente de especialização = ½ Σ |s(i,mun) − s(i,MT)| sobre os 4 grandes setores do VAB. 0 = estrutura idêntica à de MT; valores altos = estrutura muito diferente (especialização relativa).
A63: Índice de diversificação = 1 − (HHI − 1/4)/(1 − 1/4), com HHI = Σ s(i)² dos 4 setores. 1 = VAB igualmente distribuído; 0 = concentração em um único setor.
A64: Limitações: (1) só 4 grandes setores do IBGE — a diversificação intrassetorial (ex.: soja vs. cana; frigorífico vs. mineração) exige dados por CNAE (RAIS, indicador EST-04); (2) a administração pública entra no cálculo, logo municípios com alta dependência do setor público podem parecer 'diversificados'; conferir a coluna 'Setor dominante'; (3) VAB de 2021 — atualizar para 2023 via SIDRA 5938.
A65: Especializado: QL > 1,2 | Sub-representado: QL < 0,8 (limiares definidos na aba 'Indicadores (F-W)').

Sheet Ranking SWOT (provisório)
A1: ⚠ RANKING SWOT — COBERTURA MÍNIMA ATINGIDA; NOTAS EXTERNAS A VALIDAR
A2: A regra de 75% de cobertura foi atingida em 25/09/2026: 14 de 16 indicadores internos com dado e 11 de 11 fatores externos pontuados. As notas externas ainda são preliminares (uma rodada, pesquisa web-based) e precisam de consenso da equipe antes de uso em relatório.
A4: Município | B4: Forças | C4: Fraquezas | D4: Indicadores com dado | E4: Cobertura interna | F4: Índice interno (F−W)/n | G4: Oportunidades | H4: Ameaças | I4: Fatores pontuados | J4: Cobertura externa | K4: Índice externo (O−T)/n | L4: Índice SWOT | M4: Posição | N4: Status
A5: Barão de Melgaço | B5: =Painel!B4 -> 3 | C5: =Painel!C4 -> 10 | D5: =16-Painel!E4 -> 14 | E5: =D5/16 -> 0.875 | F5: =IF(D5=0,"",(B5-C5)/D5) -> -0.5 | G5: =Painel!G4 -> 3 | H5: =Painel!H4 -> 4 | I5: =COUNT('Fatores Externos (O-A)'!F$6:F$16) -> 11 | J5: =I5/11 -> 1 | K5: =IF(I5=0,"",(G5-H5)/I5) -> -0.090909091 | L5: =IF(F5="","",IF(K5="",F5,(F5+K5)/2)) -> -0.29545455 | M5: =IF(L5="","",RANK(L5,$L$5:$L$17,0)) -> 8 | N5: =IF(AND(E5>=0.75,J5>=0.75),"Consolidado","PROVISÓRIO") -> Consolidado | T5: =IF(L5="",-9,L5)-ROW()*0.000000001 -> -0.29545455
A6: Cáceres | B6: =Painel!B5 -> 3 | C6: =Painel!C5 -> 8 | D6: =16-Painel!E5 -> 14 | E6: =D6/16 -> 0.875 | F6: =IF(D6=0,"",(B6-C6)/D6) -> -0.35714286 | G6: =Painel!G5 -> 6 | H6: =Painel!H5 -> 4 | I6: =COUNT('Fatores Externos (O-A)'!G$6:G$16) -> 11 | J6: =I6/11 -> 1 | K6: =IF(I6=0,"",(G6-H6)/I6) -> 0.18181818 | L6: =IF(F6="","",IF(K6="",F6,(F6+K6)/2)) -> -0.087662338 | M6: =IF(L6="","",RANK(L6,$L$5:$L$17,0)) -> 4 | N6: =IF(AND(E6>=0.75,J6>=0.75),"Consolidado","PROVISÓRIO") -> Consolidado | T6: =IF(L6="",-9,L6)-ROW()*0.000000001 -> -0.087662344
A7: Curvelândia | B7: =Painel!B6 -> 3 | C7: =Painel!C6 -> 10 | D7: =16-Painel!E6 -> 14 | E7: =D7/16 -> 0.875 | F7: =IF(D7=0,"",(B7-C7)/D7) -> -0.5 | G7: =Painel!G6 -> 2 | H7: =Painel!H6 -> 3 | I7: =COUNT('Fatores Externos (O-A)'!H$6:H$16) -> 11 | J7: =I7/11 -> 1 | K7: =IF(I7=0,"",(G7-H7)/I7) -> -0.090909091 | L7: =IF(F7="","",IF(K7="",F7,(F7+K7)/2)) -> -0.29545455 | M7: =IF(L7="","",RANK(L7,$L$5:$L$17,0)) -> 8 | N7: =IF(AND(E7>=0.75,J7>=0.75),"Consolidado","PROVISÓRIO") -> Consolidado | T7: =IF(L7="",-9,L7)-ROW()*0.000000001 -> -0.29545455
A8: Glória D'Oeste | B8: =Painel!B7 -> 3 | C8: =Painel!C7 -> 10 | D8: =16-Painel!E7 -> 14 | E8: =D8/16 -> 0.875 | F8: =IF(D8=0,"",(B8-C8)/D8) -> -0.5 | G8: =Painel!G7 -> 2 | H8: =Painel!H7 -> 3 | I8: =COUNT('Fatores Externos (O-A)'!I$6:I$16) -> 11 | J8: =I8/11 -> 1 | K8: =IF(I8=0,"",(G8-H8)/I8) -> -0.090909091 | L8: =IF(F8="","",IF(K8="",F8,(F8+K8)/2)) -> -0.29545455 | M8: =IF(L8="","",RANK(L8,$L$5:$L$17,0)) -> 8 | N8: =IF(AND(E8>=0.75,J8>=0.75),"Consolidado","PROVISÓRIO") -> Consolidado | T8: =IF(L8="",-9,L8)-ROW()*0.000000001 -> -0.29545455
A9: Itiquira | B9: =Painel!B8 -> 7 | C9: =Painel!C8 -> 6 | D9: =16-Painel!E8 -> 14 | E9: =D9/16 -> 0.875 | F9: =IF(D9=0,"",(B9-C9)/D9) -> 0.071428571 | G9: =Painel!G8 -> 5 | H9: =Painel!H8 -> 5 | I9: =COUNT('Fatores Externos (O-A)'!J$6:J$16) -> 11 | J9: =I9/11 -> 1 | K9: =IF(I9=0,"",(G9-H9)/I9) -> 0 | L9: =IF(F9="","",IF(K9="",F9,(F9+K9)/2)) -> 0.035714286 | M9: =IF(L9="","",RANK(L9,$L$5:$L$17,0)) -> 2 | N9: =IF(AND(E9>=0.75,J9>=0.75),"Consolidado","PROVISÓRIO") -> Consolidado | T9: =IF(L9="",-9,L9)-ROW()*0.000000001 -> 0.035714277
A10: Juscimeira | B10: =Painel!B9 -> 3 | C10: =Painel!C9 -> 7 | D10: =16-Painel!E9 -> 14 | E10: =D10/16 -> 0.875 | F10: =IF(D10=0,"",(B10-C10)/D10) -> -0.28571429 | G10: =Painel!G9 -> 5 | H10: =Painel!H9 -> 4 | I10: =COUNT('Fatores Externos (O-A)'!K$6:K$16) -> 11 | J10: =I10/11 -> 1 | K10: =IF(I10=0,"",(G10-H10)/I10) -> 0.090909091 | L10: =IF(F10="","",IF(K10="",F10,(F10+K10)/2)) -> -0.097402597 | M10: =IF(L10="","",RANK(L10,$L$5:$L$17,0)) -> 5 | N10: =IF(AND(E10>=0.75,J10>=0.75),"Consolidado","PROVISÓRIO") -> Consolidado | T10: =IF(L10="",-9,L10)-ROW()*0.000000001 -> -0.097402607
A11: Lambari D'Oeste | B11: =Painel!B10 -> 2 | C11: =Painel!C10 -> 9 | D11: =16-Painel!E10 -> 14 | E11: =D11/16 -> 0.875 | F11: =IF(D11=0,"",(B11-C11)/D11) -> -0.5 | G11: =Painel!G10 -> 3 | H11: =Painel!H10 -> 4 | I11: =COUNT('Fatores Externos (O-A)'!L$6:L$16) -> 11 | J11: =I11/11 -> 1 | K11: =IF(I11=0,"",(G11-H11)/I11) -> -0.090909091 | L11: =IF(F11="","",IF(K11="",F11,(F11+K11)/2)) -> -0.29545455 | M11: =IF(L11="","",RANK(L11,$L$5:$L$17,0)) -> 8 | N11: =IF(AND(E11>=0.75,J11>=0.75),"Consolidado","PROVISÓRIO") -> Consolidado | T11: =IF(L11="",-9,L11)-ROW()*0.000000001 -> -0.29545456
A12: Mirassol D'Oeste | B12: =Painel!B11 -> 2 | C12: =Painel!C11 -> 8 | D12: =16-Painel!E11 -> 14 | E12: =D12/16 -> 0.875 | F12: =IF(D12=0,"",(B12-C12)/D12) -> -0.42857143 | G12: =Painel!G11 -> 4 | H12: =Painel!H11 -> 1 | I12: =COUNT('Fatores Externos (O-A)'!M$6:M$16) -> 11 | J12: =I12/11 -> 1 | K12: =IF(I12=0,"",(G12-H12)/I12) -> 0.27272727 | L12: =IF(F12="","",IF(K12="",F12,(F12+K12)/2)) -> -0.077922078 | M12: =IF(L12="","",RANK(L12,$L$5:$L$17,0)) -> 3 | N12: =IF(AND(E12>=0.75,J12>=0.75),"Consolidado","PROVISÓRIO") -> Consolidado | T12: =IF(L12="",-9,L12)-ROW()*0.000000001 -> -0.07792209
A13: Nossa Senhora do Livramento | B13: =Painel!B12 -> 4 | C13: =Painel!C12 -> 8 | D13: =16-Painel!E12 -> 14 | E13: =D13/16 -> 0.875 | F13: =IF(D13=0,"",(B13-C13)/D13) -> -0.28571429 | G13: =Painel!G12 -> 4 | H13: =Painel!H12 -> 3 | I13: =COUNT('Fatores Externos (O-A)'!N$6:N$16) -> 11 | J13: =I13/11 -> 1 | K13: =IF(I13=0,"",(G13-H13)/I13) -> 0.090909091 | L13: =IF(F13="","",IF(K13="",F13,(F13+K13)/2)) -> -0.097402597 | M13: =IF(L13="","",RANK(L13,$L$5:$L$17,0)) -> 5 | N13: =IF(AND(E13>=0.75,J13>=0.75),"Consolidado","PROVISÓRIO") -> Consolidado | T13: =IF(L13="",-9,L13)-ROW()*0.000000001 -> -0.09740261
A14: Poconé | B14: =Painel!B13 -> 1 | C14: =Painel!C13 -> 11 | D14: =16-Painel!E13 -> 14 | E14: =D14/16 -> 0.875 | F14: =IF(D14=0,"",(B14-C14)/D14) -> -0.71428571 | G14: =Painel!G13 -> 4 | H14: =Painel!H13 -> 4 | I14: =COUNT('Fatores Externos (O-A)'!O$6:O$16) -> 11 | J14: =I14/11 -> 1 | K14: =IF(I14=0,"",(G14-H14)/I14) -> 0 | L14: =IF(F14="","",IF(K14="",F14,(F14+K14)/2)) -> -0.35714286 | M14: =IF(L14="","",RANK(L14,$L$5:$L$17,0)) -> 13 | N14: =IF(AND(E14>=0.75,J14>=0.75),"Consolidado","PROVISÓRIO") -> Consolidado | T14: =IF(L14="",-9,L14)-ROW()*0.000000001 -> -0.35714287
A15: Porto Esperidião | B15: =Painel!B14 -> 3 | C15: =Painel!C14 -> 9 | D15: =16-Painel!E14 -> 14 | E15: =D15/16 -> 0.875 | F15: =IF(D15=0,"",(B15-C15)/D15) -> -0.42857143 | G15: =Painel!G14 -> 3 | H15: =Painel!H14 -> 4 | I15: =COUNT('Fatores Externos (O-A)'!P$6:P$16) -> 11 | J15: =I15/11 -> 1 | K15: =IF(I15=0,"",(G15-H15)/I15) -> -0.090909091 | L15: =IF(F15="","",IF(K15="",F15,(F15+K15)/2)) -> -0.25974026 | M15: =IF(L15="","",RANK(L15,$L$5:$L$17,0)) -> 7 | N15: =IF(AND(E15>=0.75,J15>=0.75),"Consolidado","PROVISÓRIO") -> Consolidado | T15: =IF(L15="",-9,L15)-ROW()*0.000000001 -> -0.25974027
A16: Rondonópolis | B16: =Painel!B15 -> 4 | C16: =Painel!C15 -> 3 | D16: =16-Painel!E15 -> 14 | E16: =D16/16 -> 0.875 | F16: =IF(D16=0,"",(B16-C16)/D16) -> 0.071428571 | G16: =Painel!G15 -> 5 | H16: =Painel!H15 -> 3 | I16: =COUNT('Fatores Externos (O-A)'!Q$6:Q$16) -> 11 | J16: =I16/11 -> 1 | K16: =IF(I16=0,"",(G16-H16)/I16) -> 0.18181818 | L16: =IF(F16="","",IF(K16="",F16,(F16+K16)/2)) -> 0.12662338 | M16: =IF(L16="","",RANK(L16,$L$5:$L$17,0)) -> 1 | N16: =IF(AND(E16>=0.75,J16>=0.75),"Consolidado","PROVISÓRIO") -> Consolidado | T16: =IF(L16="",-9,L16)-ROW()*0.000000001 -> 0.12662336
A17: Santo Antônio do Leverger | B17: =Painel!B16 -> 2 | C17: =Painel!C16 -> 11 | D17: =16-Painel!E16 -> 14 | E17: =D17/16 -> 0.875 | F17: =IF(D17=0,"",(B17-C17)/D17) -> -0.64285714 | G17: =Painel!G16 -> 5 | H17: =Painel!H16 -> 5 | I17: =COUNT('Fatores Externos (O-A)'!R$6:R$16) -> 11 | J17: =I17/11 -> 1 | K17: =IF(I17=0,"",(G17-H17)/I17) -> 0 | L17: =IF(F17="","",IF(K17="",F17,(F17+K17)/2)) -> -0.32142857 | M17: =IF(L17="","",RANK(L17,$L$5:$L$17,0)) -> 12 | N17: =IF(AND(E17>=0.75,J17>=0.75),"Consolidado","PROVISÓRIO") -> Consolidado | T17: =IF(L17="",-9,L17)-ROW()*0.000000001 -> -0.32142859
A20: CLASSIFICAÇÃO ORDENADA (provisória)
A21: Posição | B21: Município | C21: Índice SWOT | D21: Cobertura interna | E21: Cobertura externa | F21: Status
A22: =INDEX($M$5:$M$17,MATCH(LARGE($T$5:$T$17,1),$T$5:$T$17,0)) -> 1 | B22: =INDEX($A$5:$A$17,MATCH(LARGE($T$5:$T$17,1),$T$5:$T$17,0)) -> Rondonópolis | C22: =INDEX($L$5:$L$17,MATCH(LARGE($T$5:$T$17,1),$T$5:$T$17,0)) -> 0.12662338 | D22: =INDEX($E$5:$E$17,MATCH(LARGE($T$5:$T$17,1),$T$5:$T$17,0)) -> 0.875 | E22: =INDEX($J$5:$J$17,MATCH(LARGE($T$5:$T$17,1),$T$5:$T$17,0)) -> 1 | F22: =INDEX($N$5:$N$17,MATCH(LARGE($T$5:$T$17,1),$T$5:$T$17,0)) -> Consolidado
A23: =INDEX($M$5:$M$17,MATCH(LARGE($T$5:$T$17,2),$T$5:$T$17,0)) -> 2 | B23: =INDEX($A$5:$A$17,MATCH(LARGE($T$5:$T$17,2),$T$5:$T$17,0)) -> Itiquira | C23: =INDEX($L$5:$L$17,MATCH(LARGE($T$5:$T$17,2),$T$5:$T$17,0)) -> 0.035714286 | D23: =INDEX($E$5:$E$17,MATCH(LARGE($T$5:$T$17,2),$T$5:$T$17,0)) -> 0.875 | E23: =INDEX($J$5:$J$17,MATCH(LARGE($T$5:$T$17,2),$T$5:$T$17,0)) -> 1 | F23: =INDEX($N$5:$N$17,MATCH(LARGE($T$5:$T$17,2),$T$5:$T$17,0)) -> Consolidado
A24: =INDEX($M$5:$M$17,MATCH(LARGE($T$5:$T$17,3),$T$5:$T$17,0)) -> 3 | B24: =INDEX($A$5:$A$17,MATCH(LARGE($T$5:$T$17,3),$T$5:$T$17,0)) -> Mirassol D'Oeste | C24: =INDEX($L$5:$L$17,MATCH(LARGE($T$5:$T$17,3),$T$5:$T$17,0)) -> -0.077922078 | D24: =INDEX($E$5:$E$17,MATCH(LARGE($T$5:$T$17,3),$T$5:$T$17,0)) -> 0.875 | E24: =INDEX($J$5:$J$17,MATCH(LARGE($T$5:$T$17,3),$T$5:$T$17,0)) -> 1 | F24: =INDEX($N$5:$N$17,MATCH(LARGE($T$5:$T$17,3),$T$5:$T$17,0)) -> Consolidado
A25: =INDEX($M$5:$M$17,MATCH(LARGE($T$5:$T$17,4),$T$5:$T$17,0)) -> 4 | B25: =INDEX($A$5:$A$17,MATCH(LARGE($T$5:$T$17,4),$T$5:$T$17,0)) -> Cáceres | C25: =INDEX($L$5:$L$17,MATCH(LARGE($T$5:$T$17,4),$T$5:$T$17,0)) -> -0.087662338 | D25: =INDEX($E$5:$E$17,MATCH(LARGE($T$5:$T$17,4),$T$5:$T$17,0)) -> 0.875 | E25: =INDEX($J$5:$J$17,MATCH(LARGE($T$5:$T$17,4),$T$5:$T$17,0)) -> 1 | F25: =INDEX($N$5:$N$17,MATCH(LARGE($T$5:$T$17,4),$T$5:$T$17,0)) -> Consolidado
A26: =INDEX($M$5:$M$17,MATCH(LARGE($T$5:$T$17,5),$T$5:$T$17,0)) -> 5 | B26: =INDEX($A$5:$A$17,MATCH(LARGE($T$5:$T$17,5),$T$5:$T$17,0)) -> Juscimeira | C26: =INDEX($L$5:$L$17,MATCH(LARGE($T$5:$T$17,5),$T$5:$T$17,0)) -> -0.097402597 | D26: =INDEX($E$5:$E$17,MATCH(LARGE($T$5:$T$17,5),$T$5:$T$17,0)) -> 0.875 | E26: =INDEX($J$5:$J$17,MATCH(LARGE($T$5:$T$17,5),$T$5:$T$17,0)) -> 1 | F26: =INDEX($N$5:$N$17,MATCH(LARGE($T$5:$T$17,5),$T$5:$T$17,0)) -> Consolidado
A27: =INDEX($M$5:$M$17,MATCH(LARGE($T$5:$T$17,6),$T$5:$T$17,0)) -> 5 | B27: =INDEX($A$5:$A$17,MATCH(LARGE($T$5:$T$17,6),$T$5:$T$17,0)) -> Nossa Senhora do Livramento | C27: =INDEX($L$5:$L$17,MATCH(LARGE($T$5:$T$17,6),$T$5:$T$17,0)) -> -0.097402597 | D27: =INDEX($E$5:$E$17,MATCH(LARGE($T$5:$T$17,6),$T$5:$T$17,0)) -> 0.875 | E27: =INDEX($J$5:$J$17,MATCH(LARGE($T$5:$T$17,6),$T$5:$T$17,0)) -> 1 | F27: =INDEX($N$5:$N$17,MATCH(LARGE($T$5:$T$17,6),$T$5:$T$17,0)) -> Consolidado
A28: =INDEX($M$5:$M$17,MATCH(LARGE($T$5:$T$17,7),$T$5:$T$17,0)) -> 7 | B28: =INDEX($A$5:$A$17,MATCH(LARGE($T$5:$T$17,7),$T$5:$T$17,0)) -> Porto Esperidião | C28: =INDEX($L$5:$L$17,MATCH(LARGE($T$5:$T$17,7),$T$5:$T$17,0)) -> -0.25974026 | D28: =INDEX($E$5:$E$17,MATCH(LARGE($T$5:$T$17,7),$T$5:$T$17,0)) -> 0.875 | E28: =INDEX($J$5:$J$17,MATCH(LARGE($T$5:$T$17,7),$T$5:$T$17,0)) -> 1 | F28: =INDEX($N$5:$N$17,MATCH(LARGE($T$5:$T$17,7),$T$5:$T$17,0)) -> Consolidado
A29: =INDEX($M$5:$M$17,MATCH(LARGE($T$5:$T$17,8),$T$5:$T$17,0)) -> 8 | B29: =INDEX($A$5:$A$17,MATCH(LARGE($T$5:$T$17,8),$T$5:$T$17,0)) -> Barão de Melgaço | C29: =INDEX($L$5:$L$17,MATCH(LARGE($T$5:$T$17,8),$T$5:$T$17,0)) -> -0.29545455 | D29: =INDEX($E$5:$E$17,MATCH(LARGE($T$5:$T$17,8),$T$5:$T$17,0)) -> 0.875 | E29: =INDEX($J$5:$J$17,MATCH(LARGE($T$5:$T$17,8),$T$5:$T$17,0)) -> 1 | F29: =INDEX($N$5:$N$17,MATCH(LARGE($T$5:$T$17,8),$T$5:$T$17,0)) -> Consolidado
A30: =INDEX($M$5:$M$17,MATCH(LARGE($T$5:$T$17,9),$T$5:$T$17,0)) -> 8 | B30: =INDEX($A$5:$A$17,MATCH(LARGE($T$5:$T$17,9),$T$5:$T$17,0)) -> Curvelândia | C30: =INDEX($L$5:$L$17,MATCH(LARGE($T$5:$T$17,9),$T$5:$T$17,0)) -> -0.29545455 | D30: =INDEX($E$5:$E$17,MATCH(LARGE($T$5:$T$17,9),$T$5:$T$17,0)) -> 0.875 | E30: =INDEX($J$5:$J$17,MATCH(LARGE($T$5:$T$17,9),$T$5:$T$17,0)) -> 1 | F30: =INDEX($N$5:$N$17,MATCH(LARGE($T$5:$T$17,9),$T$5:$T$17,0)) -> Consolidado
A31: =INDEX($M$5:$M$17,MATCH(LARGE($T$5:$T$17,10),$T$5:$T$17,0)) -> 8 | B31: =INDEX($A$5:$A$17,MATCH(LARGE($T$5:$T$17,10),$T$5:$T$17,0)) -> Glória D'Oeste | C31: =INDEX($L$5:$L$17,MATCH(LARGE($T$5:$T$17,10),$T$5:$T$17,0)) -> -0.29545455 | D31: =INDEX($E$5:$E$17,MATCH(LARGE($T$5:$T$17,10),$T$5:$T$17,0)) -> 0.875 | E31: =INDEX($J$5:$J$17,MATCH(LARGE($T$5:$T$17,10),$T$5:$T$17,0)) -> 1 | F31: =INDEX($N$5:$N$17,MATCH(LARGE($T$5:$T$17,10),$T$5:$T$17,0)) -> Consolidado
A32: =INDEX($M$5:$M$17,MATCH(LARGE($T$5:$T$17,11),$T$5:$T$17,0)) -> 8 | B32: =INDEX($A$5:$A$17,MATCH(LARGE($T$5:$T$17,11),$T$5:$T$17,0)) -> Lambari D'Oeste | C32: =INDEX($L$5:$L$17,MATCH(LARGE($T$5:$T$17,11),$T$5:$T$17,0)) -> -0.29545455 | D32: =INDEX($E$5:$E$17,MATCH(LARGE($T$5:$T$17,11),$T$5:$T$17,0)) -> 0.875 | E32: =INDEX($J$5:$J$17,MATCH(LARGE($T$5:$T$17,11),$T$5:$T$17,0)) -> 1 | F32: =INDEX($N$5:$N$17,MATCH(LARGE($T$5:$T$17,11),$T$5:$T$17,0)) -> Consolidado
A33: =INDEX($M$5:$M$17,MATCH(LARGE($T$5:$T$17,12),$T$5:$T$17,0)) -> 12 | B33: =INDEX($A$5:$A$17,MATCH(LARGE($T$5:$T$17,12),$T$5:$T$17,0)) -> Santo Antônio do Leverger | C33: =INDEX($L$5:$L$17,MATCH(LARGE($T$5:$T$17,12),$T$5:$T$17,0)) -> -0.32142857 | D33: =INDEX($E$5:$E$17,MATCH(LARGE($T$5:$T$17,12),$T$5:$T$17,0)) -> 0.875 | E33: =INDEX($J$5:$J$17,MATCH(LARGE($T$5:$T$17,12),$T$5:$T$17,0)) -> 1 | F33: =INDEX($N$5:$N$17,MATCH(LARGE($T$5:$T$17,12),$T$5:$T$17,0)) -> Consolidado
A34: =INDEX($M$5:$M$17,MATCH(LARGE($T$5:$T$17,13),$T$5:$T$17,0)) -> 13 | B34: =INDEX($A$5:$A$17,MATCH(LARGE($T$5:$T$17,13),$T$5:$T$17,0)) -> Poconé | C34: =INDEX($L$5:$L$17,MATCH(LARGE($T$5:$T$17,13),$T$5:$T$17,0)) -> -0.35714286 | D34: =INDEX($E$5:$E$17,MATCH(LARGE($T$5:$T$17,13),$T$5:$T$17,0)) -> 0.875 | E34: =INDEX($J$5:$J$17,MATCH(LARGE($T$5:$T$17,13),$T$5:$T$17,0)) -> 1 | F34: =INDEX($N$5:$N$17,MATCH(LARGE($T$5:$T$17,13),$T$5:$T$17,0)) -> Consolidado
A36: Índice interno = (Forças − Fraquezas) ÷ indicadores com dado; varia de −1 a +1 e corrige municípios com mais lacunas. Índice externo = (Oportunidades − Ameaças) ÷ fatores pontuados. Índice SWOT = média dos dois (ou só o interno enquanto não houver fatores pontuados).
A37: Empates recebem a mesma posição. Todos os indicadores têm peso igual; definir pesos por área-chave é uma decisão a tomar com a coordenação.
A38: Atenção: pela regra atual, QL < 0,8 conta como Fraqueza, o que penaliza municípios especializados em outro setor (ex.: agropecuária em Rondonópolis). Revisar essa regra antes de consolidar o ranking.

Sheet Fontes e Notas
A1: FONTES, MÉTODO E VALIDAÇÃO DOS DADOS PREENCHIDOS
A3: Cód. | B3: Ano | C3: Fonte | D3: Cálculo | E3: Validação
A4: AGR-01 / IND-01 / CS-01 | B4: 2021 | C4: IBGE – PIB dos Municípios, SIDRA Tabela 5938 (VAB a preços correntes por atividade) | D4: QL = (VAB setor_mun / VAB total_mun) ÷ (VAB setor_MT / VAB total_MT). Base MT = soma dos 141 municípios. Serviços = exclusive administração pública. Participações MT 2021: agropecuária 37,98%; indústria 15,30%; serviços 34,84%; adm. pública 11,89%. | E4: Participações setoriais de Cáceres e Poconé conferem com fonte independente (Caravela, base IBGE 2021).
A5: EST-02 | B5: 2021 | C5: IBGE – PIB dos Municípios, SIDRA Tabela 5938 | D5: VAB da administração, defesa, educação e saúde públicas e seguridade social ÷ VAB total × 100. Ref. MT = 11,89%. | E5: Idem acima.
A6: EST-01 | B6: 2023 | C6: IBGE – PIB dos Municípios 2023; população do Censo 2022 | D6: Valores oficiais do portal IBGE Cidades e Estados. Para Cáceres e Rondonópolis: PIB 2023 ÷ população do Censo 2022 (mesmo método do IBGE). Ref. MT = R$ 74.620,05. | E6: O cálculo PIB 2023 ÷ Censo 2022 reproduz o valor oficial do IBGE em 9 municípios (diferença < R$ 0,10).
A8: LIMITAÇÃO IMPORTANTE | B8: O VAB setorial de 2022–2023 já foi divulgado pelo IBGE (dez/2025), mas não estava acessível no ambiente em que esta planilha foi preenchida. Os QLs e o EST-02 usam 2021 e devem ser atualizados pela Tabela 5938 do SIDRA (variáveis de VAB, anos 2022–2023). O PIB per capita (EST-01) já está em 2023.
A10: PENDENTES (2 indicadores)
A11: AGR-05 | B11: IBGE – PAM, SIDRA Tabela 5457 (valor da produção por produto). A base tratada d1_agropecuaria.csv traz só a diversificação do VBP entre lavoura, pecuária, extrativismo e pesca, que não mede a mesma coisa; por isso o indicador segue em branco.
A12: AGR-02, AGR-03 | B12: Preenchidos em 25/09/2026 (ver bloco "BASES TRATADAS" abaixo).
A13: AGR-04 | B13: IBGE – Censo Agropecuário 2017 (orientação técnica recebida)
A14: IND-02, IND-03, CS-02, EST-03, EST-04 | B14: Preenchidos em 25/09/2026 com d1_emprego_rais.csv (ver bloco "BASES TRATADAS" abaixo).
A15: CS-03 | B15: Preenchido em 25/09/2026 com d1_empresas.csv (CEMPRE 2021).
A16: EST-05 | B16: Preenchido em 25/09/2026 com d6_financas.csv (ver bloco "BASES TRATADAS" abaixo).
A18: RODADA DE 25/09/2026 — FATORES EXTERNOS (O-A)
A19: OP-01 a AM-05 | B19: Notas 0–3 atribuídas a partir de pesquisa web-based (evidências registradas na coluna E da aba 'Fatores Externos (O-A)'). Principais fontes: IBGE/PPM 2023 (rebanho de MT e Cáceres); Embrapa Pantanal, Comunicado Técnico 122; Corpo de Bombeiros-MT e INPE (área queimada 2024); Rumo/BNDES (Ferrovia Estadual); Portos e Navios e Gov. MT (Porto de Cáceres); NovaCana (Cooperb); EC 132/2023, LC 214/2025; IBGE/REGIC 2018.
A20: Status | B20: Notas preliminares de uma única rodada. Seguir o PASSO 3: revisar por consenso de dois pesquisadores e confrontar com a pesquisa de campo antes do Relatório Parcial.
A21: Indicadores internos pendentes | B21: Pendentes: AGR-04 (Censo Agro 2017, fora do catálogo) e AGR-05 (a base só tem diversificação entre lavoura, pecuária, extrativismo e pesca).
A23: RODADA DE 25/09/2026 — BASES TRATADAS (CATALOGO_BASES_TRATADAS, dimensão D1_PESM)
A24: Cód. | B24: Ano | C24: Fonte | D24: Cálculo | E24: Validação
A25: AGR-02 | B25: 2024 | C25: d1_agropecuaria.csv (IBGE – PAM): pam_valor_producao_brl (R$ mil) e pam_area_colhida_ha | D25: Valor da produção das lavouras × 1.000 ÷ área colhida (R$/ha). Ref. MT = soma dos 141 municípios = R$ 5.602,90/ha. | E25: Critério Razão MT (±10%). Nota: municípios pequenos com pouca área colhida (ex.: Barão de Melgaço, 354 ha) têm valor/ha alto e instável; conferir a composição das lavouras.
A26: AGR-03 | B26: 2019–2024 | C26: d1_agropecuaria.csv (IBGE – PPM): rebanho_bovino | D26: (Efetivo 2024 ÷ efetivo 2019 − 1) × 100. Ref. MT = +3,79% (31,65 → 32,85 milhões de cabeças). | E26: Total MT 2024 confere com o divulgado pelo IBGE (32,9 milhões). Critério Dif. MT (±2 p.p.).
A27: EST-01 | B27: 2023 | C27: painel_pantanal_norte.csv: pib ÷ populacao | D27: Conferência da planilha: pib (R$ mil) ÷ população reproduz os 13 valores já preenchidos. | E27: Sem alteração.
A28: Séries históricas | B28: 2000–2025 | C28: painel_pantanal_norte.csv, painel_municipios_mt.csv, d1_agropecuaria.csv | D28: Usadas nos gráficos de evolução da página (PIB per capita relativo a MT, composição do VAB, rebanho, valor/ha das lavouras, crédito rural, desmatamento). | E28: O VAB setorial das bases vai até 2021 e não inclui a administração pública; o PIB vai até 2023.
A29: IND-02 | B29: 2019–2024 | C29: d1_emprego_rais.csv (RAIS/MTE) | D29: Vínculos industriais = empregos_formais × participação de ind. alimentos, madeira/papel, outras indústrias e construção. Variação 2019–2024. Ref. MT = +36.92%. | E29: Bases muito pequenas em Barão de Melgaço, Glória D'Oeste, Itiquira e Porto Esperidião (menos de 100 vínculos em 2019): ver comentários nas células.
A30: IND-03 | B30: 2024 | C30: d1_emprego_rais.csv (RAIS/MTE) | D30: Média das remunerações nominais dos grupos industriais, ponderada pelos vínculos. Ref. MT = R$ 2956.72. | E30: Grupos sem remuneração informada foram excluídos da ponderação.
A31: CS-02 | B31: 2019–2024 | C31: d1_emprego_rais.csv (RAIS/MTE) | D31: Vínculos em comércio e serviços (exceto adm. pública). Variação 2019–2024. Ref. MT = +38.11%.
A32: CS-03 | B32: 2021 | C32: d1_empresas.csv (IBGE – CEMPRE) e população de painel_municipios_mt.csv | D32: Número de empresas ÷ população × 1.000. Ref. MT = 33.22. | E32: Confere com a coluna empresas_por_1000_hab da própria base.
A33: EST-03 | B33: 2024 | C33: d1_emprego_rais.csv e painel_municipios_mt.csv | D33: Empregos formais ÷ população × 100. Ref. MT = 31.51.
A34: EST-04 | B34: 2024 | C34: d1_emprego_rais.csv (RAIS/MTE) | D34: HHI = Σ s² das participações dos 16 grupos setoriais do emprego formal. Ref. MT = 0.1254. | E34: Os 16 grupos da base tratada aproximam as seções CNAE; o HHI é comparável entre municípios e MT porque usa o mesmo recorte.
A35: Conferência | B35: 2021 / 2023 | C35: d1_pib_vab.csv (IBGE – PIB dos Municípios) | D35: QLs (AGR-01, IND-01, CS-01) e EST-02 de 2021 recalculados com lq_agro, lq_ind, lq_serv e sh_adespss_va; participações setoriais de MT; vinculos_31dez 2023 comparado com a RAIS. | E35: Diferença máxima menor que 0,001 nos QLs e no EST-02; participações de MT idênticas às da aba Ranking Locacional; vínculos idênticos. O VAB setorial da base também termina em 2021, então a LIMITAÇÃO acima continua valendo.
A36: EST-05 | B36: 2022 | C36: d6_financas.csv (Siconfi/FINBRA), coluna autonomia_fiscal_pct | D36: Receita própria ÷ receita total × 100 (a base não traz a receita corrente). Ref. MT = Σ receita própria ÷ Σ receita total dos 141 municípios = 18.24%. | E36: O cálculo com receita_propria_real ÷ receita_total_real reproduz a coluna (diferença < 0,01 p.p.). Denominador diferente do previsto (receita total em vez de corrente): tratar como aproximação.

Sheet Parâmetros
A1: PARÂMETROS
A3: Banda relativa (critério 'Razão MT') | B3: 0.1 | C3: Proposta inicial; ajustar após validação.
A4: Banda em p.p. (critério 'Dif. MT (p.p.)') | B4: 2
A5: Corte de relevância dos fatores externos (0–3) | B5: 2 | C5: Fator entra no quadrante se intensidade ≥ corte.
A8: Municípios do Pantanal Norte (Plano de Trabalho)
A9: Barão de Melgaço
A10: Cáceres
A11: Curvelândia
A12: Glória D'Oeste
A13: Itiquira
A14: Juscimeira
A15: Lambari D'Oeste
A16: Mirassol D'Oeste
A17: Nossa Senhora do Livramento
A18: Poconé
A19: Porto Esperidião
... A21: Santo Antônio do Leverger

Sheet Indicadores (F-W)
A1: INDICADORES INTERNOS — FORÇAS E FRAQUEZAS DO PESM
A2: Entrada: fundo amarelo / texto azul. Classificação automática: Força | Neutro | Fraqueza.
A4: Cód. | B4: Área-chave | C4: Indicador | D4: Unidade | E4: Sentido | F4: Fonte sugerida | G4: Ano ref. | H4: Critério | I4: Valor ref. MT | J4: Lim. inf. (manual) | K4: Lim. sup. (manual) | L4: Lim. inf. (efetivo) | M4: Lim. sup. (efetivo) | N4: Barão de Melgaço | P4: Cáceres | R4: Curvelândia | T4: Glória D'Oeste | V4: Itiquira | X4: Juscimeira | Z4: Lambari D'Oeste | AB4: Mirassol D'Oeste | AD4: Nossa Senhora do Livramento | AF4: Poconé | AH4: Porto Esperidião | AJ4: Rondonópolis | AL4: Santo Antônio do Leverger
N5: Dado bruto | O5: Classificação | P5: Dado bruto | Q5: Classificação | R5: Dado bruto | S5: Classificação | T5: Dado bruto | U5: Classificação | V5: Dado bruto | W5: Classificação | X5: Dado bruto | Y5: Classificação | Z5: Dado bruto | AA5: Classificação | AB5: Dado bruto | AC5: Classificação | AD5: Dado bruto | AE5: Classificação | AF5: Dado bruto | AG5: Classificação | AH5: Dado bruto | AI5: Classificação | AJ5: Dado bruto | AK5: Classificação | AL5: Dado bruto | AM5: Classificação
A6: AGR-01 | B6: Agropecuária | C6: Quociente locacional do VAB agropecuário (base MT) | D6: índice | E6: + | F6: IBGE – PIB dos Municípios | G6: 2021 | H6: Absoluto | I6: 1 | J6: 0.8 | K6: 1.2 | L6: =IF($H6="Absoluto",IF($J6="","",$J6),IF($I6="","",IF($H6="Razão MT",MIN($I6*(1-Parâmetros!$B$3),$I6*(1+Parâmetros!$B$3)),$I6-Parâmetros!$B$4))) -> 0.8 | M6: =IF($H6="Absoluto",IF($K6="","",$K6),IF($I6="","",IF($H6="Razão MT",MAX($I6*(1-Parâmetros!$B$3),$I6*(1+Parâmetros!$B$3)),$I6+Parâmetros!$B$4))) -> 1.2 | N6: 0.9631 | O6: =IF(OR(N6="",$L6="",$M6=""),"",IF($E6="+",IF(N6>$M6,"Força",IF(N6<$L6,"Fraqueza","Neutro")),IF(N6<$L6,"Força",IF(N6>$M6,"Fraqueza","Neutro")))) -> Neutro | P6: 0.3713 | Q6: =IF(OR(P6="",$L6="",$M6=""),"",IF($E6="+",IF(P6>$M6,"Força",IF(P6<$L6,"Fraqueza","Neutro")),IF(P6<$L6,"Força",IF(P6>$M6,"Fraqueza","Neutro")))) -> Fraqueza | R6: 1.2022 | S6: =IF(OR(R6="",$L6="",$M6=""),"",IF($E6="+",IF(R6>$M6,"Força",IF(R6<$L6,"Fraqueza","Neutro")),IF(R6<$L6,"Força",IF(R6>$M6,"Fraqueza","Neutro")))) -> Força | T6: 1.3866 | U6: =IF(OR(T6="",$L6="",$M6=""),"",IF($E6="+",IF(T6>$M6,"Força",IF(T6<$L6,"Fraqueza","Neutro")),IF(T6<$L6,"Força",IF(T6>$M6,"Fraqueza","Neutro")))) -> Força | V6: 1.6266 | W6: =IF(OR(V6="",$L6="",$M6=""),"",IF($E6="+",IF(V6>$M6,"Força",IF(V6<$L6,"Fraqueza","Neutro")),IF(V6<$L6,"Força",IF(V6>$M6,"Fraqueza","Neutro")))) -> Força | X6: 1.319 | Y6: =IF(OR(X6="",$L6="",$M6=""),"",IF($E6="+",IF(X6>$M6,"Força",IF(X6<$L6,"Fraqueza","Neutro")),IF(X6<$L6,"Força",IF(X6>$M6,"Fraqueza","Neutro")))) -> Força | Z6: 1.364 | AA6: =IF(OR(Z6="",$L6="",$M6=""),"",IF($E6="+",IF(Z6>$M6,"Força",IF(Z6<$L6,"Fraqueza","Neutro")),IF(Z6<$L6,"Força",IF(Z6>$M6,"Fraqueza","Neutro")))) -> Força | AB6: 0.416 | AC6: =IF(OR(AB6="",$L6="",$M6=""),"",IF($E6="+",IF(AB6>$M6,"Força",IF(AB6<$L6,"Fraqueza","Neutro")),IF(AB6<$L6,"Força",IF(AB6>$M6,"Fraqueza","Neutro")))) -> Fraqueza | AD6: 0.5183 | AE6: =IF(OR(AD6="",$L6="",$M6=""),"",IF($E6="+",IF(AD6>$M6,"Força",IF(AD6<$L6,"Fraqueza","Neutro")),IF(AD6<$L6,"Força",IF(AD6>$M6,"Fraqueza","Neutro")))) -> Fraqueza | AF6: 0.5066 | AG6: =IF(OR(AF6="",$L6="",$M6=""),"",IF($E6="+",IF(AF6>$M6,"Força",IF(AF6<$L6,"Fraqueza","Neutro")),IF(AF6<$L6,"Força",IF(AF6>$M6,"Fraqueza","Neutro")))) -> Fraqueza | AH6: 1.0048 | AI6: =IF(OR(AH6="",$L6="",$M6=""),"",IF($E6="+",IF(AH6>$M6,"Força",IF(AH6<$L6,"Fraqueza","Neutro")),IF(AH6<$L6,"Força",IF(AH6>$M6,"Fraqueza","Neutro")))) -> Neutro | AJ6: 0.1067 | AK6: =IF(OR(AJ6="",$L6="",$M6=""),"",IF($E6="+",IF(AJ6>$M6,"Força",IF(AJ6<$L6,"Fraqueza","Neutro")),IF(AJ6<$L6,"Força",IF(AJ6>$M6,"Fraqueza","Neutro")))) -> Fraqueza | AL6: 1.714 | AM6: =IF(OR(AL6="",$L6="",$M6=""),"",IF($E6="+",IF(AL6>$M6,"Força",IF(AL6<$L6,"Fraqueza","Neutro")),IF(AL6<$L6,"Força",IF(AL6>$M6,"Fraqueza","Neutro")))) -> Força
A7: AGR-02 | B7: Agropecuária | C7: Valor da produção das lavouras por área colhida | D7: R$/ha | E7: + | F7: IBGE – PAM | G7: 2024 | H7: Razão MT | I7: 5602.9 | L7: =IF($H7="Absoluto",IF($J7="","",$J7),IF($I7="","",IF($H7="Razão MT",MIN($I7*(1-Parâmetros!$B$3),$I7*(1+Parâmetros!$B$3)),$I7-Parâmetros!$B$4))) -> 5042.61 | M7: =IF($H7="Absoluto",IF($K7="","",$K7),IF($I7="","",IF($H7="Razão MT",MAX($I7*(1-Parâmetros!$B$3),$I7*(1+Parâmetros!$B$3)),$I7+Parâmetros!$B$4))) -> 6163.19 | N7: 19926.55 | O7: =IF(OR(N7="",$L7="",$M7=""),"",IF($E7="+",IF(N7>$M7,"Força",IF(N7<$L7,"Fraqueza","Neutro")),IF(N7<$L7,"Força",IF(N7>$M7,"Fraqueza","Neutro")))) -> Força | P7: 5729.32 | Q7: =IF(OR(P7="",$L7="",$M7=""),"",IF($E7="+",IF(P7>$M7,"Força",IF(P7<$L7,"Fraqueza","Neutro")),IF(P7<$L7,"Força",IF(P7>$M7,"Fraqueza","Neutro")))) -> Neutro | R7: 10834.24 | S7: =IF(OR(R7="",$L7="",$M7=""),"",IF($E7="+",IF(R7>$M7,"Força",IF(R7<$L7,"Fraqueza","Neutro")),IF(R7<$L7,"Força",IF(R7>$M7,"Fraqueza","Neutro")))) -> Força | T7: 10020.12 | U7: =IF(OR(T7="",$L7="",$M7=""),"",IF($E7="+",IF(T7>$M7,"Força",IF(T7<$L7,"Fraqueza","Neutro")),IF(T7<$L7,"Força",IF(T7>$M7,"Fraqueza","Neutro")))) -> Força | V7: 5402.93 | W7: =IF(OR(V7="",$L7="",$M7=""),"",IF($E7="+",IF(V7>$M7,"Força",IF(V7<$L7,"Fraqueza","Neutro")),IF(V7<$L7,"Força",IF(V7>$M7,"Fraqueza","Neutro")))) -> Neutro | X7: 5889.67 | Y7: =IF(OR(X7="",$L7="",$M7=""),"",IF($E7="+",IF(X7>$M7,"Força",IF(X7<$L7,"Fraqueza","Neutro")),IF(X7<$L7,"Força",IF(X7>$M7,"Fraqueza","Neutro")))) -> Neutro | Z7: 9903.13 | AA7: =IF(OR(Z7="",$L7="",$M7=""),"",IF($E7="+",IF(Z7>$M7,"Força",IF(Z7<$L7,"Fraqueza","Neutro")),IF(Z7<$L7,"Força",IF(Z7>$M7,"Fraqueza","Neutro")))) -> Força | AB7: 10166.09 | AC7: =IF(OR(AB7="",$L7="",$M7=""),"",IF($E7="+",IF(AB7>$M7,"Força",IF(AB7<$L7,"Fraqueza","Neutro")),IF(AB7<$L7,"Força",IF(AB7>$M7,"Fraqueza","Neutro")))) -> Força | AD7: 5734.66 | AE7: =IF(OR(AD7="",$L7="",$M7=""),"",IF($E7="+",IF(AD7>$M7,"Força",IF(AD7<$L7,"Fraqueza","Neutro")),IF(AD7<$L7,"Força",IF(AD7>$M7,"Fraqueza","Neutro")))) -> Neutro | AF7: 5045 | AG7: =IF(OR(AF7="",$L7="",$M7=""),"",IF($E7="+",IF(AF7>$M7,"Força",IF(AF7<$L7,"Fraqueza","Neutro")),IF(AF7<$L7,"Força",IF(AF7>$M7,"Fraqueza","Neutro")))) -> Neutro | AH7: 6552.04 | AI7: =IF(OR(AH7="",$L7="",$M7=""),"",IF($E7="+",IF(AH7>$M7,"Força",IF(AH7<$L7,"Fraqueza","Neutro")),IF(AH7<$L7,"Força",IF(AH7>$M7,"Fraqueza","Neutro")))) -> Força | AJ7: 5354.94 | AK7: =IF(OR(AJ7="",$L7="",$M7=""),"",IF($E7="+",IF(AJ7>$M7,"Força",IF(AJ7<$L7,"Fraqueza","Neutro")),IF(AJ7<$L7,"Força",IF(AJ7>$M7,"Fraqueza","Neutro")))) -> Neutro | AL7: 4958.82 | AM7: =IF(OR(AL7="",$L7="",$M7=""),"",IF($E7="+",IF(AL7>$M7,"Força",IF(AL7<$L7,"Fraqueza","Neutro")),IF(AL7<$L7,"Força",IF(AL7>$M7,"Fraqueza","Neutro")))) -> Fraqueza
A8: AGR-03 | B8: Agropecuária | C8: Variação do efetivo bovino em 5 anos | D8: % | E8: + | F8: IBGE – PPM | G8: 2024 | H8: Dif. MT (p.p.) | I8: 3.79 | L8: =IF($H8="Absoluto",IF($J8="","",$J8),IF($I8="","",IF($H8="Razão MT",MIN($I8*(1-Parâmetros!$B$3),$I8*(1+Parâmetros!$B$3)),$I8-Parâmetros!$B$4))) -> 1.79 | M8: =IF($H8="Absoluto",IF($K8="","",$K8),IF($I8="","",IF($H8="Razão MT",MAX($I8*(1-Parâmetros!$B$3),$I8*(1+Parâmetros!$B$3)),$I8+Parâmetros!$B$4))) -> 5.79 | N8: 16.6 | O8: =IF(OR(N8="",$L8="",$M8=""),"",IF($E8="+",IF(N8>$M8,"Força",IF(N8<$L8,"Fraqueza","Neutro")),IF(N8<$L8,"Força",IF(N8>$M8,"Fraqueza","Neutro")))) -> Força | P8: 22.65 | Q8: =IF(OR(P8="",$L8="",$M8=""),"",IF($E8="+",IF(P8>$M8,"Força",IF(P8<$L8,"Fraqueza","Neutro")),IF(P8<$L8,"Força",IF(P8>$M8,"Fraqueza","Neutro")))) -> Força | R8: 2.73 | S8: =IF(OR(R8="",$L8="",$M8=""),"",IF($E8="+",IF(R8>$M8,"Força",IF(R8<$L8,"Fraqueza","Neutro")),IF(R8<$L8,"Força",IF(R8>$M8,"Fraqueza","Neutro")))) -> Neutro | T8: 2.27 | U8: =IF(OR(T8="",$L8="",$M8=""),"",IF($E8="+",IF(T8>$M8,"Força",IF(T8<$L8,"Fraqueza","Neutro")),IF(T8<$L8,"Força",IF(T8>$M8,"Fraqueza","Neutro")))) -> Neutro | V8: 26.4 | W8: =IF(OR(V8="",$L8="",$M8=""),"",IF($E8="+",IF(V8>$M8,"Força",IF(V8<$L8,"Fraqueza","Neutro")),IF(V8<$L8,"Força",IF(V8>$M8,"Fraqueza","Neutro")))) -> Força | X8: 1.8 | Y8: =IF(OR(X8="",$L8="",$M8=""),"",IF($E8="+",IF(X8>$M8,"Força",IF(X8<$L8,"Fraqueza","Neutro")),IF(X8<$L8,"Força",IF(X8>$M8,"Fraqueza","Neutro")))) -> Neutro | Z8: -2.74 | AA8: =IF(OR(Z8="",$L8="",$M8=""),"",IF($E8="+",IF(Z8>$M8,"Força",IF(Z8<$L8,"Fraqueza","Neutro")),IF(Z8<$L8,"Força",IF(Z8>$M8,"Fraqueza","Neutro")))) -> Fraqueza | AB8: -2.58 | AC8: =IF(OR(AB8="",$L8="",$M8=""),"",IF($E8="+",IF(AB8>$M8,"Força",IF(AB8<$L8,"Fraqueza","Neutro")),IF(AB8<$L8,"Força",IF(AB8>$M8,"Fraqueza","Neutro")))) -> Fraqueza | AD8: 23.81 | AE8: =IF(OR(AD8="",$L8="",$M8=""),"",IF($E8="+",IF(AD8>$M8,"Força",IF(AD8<$L8,"Fraqueza","Neutro")),IF(AD8<$L8,"Força",IF(AD8>$M8,"Fraqueza","Neutro")))) -> Força | AF8: 16.79 | AG8: =IF(OR(AF8="",$L8="",$M8=""),"",IF($E8="+",IF(AF8>$M8,"Força",IF(AF8<$L8,"Fraqueza","Neutro")),IF(AF8<$L8,"Força",IF(AF8>$M8,"Fraqueza","Neutro")))) -> Força | AH8: 8.4 | AI8: =IF(OR(AH8="",$L8="",$M8=""),"",IF($E8="+",IF(AH8>$M8,"Força",IF(AH8<$L8,"Fraqueza","Neutro")),IF(AH8<$L8,"Força",IF(AH8>$M8,"Fraqueza","Neutro")))) -> Força | AJ8: 0.39 | AK8: =IF(OR(AJ8="",$L8="",$M8=""),"",IF($E8="+",IF(AJ8>$M8,"Força",IF(AJ8<$L8,"Fraqueza","Neutro")),IF(AJ8<$L8,"Força",IF(AJ8>$M8,"Fraqueza","Neutro")))) -> Fraqueza | AL8: 4.74 | AM8: =IF(OR(AL8="",$L8="",$M8=""),"",IF($E8="+",IF(AL8>$M8,"Força",IF(AL8<$L8,"Fraqueza","Neutro")),IF(AL8<$L8,"Força",IF(AL8>$M8,"Fraqueza","Neutro")))) -> Neutro
A9: AGR-04 | B9: Agropecuária | C9: Estabelecimentos agropecuários que receberam assistência técnica | D9: % | E9: + | F9: IBGE – Censo Agropecuário 2017 | H9: Dif. MT (p.p.) | L9: =IF($H9="Absoluto",IF($J9="","",$J9),IF($I9="","",IF($H9="Razão MT",MIN($I9*(1-Parâmetros!$B$3),$I9*(1+Parâmetros!$B$3)),$I9-Parâmetros!$B$4))) | M9: =IF($H9="Absoluto",IF($K9="","",$K9),IF($I9="","",IF($H9="Razão MT",MAX($I9*(1-Parâmetros!$B$3),$I9*(1+Parâmetros!$B$3)),$I9+Parâmetros!$B$4))) | O9: =IF(OR(N9="",$L9="",$M9=""),"",IF($E9="+",IF(N9>$M9,"Força",IF(N9<$L9,"Fraqueza","Neutro")),IF(N9<$L9,"Força",IF(N9>$M9,"Fraqueza","Neutro")))) | Q9: =IF(OR(P9="",$L9="",$M9=""),"",IF($E9="+",IF(P9>$M9,"Força",IF(P9<$L9,"Fraqueza","Neutro")),IF(P9<$L9,"Força",IF(P9>$M9,"Fraqueza","Neutro")))) | S9: =IF(OR(R9="",$L9="",$M9=""),"",IF($E9="+",IF(R9>$M9,"Força",IF(R9<$L9,"Fraqueza","Neutro")),IF(R9<$L9,"Força",IF(R9>$M9,"Fraqueza","Neutro")))) | U9: =IF(OR(T9="",$L9="",$M9=""),"",IF($E9="+",IF(T9>$M9,"Força",IF(T9<$L9,"Fraqueza","Neutro")),IF(T9<$L9,"Força",IF(T9>$M9,"Fraqueza","Neutro")))) | W9: =IF(OR(V9="",$L9="",$M9=""),"",IF($E9="+",IF(V9>$M9,"Força",IF(V9<$L9,"Fraqueza","Neutro")),IF(V9<$L9,"Força",IF(V9>$M9,"Fraqueza","Neutro")))) | Y9: =IF(OR(X9="",$L9="",$M9=""),"",IF($E9="+",IF(X9>$M9,"Força",IF(X9<$L9,"Fraqueza","Neutro")),IF(X9<$L9,"Força",IF(X9>$M9,"Fraqueza","Neutro")))) | AA9: =IF(OR(Z9="",$L9="",$M9=""),"",IF($E9="+",IF(Z9>$M9,"Força",IF(Z9<$L9,"Fraqueza","Neutro")),IF(Z9<$L9,"Força",IF(Z9>$M9,"Fraqueza","Neutro")))) | AC9: =IF(OR(AB9="",$L9="",$M9=""),"",IF($E9="+",IF(AB9>$M9,"Força",IF(AB9<$L9,"Fraqueza","Neutro")),IF(AB9<$L9,"Força",IF(AB9>$M9,"Fraqueza","Neutro")))) | AE9: =IF(OR(AD9="",$L9="",$M9=""),"",IF($E9="+",IF(AD9>$M9,"Força",IF(AD9<$L9,"Fraqueza","Neutro")),IF(AD9<$L9,"Força",IF(AD9>$M9,"Fraqueza","Neutro")))) | AG9: =IF(OR(AF9="",$L9="",$M9=""),"",IF($E9="+",IF(AF9>$M9,"Força",IF(AF9<$L9,"Fraqueza","Neutro")),IF(AF9<$L9,"Força",IF(AF9>$M9,"Fraqueza","Neutro")))) | AI9: =IF(OR(AH9="",$L9="",$M9=""),"",IF($E9="+",IF(AH9>$M9,"Força",IF(AH9<$L9,"Fraqueza","Neutro")),IF(AH9<$L9,"Força",IF(AH9>$M9,"Fraqueza","Neutro")))) | AK9: =IF(OR(AJ9="",$L9="",$M9=""),"",IF($E9="+",IF(AJ9>$M9,"Força",IF(AJ9<$L9,"Fraqueza","Neutro")),IF(AJ9<$L9,"Força",IF(AJ9>$M9,"Fraqueza","Neutro")))) | AM9: =IF(OR(AL9="",$L9="",$M9=""),"",IF($E9="+",IF(AL9>$M9,"Força",IF(AL9<$L9,"Fraqueza","Neutro")),IF(AL9<$L9,"Força",IF(AL9>$M9,"Fraqueza","Neutro"))))
A10: AGR-05 | B10: Agropecuária | C10: Diversificação agrícola (1 − HHI do valor da produção das lavouras) | D10: índice 0–1 | E10: + | F10: Calculado a partir da PAM | H10: Razão MT | L10: =IF($H10="Absoluto",IF($J10="","",$J10),IF($I10="","",IF($H10="Razão MT",MIN($I10*(1-Parâmetros!$B$3),$I10*(1+Parâmetros!$B$3)),$I10-Parâmetros!$B$4))) | M10: =IF($H10="Absoluto",IF($K10="","",$K10),IF($I10="","",IF($H10="Razão MT",MAX($I10*(1-Parâmetros!$B$3),$I10*(1+Parâmetros!$B$3)),$I10+Parâmetros!$B$4))) | O10: =IF(OR(N10="",$L10="",$M10=""),"",IF($E10="+",IF(N10>$M10,"Força",IF(N10<$L10,"Fraqueza","Neutro")),IF(N10<$L10,"Força",IF(N10>$M10,"Fraqueza","Neutro")))) | Q10: =IF(OR(P10="",$L10="",$M10=""),"",IF($E10="+",IF(P10>$M10,"Força",IF(P10<$L10,"Fraqueza","Neutro")),IF(P10<$L10,"Força",IF(P10>$M10,"Fraqueza","Neutro")))) | S10: =IF(OR(R10="",$L10="",$M10=""),"",IF($E10="+",IF(R10>$M10,"Força",IF(R10<$L10,"Fraqueza","Neutro")),IF(R10<$L10,"Força",IF(R10>$M10,"Fraqueza","Neutro")))) | U10: =IF(OR(T10="",$L10="",$M10=""),"",IF($E10="+",IF(T10>$M10,"Força",IF(T10<$L10,"Fraqueza","Neutro")),IF(T10<$L10,"Força",IF(T10>$M10,"Fraqueza","Neutro")))) | W10: =IF(OR(V10="",$L10="",$M10=""),"",IF($E10="+",IF(V10>$M10,"Força",IF(V10<$L10,"Fraqueza","Neutro")),IF(V10<$L10,"Força",IF(V10>$M10,"Fraqueza","Neutro")))) | Y10: =IF(OR(X10="",$L10="",$M10=""),"",IF($E10="+",IF(X10>$M10,"Força",IF(X10<$L10,"Fraqueza","Neutro")),IF(X10<$L10,"Força",IF(X10>$M10,"Fraqueza","Neutro")))) | AA10: =IF(OR(Z10="",$L10="",$M10=""),"",IF($E10="+",IF(Z10>$M10,"Força",IF(Z10<$L10,"Fraqueza","Neutro")),IF(Z10<$L10,"Força",IF(Z10>$M10,"Fraqueza","Neutro")))) | AC10: =IF(OR(AB10="",$L10="",$M10=""),"",IF($E10="+",IF(AB10>$M10,"Força",IF(AB10<$L10,"Fraqueza","Neutro")),IF(AB10<$L10,"Força",IF(AB10>$M10,"Fraqueza","Neutro")))) | AE10: =IF(OR(AD10="",$L10="",$M10=""),"",IF($E10="+",IF(AD10>$M10,"Força",IF(AD10<$L10,"Fraqueza","Neutro")),IF(AD10<$L10,"Força",IF(AD10>$M10,"Fraqueza","Neutro")))) | AG10: =IF(OR(AF10="",$L10="",$M10=""),"",IF($E10="+",IF(AF10>$M10,"Força",IF(AF10<$L10,"Fraqueza","Neutro")),IF(AF10<$L10,"Força",IF(AF10>$M10,"Fraqueza","Neutro")))) | AI10: =IF(OR(AH10="",$L10="",$M10=""),"",IF($E10="+",IF(AH10>$M10,"Força",IF(AH10<$L10,"Fraqueza","Neutro")),IF(AH10<$L10,"Força",IF(AH10>$M10,"Fraqueza","Neutro")))) | AK10: =IF(OR(AJ10="",$L10="",$M10=""),"",IF($E10="+",IF(AJ10>$M10,"Força",IF(AJ10<$L10,"Fraqueza","Neutro")),IF(AJ10<$L10,"Força",IF(AJ10>$M10,"Fraqueza","Neutro")))) | AM10: =IF(OR(AL10="",$L10="",$M10=""),"",IF($E10="+",IF(AL10>$M10,"Força",IF(AL10<$L10,"Fraqueza","Neutro")),IF(AL10<$L10,"Força",IF(AL10>$M10,"Fraqueza","Neutro"))))
A11: IND-01 | B11: Indústria | C11: Quociente locacional do VAB industrial (base MT) | D11: índice | E11: + | F11: IBGE – PIB dos Municípios | G11: 2021 | H11: Absoluto | I11: 1 | J11: 0.8 | K11: 1.2 | L11: =IF($H11="Absoluto",IF($J11="","",$J11),IF($I11="","",IF($H11="Razão MT",MIN($I11*(1-Parâmetros!$B$3),$I11*(1+Parâmetros!$B$3)),$I11-Parâmetros!$B$4))) -> 0.8 | M11: =IF($H11="Absoluto",IF($K11="","",$K11),IF($I11="","",IF($H11="Razão MT",MAX($I11*(1-Parâmetros!$B$3),$I11*(1+Parâmetros!$B$3)),$I11+Parâmetros!$B$4))) -> 1.2 | N11: 0.169 | O11: =IF(OR(N11="",$L11="",$M11=""),"",IF($E11="+",IF(N11>$M11,"Força",IF(N11<$L11,"Fraqueza","Neutro")),IF(N11<$L11,"Força",IF(N11>$M11,"Fraqueza","Neutro")))) -> Fraqueza | P11: 0.6374 | Q11: =IF(OR(P11="",$L11="",$M11=""),"",IF($E11="+",IF(P11>$M11,"Força",IF(P11<$L11,"Fraqueza","Neutro")),IF(P11<$L11,"Força",IF(P11>$M11,"Fraqueza","Neutro")))) -> Fraqueza | R11: 0.4717 | S11: =IF(OR(R11="",$L11="",$M11=""),"",IF($E11="+",IF(R11>$M11,"Força",IF(R11<$L11,"Fraqueza","Neutro")),IF(R11<$L11,"Força",IF(R11>$M11,"Fraqueza","Neutro")))) -> Fraqueza | T11: 0.2854 | U11: =IF(OR(T11="",$L11="",$M11=""),"",IF($E11="+",IF(T11>$M11,"Força",IF(T11<$L11,"Fraqueza","Neutro")),IF(T11<$L11,"Força",IF(T11>$M11,"Fraqueza","Neutro")))) -> Fraqueza | V11: 1.2891 | W11: =IF(OR(V11="",$L11="",$M11=""),"",IF($E11="+",IF(V11>$M11,"Força",IF(V11<$L11,"Fraqueza","Neutro")),IF(V11<$L11,"Força",IF(V11>$M11,"Fraqueza","Neutro")))) -> Força | X11: 1.1671 | Y11: =IF(OR(X11="",$L11="",$M11=""),"",IF($E11="+",IF(X11>$M11,"Força",IF(X11<$L11,"Fraqueza","Neutro")),IF(X11<$L11,"Força",IF(X11>$M11,"Fraqueza","Neutro")))) -> Neutro | Z11: 1.1956 | AA11: =IF(OR(Z11="",$L11="",$M11=""),"",IF($E11="+",IF(Z11>$M11,"Força",IF(Z11<$L11,"Fraqueza","Neutro")),IF(Z11<$L11,"Força",IF(Z11>$M11,"Fraqueza","Neutro")))) -> Neutro | AB11: 1.2112 | AC11: =IF(OR(AB11="",$L11="",$M11=""),"",IF($E11="+",IF(AB11>$M11,"Força",IF(AB11<$L11,"Fraqueza","Neutro")),IF(AB11<$L11,"Força",IF(AB11>$M11,"Fraqueza","Neutro")))) -> Força | AD11: 2.0033 | AE11: =IF(OR(AD11="",$L11="",$M11=""),"",IF($E11="+",IF(AD11>$M11,"Força",IF(AD11<$L11,"Fraqueza","Neutro")),IF(AD11<$L11,"Força",IF(AD11>$M11,"Fraqueza","Neutro")))) -> Força | AF11: 0.5947 | AG11: =IF(OR(AF11="",$L11="",$M11=""),"",IF($E11="+",IF(AF11>$M11,"Força",IF(AF11<$L11,"Fraqueza","Neutro")),IF(AF11<$L11,"Força",IF(AF11>$M11,"Fraqueza","Neutro")))) -> Fraqueza | AH11: 1.0107 | AI11: =IF(OR(AH11="",$L11="",$M11=""),"",IF($E11="+",IF(AH11>$M11,"Força",IF(AH11<$L11,"Fraqueza","Neutro")),IF(AH11<$L11,"Força",IF(AH11>$M11,"Fraqueza","Neutro")))) -> Neutro | AJ11: 1.8691 | AK11: =IF(OR(AJ11="",$L11="",$M11=""),"",IF($E11="+",IF(AJ11>$M11,"Força",IF(AJ11<$L11,"Fraqueza","Neutro")),IF(AJ11<$L11,"Força",IF(AJ11>$M11,"Fraqueza","Neutro")))) -> Força | AL11: 0.4719 | AM11: =IF(OR(AL11="",$L11="",$M11=""),"",IF($E11="+",IF(AL11>$M11,"Força",IF(AL11<$L11,"Fraqueza","Neutro")),IF(AL11<$L11,"Força",IF(AL11>$M11,"Fraqueza","Neutro")))) -> Fraqueza
A12: IND-02 | B12: Indústria | C12: Variação do emprego formal na indústria em 5 anos | D12: % | E12: + | F12: RAIS (MTE) | G12: 2024 | H12: Dif. MT (p.p.) | I12: 36.92 | L12: =IF($H12="Absoluto",IF($J12="","",$J12),IF($I12="","",IF($H12="Razão MT",MIN($I12*(1-Parâmetros!$B$3),$I12*(1+Parâmetros!$B$3)),$I12-Parâmetros!$B$4))) -> 34.92 | M12: =IF($H12="Absoluto",IF($K12="","",$K12),IF($I12="","",IF($H12="Razão MT",MAX($I12*(1-Parâmetros!$B$3),$I12*(1+Parâmetros!$B$3)),$I12+Parâmetros!$B$4))) -> 38.92 | N12: 2299.57 | O12: =IF(OR(N12="",$L12="",$M12=""),"",IF($E12="+",IF(N12>$M12,"Força",IF(N12<$L12,"Fraqueza","Neutro")),IF(N12<$L12,"Força",IF(N12>$M12,"Fraqueza","Neutro")))) -> Força | P12: 58.91 | Q12: =IF(OR(P12="",$L12="",$M12=""),"",IF($E12="+",IF(P12>$M12,"Força",IF(P12<$L12,"Fraqueza","Neutro")),IF(P12<$L12,"Força",IF(P12>$M12,"Fraqueza","Neutro")))) -> Força | R12: -45.74 | S12: =IF(OR(R12="",$L12="",$M12=""),"",IF($E12="+",IF(R12>$M12,"Força",IF(R12<$L12,"Fraqueza","Neutro")),IF(R12<$L12,"Força",IF(R12>$M12,"Fraqueza","Neutro")))) -> Fraqueza | T12: 150 | U12: =IF(OR(T12="",$L12="",$M12=""),"",IF($E12="+",IF(T12>$M12,"Força",IF(T12<$L12,"Fraqueza","Neutro")),IF(T12<$L12,"Força",IF(T12>$M12,"Fraqueza","Neutro")))) -> Força | V12: 123.51 | W12: =IF(OR(V12="",$L12="",$M12=""),"",IF($E12="+",IF(V12>$M12,"Força",IF(V12<$L12,"Fraqueza","Neutro")),IF(V12<$L12,"Força",IF(V12>$M12,"Fraqueza","Neutro")))) -> Força | X12: 107.6 | Y12: =IF(OR(X12="",$L12="",$M12=""),"",IF($E12="+",IF(X12>$M12,"Força",IF(X12<$L12,"Fraqueza","Neutro")),IF(X12<$L12,"Força",IF(X12>$M12,"Fraqueza","Neutro")))) -> Força | Z12: 17.39 | AA12: =IF(OR(Z12="",$L12="",$M12=""),"",IF($E12="+",IF(Z12>$M12,"Força",IF(Z12<$L12,"Fraqueza","Neutro")),IF(Z12<$L12,"Força",IF(Z12>$M12,"Fraqueza","Neutro")))) -> Fraqueza | AB12: 1.57 | AC12: =IF(OR(AB12="",$L12="",$M12=""),"",IF($E12="+",IF(AB12>$M12,"Força",IF(AB12<$L12,"Fraqueza","Neutro")),IF(AB12<$L12,"Força",IF(AB12>$M12,"Fraqueza","Neutro")))) -> Fraqueza | AD12: 64.63 | AE12: =IF(OR(AD12="",$L12="",$M12=""),"",IF($E12="+",IF(AD12>$M12,"Força",IF(AD12<$L12,"Fraqueza","Neutro")),IF(AD12<$L12,"Força",IF(AD12>$M12,"Fraqueza","Neutro")))) -> Força | AF12: 31.45 | AG12: =IF(OR(AF12="",$L12="",$M12=""),"",IF($E12="+",IF(AF12>$M12,"Força",IF(AF12<$L12,"Fraqueza","Neutro")),IF(AF12<$L12,"Força",IF(AF12>$M12,"Fraqueza","Neutro")))) -> Fraqueza | AH12: 633.3 | AI12: =IF(OR(AH12="",$L12="",$M12=""),"",IF($E12="+",IF(AH12>$M12,"Força",IF(AH12<$L12,"Fraqueza","Neutro")),IF(AH12<$L12,"Força",IF(AH12>$M12,"Fraqueza","Neutro")))) -> Força | AJ12: 30.12 | AK12: =IF(OR(AJ12="",$L12="",$M12=""),"",IF($E12="+",IF(AJ12>$M12,"Força",IF(AJ12<$L12,"Fraqueza","Neutro")),IF(AJ12<$L12,"Força",IF(AJ12>$M12,"Fraqueza","Neutro")))) -> Fraqueza | AL12: 100 | AM12: =IF(OR(AL12="",$L12="",$M12=""),"",IF($E12="+",IF(AL12>$M12,"Força",IF(AL12<$L12,"Fraqueza","Neutro")),IF(AL12<$L12,"Força",IF(AL12>$M12,"Fraqueza","Neutro")))) -> Força
A13: IND-03 | B13: Indústria | C13: Remuneração média do emprego formal industrial | D13: R$ | E13: + | F13: RAIS (MTE) | G13: 2024 | H13: Razão MT | I13: 2956.72 | L13: =IF($H13="Absoluto",IF($J13="","",$J13),IF($I13="","",IF($H13="Razão MT",MIN($I13*(1-Parâmetros!$B$3),$I13*(1+Parâmetros!$B$3)),$I13-Parâmetros!$B$4))) -> 2661.048 | M13: =IF($H13="Absoluto",IF($K13="","",$K13),IF($I13="","",IF($H13="Razão MT",MAX($I13*(1-Parâmetros!$B$3),$I13*(1+Parâmetros!$B$3)),$I13+Parâmetros!$B$4))) -> 3252.392 | N13: 2624.01 | O13: =IF(OR(N13="",$L13="",$M13=""),"",IF($E13="+",IF(N13>$M13,"Força",IF(N13<$L13,"Fraqueza","Neutro")),IF(N13<$L13,"Força",IF(N13>$M13,"Fraqueza","Neutro")))) -> Fraqueza | P13: 2345.65 | Q13: =IF(OR(P13="",$L13="",$M13=""),"",IF($E13="+",IF(P13>$M13,"Força",IF(P13<$L13,"Fraqueza","Neutro")),IF(P13<$L13,"Força",IF(P13>$M13,"Fraqueza","Neutro")))) -> Fraqueza | R13: 1956.93 | S13: =IF(OR(R13="",$L13="",$M13=""),"",IF($E13="+",IF(R13>$M13,"Força",IF(R13<$L13,"Fraqueza","Neutro")),IF(R13<$L13,"Força",IF(R13>$M13,"Fraqueza","Neutro")))) -> Fraqueza | T13: 2190.43 | U13: =IF(OR(T13="",$L13="",$M13=""),"",IF($E13="+",IF(T13>$M13,"Força",IF(T13<$L13,"Fraqueza","Neutro")),IF(T13<$L13,"Força",IF(T13>$M13,"Fraqueza","Neutro")))) -> Fraqueza | V13: 1503.38 | W13: =IF(OR(V13="",$L13="",$M13=""),"",IF($E13="+",IF(V13>$M13,"Força",IF(V13<$L13,"Fraqueza","Neutro")),IF(V13<$L13,"Força",IF(V13>$M13,"Fraqueza","Neutro")))) -> Fraqueza | X13: 3141.45 | Y13: =IF(OR(X13="",$L13="",$M13=""),"",IF($E13="+",IF(X13>$M13,"Força",IF(X13<$L13,"Fraqueza","Neutro")),IF(X13<$L13,"Força",IF(X13>$M13,"Fraqueza","Neutro")))) -> Neutro | Z13: 3096.65 | AA13: =IF(OR(Z13="",$L13="",$M13=""),"",IF($E13="+",IF(Z13>$M13,"Força",IF(Z13<$L13,"Fraqueza","Neutro")),IF(Z13<$L13,"Força",IF(Z13>$M13,"Fraqueza","Neutro")))) -> Neutro | AB13: 2809.72 | AC13: =IF(OR(AB13="",$L13="",$M13=""),"",IF($E13="+",IF(AB13>$M13,"Força",IF(AB13<$L13,"Fraqueza","Neutro")),IF(AB13<$L13,"Força",IF(AB13>$M13,"Fraqueza","Neutro")))) -> Neutro | AD13: 2895.19 | AE13: =IF(OR(AD13="",$L13="",$M13=""),"",IF($E13="+",IF(AD13>$M13,"Força",IF(AD13<$L13,"Fraqueza","Neutro")),IF(AD13<$L13,"Força",IF(AD13>$M13,"Fraqueza","Neutro")))) -> Neutro | AF13: 2150.35 | AG13: =IF(OR(AF13="",$L13="",$M13=""),"",IF($E13="+",IF(AF13>$M13,"Força",IF(AF13<$L13,"Fraqueza","Neutro")),IF(AF13<$L13,"Força",IF(AF13>$M13,"Fraqueza","Neutro")))) -> Fraqueza | AH13: 1432.11 | AI13: =IF(OR(AH13="",$L13="",$M13=""),"",IF($E13="+",IF(AH13>$M13,"Força",IF(AH13<$L13,"Fraqueza","Neutro")),IF(AH13<$L13,"Força",IF(AH13>$M13,"Fraqueza","Neutro")))) -> Fraqueza | AJ13: 2903.68 | AK13: =IF(OR(AJ13="",$L13="",$M13=""),"",IF($E13="+",IF(AJ13>$M13,"Força",IF(AJ13<$L13,"Fraqueza","Neutro")),IF(AJ13<$L13,"Força",IF(AJ13>$M13,"Fraqueza","Neutro")))) -> Neutro | AL13: 2394.42 | AM13: =IF(OR(AL13="",$L13="",$M13=""),"",IF($E13="+",IF(AL13>$M13,"Força",IF(AL13<$L13,"Fraqueza","Neutro")),IF(AL13<$L13,"Força",IF(AL13>$M13,"Fraqueza","Neutro")))) -> Fraqueza
A14: CS-01 | B14: Comércio e Serviços | C14: Quociente locacional do VAB de serviços, exceto adm. pública (base MT) | D14: índice | E14: + | F14: IBGE – PIB dos Municípios | G14: 2021 | H14: Absoluto | I14: 1 | J14: 0.8 | K14: 1.2 | L14: =IF($H14="Absoluto",IF($J14="","",$J14),IF($I14="","",IF($H14="Razão MT",MIN($I14*(1-Parâmetros!$B$3),$I14*(1+Parâmetros!$B$3)),$I14-Parâmetros!$B$4))) -> 0.8 | M14: =IF($H14="Absoluto",IF($K14="","",$K14),IF($I14="","",IF($H14="Razão MT",MAX($I14*(1-Parâmetros!$B$3),$I14*(1+Parâmetros!$B$3)),$I14+Parâmetros!$B$4))) -> 1.2 | N14: 0.4274 | O14: =IF(OR(N14="",$L14="",$M14=""),"",IF($E14="+",IF(N14>$M14,"Força",IF(N14<$L14,"Fraqueza","Neutro")),IF(N14<$L14,"Força",IF(N14>$M14,"Fraqueza","Neutro")))) -> Fraqueza | P14: 1.3013 | Q14: =IF(OR(P14="",$L14="",$M14=""),"",IF($E14="+",IF(P14>$M14,"Força",IF(P14<$L14,"Fraqueza","Neutro")),IF(P14<$L14,"Força",IF(P14>$M14,"Fraqueza","Neutro")))) -> Força | R14: 0.5029 | S14: =IF(OR(R14="",$L14="",$M14=""),"",IF($E14="+",IF(R14>$M14,"Força",IF(R14<$L14,"Fraqueza","Neutro")),IF(R14<$L14,"Força",IF(R14>$M14,"Fraqueza","Neutro")))) -> Fraqueza | T14: 0.4636 | U14: =IF(OR(T14="",$L14="",$M14=""),"",IF($E14="+",IF(T14>$M14,"Força",IF(T14<$L14,"Fraqueza","Neutro")),IF(T14<$L14,"Força",IF(T14>$M14,"Fraqueza","Neutro")))) -> Fraqueza | V14: 0.3623 | W14: =IF(OR(V14="",$L14="",$M14=""),"",IF($E14="+",IF(V14>$M14,"Força",IF(V14<$L14,"Fraqueza","Neutro")),IF(V14<$L14,"Força",IF(V14>$M14,"Fraqueza","Neutro")))) -> Fraqueza | X14: 0.4388 | Y14: =IF(OR(X14="",$L14="",$M14=""),"",IF($E14="+",IF(X14>$M14,"Força",IF(X14<$L14,"Fraqueza","Neutro")),IF(X14<$L14,"Força",IF(X14>$M14,"Fraqueza","Neutro")))) -> Fraqueza | Z14: 0.3227 | AA14: =IF(OR(Z14="",$L14="",$M14=""),"",IF($E14="+",IF(Z14>$M14,"Força",IF(Z14<$L14,"Fraqueza","Neutro")),IF(Z14<$L14,"Força",IF(Z14>$M14,"Fraqueza","Neutro")))) -> Fraqueza | AB14: 1.1498 | AC14: =IF(OR(AB14="",$L14="",$M14=""),"",IF($E14="+",IF(AB14>$M14,"Força",IF(AB14<$L14,"Fraqueza","Neutro")),IF(AB14<$L14,"Força",IF(AB14>$M14,"Fraqueza","Neutro")))) -> Neutro | AD14: 0.7089 | AE14: =IF(OR(AD14="",$L14="",$M14=""),"",IF($E14="+",IF(AD14>$M14,"Força",IF(AD14<$L14,"Fraqueza","Neutro")),IF(AD14<$L14,"Força",IF(AD14>$M14,"Fraqueza","Neutro")))) -> Fraqueza | AF14: 1.1034 | AG14: =IF(OR(AF14="",$L14="",$M14=""),"",IF($E14="+",IF(AF14>$M14,"Força",IF(AF14<$L14,"Fraqueza","Neutro")),IF(AF14<$L14,"Força",IF(AF14>$M14,"Fraqueza","Neutro")))) -> Neutro | AH14: 0.505 | AI14: =IF(OR(AH14="",$L14="",$M14=""),"",IF($E14="+",IF(AH14>$M14,"Força",IF(AH14<$L14,"Fraqueza","Neutro")),IF(AH14<$L14,"Força",IF(AH14>$M14,"Fraqueza","Neutro")))) -> Fraqueza | AJ14: 1.5988 | AK14: =IF(OR(AJ14="",$L14="",$M14=""),"",IF($E14="+",IF(AJ14>$M14,"Força",IF(AJ14<$L14,"Fraqueza","Neutro")),IF(AJ14<$L14,"Força",IF(AJ14>$M14,"Fraqueza","Neutro")))) -> Força | AL14: 0.3417 | AM14: =IF(OR(AL14="",$L14="",$M14=""),"",IF($E14="+",IF(AL14>$M14,"Força",IF(AL14<$L14,"Fraqueza","Neutro")),IF(AL14<$L14,"Força",IF(AL14>$M14,"Fraqueza","Neutro")))) -> Fraqueza
A15: CS-02 | B15: Comércio e Serviços | C15: Variação do emprego formal em comércio e serviços em 5 anos | D15: % | E15: + | F15: RAIS (MTE) | G15: 2024 | H15: Dif. MT (p.p.) | I15: 38.11 | L15: =IF($H15="Absoluto",IF($J15="","",$J15),IF($I15="","",IF($H15="Razão MT",MIN($I15*(1-Parâmetros!$B$3),$I15*(1+Parâmetros!$B$3)),$I15-Parâmetros!$B$4))) -> 36.11 | M15: =IF($H15="Absoluto",IF($K15="","",$K15),IF($I15="","",IF($H15="Razão MT",MAX($I15*(1-Parâmetros!$B$3),$I15*(1+Parâmetros!$B$3)),$I15+Parâmetros!$B$4))) -> 40.11 | N15: 28.79 | O15: =IF(OR(N15="",$L15="",$M15=""),"",IF($E15="+",IF(N15>$M15,"Força",IF(N15<$L15,"Fraqueza","Neutro")),IF(N15<$L15,"Força",IF(N15>$M15,"Fraqueza","Neutro")))) -> Fraqueza | P15: 13.05 | Q15: =IF(OR(P15="",$L15="",$M15=""),"",IF($E15="+",IF(P15>$M15,"Força",IF(P15<$L15,"Fraqueza","Neutro")),IF(P15<$L15,"Força",IF(P15>$M15,"Fraqueza","Neutro")))) -> Fraqueza | R15: 89.04 | S15: =IF(OR(R15="",$L15="",$M15=""),"",IF($E15="+",IF(R15>$M15,"Força",IF(R15<$L15,"Fraqueza","Neutro")),IF(R15<$L15,"Força",IF(R15>$M15,"Fraqueza","Neutro")))) -> Força | T15: -10.46 | U15: =IF(OR(T15="",$L15="",$M15=""),"",IF($E15="+",IF(T15>$M15,"Força",IF(T15<$L15,"Fraqueza","Neutro")),IF(T15<$L15,"Força",IF(T15>$M15,"Fraqueza","Neutro")))) -> Fraqueza | V15: 27.74 | W15: =IF(OR(V15="",$L15="",$M15=""),"",IF($E15="+",IF(V15>$M15,"Força",IF(V15<$L15,"Fraqueza","Neutro")),IF(V15<$L15,"Força",IF(V15>$M15,"Fraqueza","Neutro")))) -> Fraqueza | X15: 41.4 | Y15: =IF(OR(X15="",$L15="",$M15=""),"",IF($E15="+",IF(X15>$M15,"Força",IF(X15<$L15,"Fraqueza","Neutro")),IF(X15<$L15,"Força",IF(X15>$M15,"Fraqueza","Neutro")))) -> Força | Z15: 13.39 | AA15: =IF(OR(Z15="",$L15="",$M15=""),"",IF($E15="+",IF(Z15>$M15,"Força",IF(Z15<$L15,"Fraqueza","Neutro")),IF(Z15<$L15,"Força",IF(Z15>$M15,"Fraqueza","Neutro")))) -> Fraqueza | AB15: 14.99 | AC15: =IF(OR(AB15="",$L15="",$M15=""),"",IF($E15="+",IF(AB15>$M15,"Força",IF(AB15<$L15,"Fraqueza","Neutro")),IF(AB15<$L15,"Força",IF(AB15>$M15,"Fraqueza","Neutro")))) -> Fraqueza | AD15: 158.22 | AE15: =IF(OR(AD15="",$L15="",$M15=""),"",IF($E15="+",IF(AD15>$M15,"Força",IF(AD15<$L15,"Fraqueza","Neutro")),IF(AD15<$L15,"Força",IF(AD15>$M15,"Fraqueza","Neutro")))) -> Força | AF15: 30.43 | AG15: =IF(OR(AF15="",$L15="",$M15=""),"",IF($E15="+",IF(AF15>$M15,"Força",IF(AF15<$L15,"Fraqueza","Neutro")),IF(AF15<$L15,"Força",IF(AF15>$M15,"Fraqueza","Neutro")))) -> Fraqueza | AH15: -12.56 | AI15: =IF(OR(AH15="",$L15="",$M15=""),"",IF($E15="+",IF(AH15>$M15,"Força",IF(AH15<$L15,"Fraqueza","Neutro")),IF(AH15<$L15,"Força",IF(AH15>$M15,"Fraqueza","Neutro")))) -> Fraqueza | AJ15: 40.03 | AK15: =IF(OR(AJ15="",$L15="",$M15=""),"",IF($E15="+",IF(AJ15>$M15,"Força",IF(AJ15<$L15,"Fraqueza","Neutro")),IF(AJ15<$L15,"Força",IF(AJ15>$M15,"Fraqueza","Neutro")))) -> Neutro | AL15: 31.02 | AM15: =IF(OR(AL15="",$L15="",$M15=""),"",IF($E15="+",IF(AL15>$M15,"Força",IF(AL15<$L15,"Fraqueza","Neutro")),IF(AL15<$L15,"Força",IF(AL15>$M15,"Fraqueza","Neutro")))) -> Fraqueza
A16: CS-03 | B16: Comércio e Serviços | C16: Empresas e outras organizações ativas por mil habitantes | D16: un./mil hab. | E16: + | F16: IBGE – CEMPRE | G16: 2021 | H16: Razão MT | I16: 33.22 | L16: =IF($H16="Absoluto",IF($J16="","",$J16),IF($I16="","",IF($H16="Razão MT",MIN($I16*(1-Parâmetros!$B$3),$I16*(1+Parâmetros!$B$3)),$I16-Parâmetros!$B$4))) -> 29.898 | M16: =IF($H16="Absoluto",IF($K16="","",$K16),IF($I16="","",IF($H16="Razão MT",MAX($I16*(1-Parâmetros!$B$3),$I16*(1+Parâmetros!$B$3)),$I16+Parâmetros!$B$4))) -> 36.542 | N16: 9.06 | O16: =IF(OR(N16="",$L16="",$M16=""),"",IF($E16="+",IF(N16>$M16,"Força",IF(N16<$L16,"Fraqueza","Neutro")),IF(N16<$L16,"Força",IF(N16>$M16,"Fraqueza","Neutro")))) -> Fraqueza | P16: 19.41 | Q16: =IF(OR(P16="",$L16="",$M16=""),"",IF($E16="+",IF(P16>$M16,"Força",IF(P16<$L16,"Fraqueza","Neutro")),IF(P16<$L16,"Força",IF(P16>$M16,"Fraqueza","Neutro")))) -> Fraqueza | R16: 15.95 | S16: =IF(OR(R16="",$L16="",$M16=""),"",IF($E16="+",IF(R16>$M16,"Força",IF(R16<$L16,"Fraqueza","Neutro")),IF(R16<$L16,"Força",IF(R16>$M16,"Fraqueza","Neutro")))) -> Fraqueza | T16: 19.4 | U16: =IF(OR(T16="",$L16="",$M16=""),"",IF($E16="+",IF(T16>$M16,"Força",IF(T16<$L16,"Fraqueza","Neutro")),IF(T16<$L16,"Força",IF(T16>$M16,"Fraqueza","Neutro")))) -> Fraqueza | V16: 21.49 | W16: =IF(OR(V16="",$L16="",$M16=""),"",IF($E16="+",IF(V16>$M16,"Força",IF(V16<$L16,"Fraqueza","Neutro")),IF(V16<$L16,"Força",IF(V16>$M16,"Fraqueza","Neutro")))) -> Fraqueza | X16: 17.26 | Y16: =IF(OR(X16="",$L16="",$M16=""),"",IF($E16="+",IF(X16>$M16,"Força",IF(X16<$L16,"Fraqueza","Neutro")),IF(X16<$L16,"Força",IF(X16>$M16,"Fraqueza","Neutro")))) -> Fraqueza | Z16: 14.41 | AA16: =IF(OR(Z16="",$L16="",$M16=""),"",IF($E16="+",IF(Z16>$M16,"Força",IF(Z16<$L16,"Fraqueza","Neutro")),IF(Z16<$L16,"Força",IF(Z16>$M16,"Fraqueza","Neutro")))) -> Fraqueza | AB16: 32.17 | AC16: =IF(OR(AB16="",$L16="",$M16=""),"",IF($E16="+",IF(AB16>$M16,"Força",IF(AB16<$L16,"Fraqueza","Neutro")),IF(AB16<$L16,"Força",IF(AB16>$M16,"Fraqueza","Neutro")))) -> Neutro | AD16: 14.51 | AE16: =IF(OR(AD16="",$L16="",$M16=""),"",IF($E16="+",IF(AD16>$M16,"Força",IF(AD16<$L16,"Fraqueza","Neutro")),IF(AD16<$L16,"Força",IF(AD16>$M16,"Fraqueza","Neutro")))) -> Fraqueza | AF16: 16.35 | AG16: =IF(OR(AF16="",$L16="",$M16=""),"",IF($E16="+",IF(AF16>$M16,"Força",IF(AF16<$L16,"Fraqueza","Neutro")),IF(AF16<$L16,"Força",IF(AF16>$M16,"Fraqueza","Neutro")))) -> Fraqueza | AH16: 13.06 | AI16: =IF(OR(AH16="",$L16="",$M16=""),"",IF($E16="+",IF(AH16>$M16,"Força",IF(AH16<$L16,"Fraqueza","Neutro")),IF(AH16<$L16,"Força",IF(AH16>$M16,"Fraqueza","Neutro")))) -> Fraqueza | AJ16: 36.86 | AK16: =IF(OR(AJ16="",$L16="",$M16=""),"",IF($E16="+",IF(AJ16>$M16,"Força",IF(AJ16<$L16,"Fraqueza","Neutro")),IF(AJ16<$L16,"Força",IF(AJ16>$M16,"Fraqueza","Neutro")))) -> Força | AL16: 16.12 | AM16: =IF(OR(AL16="",$L16="",$M16=""),"",IF($E16="+",IF(AL16>$M16,"Força",IF(AL16<$L16,"Fraqueza","Neutro")),IF(AL16<$L16,"Força",IF(AL16>$M16,"Fraqueza","Neutro")))) -> Fraqueza
A17: EST-01 | B17: Estrutura Econômica e Fiscal | C17: PIB per capita | D17: R$ | E17: + | F17: IBGE – PIB dos Municípios | G17: 2023 | H17: Razão MT | I17: 74620.05 | L17: =IF($H17="Absoluto",IF($J17="","",$J17),IF($I17="","",IF($H17="Razão MT",MIN($I17*(1-Parâmetros!$B$3),$I17*(1+Parâmetros!$B$3)),$I17-Parâmetros!$B$4))) -> 67158.045 | M17: =IF($H17="Absoluto",IF($K17="","",$K17),IF($I17="","",IF($H17="Razão MT",MAX($I17*(1-Parâmetros!$B$3),$I17*(1+Parâmetros!$B$3)),$I17+Parâmetros!$B$4))) -> 82082.055 | N17: 19806.58 | O17: =IF(OR(N17="",$L17="",$M17=""),"",IF($E17="+",IF(N17>$M17,"Força",IF(N17<$L17,"Fraqueza","Neutro")),IF(N17<$L17,"Força",IF(N17>$M17,"Fraqueza","Neutro")))) -> Fraqueza | P17: 31174.15 | Q17: =IF(OR(P17="",$L17="",$M17=""),"",IF($E17="+",IF(P17>$M17,"Força",IF(P17<$L17,"Fraqueza","Neutro")),IF(P17<$L17,"Força",IF(P17>$M17,"Fraqueza","Neutro")))) -> Fraqueza | R17: 27693.14 | S17: =IF(OR(R17="",$L17="",$M17=""),"",IF($E17="+",IF(R17>$M17,"Força",IF(R17<$L17,"Fraqueza","Neutro")),IF(R17<$L17,"Força",IF(R17>$M17,"Fraqueza","Neutro")))) -> Fraqueza | T17: 39644.82 | U17: =IF(OR(T17="",$L17="",$M17=""),"",IF($E17="+",IF(T17>$M17,"Força",IF(T17<$L17,"Fraqueza","Neutro")),IF(T17<$L17,"Força",IF(T17>$M17,"Fraqueza","Neutro")))) -> Fraqueza | V17: 167482.75 | W17: =IF(OR(V17="",$L17="",$M17=""),"",IF($E17="+",IF(V17>$M17,"Força",IF(V17<$L17,"Fraqueza","Neutro")),IF(V17<$L17,"Força",IF(V17>$M17,"Fraqueza","Neutro")))) -> Força | X17: 48349.24 | Y17: =IF(OR(X17="",$L17="",$M17=""),"",IF($E17="+",IF(X17>$M17,"Força",IF(X17<$L17,"Fraqueza","Neutro")),IF(X17<$L17,"Força",IF(X17>$M17,"Fraqueza","Neutro")))) -> Fraqueza | Z17: 59335.82 | AA17: =IF(OR(Z17="",$L17="",$M17=""),"",IF($E17="+",IF(Z17>$M17,"Força",IF(Z17<$L17,"Fraqueza","Neutro")),IF(Z17<$L17,"Força",IF(Z17>$M17,"Fraqueza","Neutro")))) -> Fraqueza | AB17: 43433.97 | AC17: =IF(OR(AB17="",$L17="",$M17=""),"",IF($E17="+",IF(AB17>$M17,"Força",IF(AB17<$L17,"Fraqueza","Neutro")),IF(AB17<$L17,"Força",IF(AB17>$M17,"Fraqueza","Neutro")))) -> Fraqueza | AD17: 33510.51 | AE17: =IF(OR(AD17="",$L17="",$M17=""),"",IF($E17="+",IF(AD17>$M17,"Força",IF(AD17<$L17,"Fraqueza","Neutro")),IF(AD17<$L17,"Força",IF(AD17>$M17,"Fraqueza","Neutro")))) -> Fraqueza | AF17: 27609.14 | AG17: =IF(OR(AF17="",$L17="",$M17=""),"",IF($E17="+",IF(AF17>$M17,"Força",IF(AF17<$L17,"Fraqueza","Neutro")),IF(AF17<$L17,"Força",IF(AF17>$M17,"Fraqueza","Neutro")))) -> Fraqueza | AH17: 31726.19 | AI17: =IF(OR(AH17="",$L17="",$M17=""),"",IF($E17="+",IF(AH17>$M17,"Força",IF(AH17<$L17,"Fraqueza","Neutro")),IF(AH17<$L17,"Força",IF(AH17>$M17,"Fraqueza","Neutro")))) -> Fraqueza | AJ17: 67650.09 | AK17: =IF(OR(AJ17="",$L17="",$M17=""),"",IF($E17="+",IF(AJ17>$M17,"Força",IF(AJ17<$L17,"Fraqueza","Neutro")),IF(AJ17<$L17,"Força",IF(AJ17>$M17,"Fraqueza","Neutro")))) -> Neutro | AL17: 48781.11 | AM17: =IF(OR(AL17="",$L17="",$M17=""),"",IF($E17="+",IF(AL17>$M17,"Força",IF(AL17<$L17,"Fraqueza","Neutro")),IF(AL17<$L17,"Força",IF(AL17>$M17,"Fraqueza","Neutro")))) -> Fraqueza
A18: EST-02 | B18: Estrutura Econômica e Fiscal | C18: Participação da administração pública no VAB total | D18: % | E18: - | F18: IBGE – PIB dos Municípios | G18: 2021 | H18: Dif. MT (p.p.) | I18: 11.89 | L18: =IF($H18="Absoluto",IF($J18="","",$J18),IF($I18="","",IF($H18="Razão MT",MIN($I18*(1-Parâmetros!$B$3),$I18*(1+Parâmetros!$B$3)),$I18-Parâmetros!$B$4))) -> 9.89 | M18: =IF($H18="Absoluto",IF($K18="","",$K18),IF($I18="","",IF($H18="Razão MT",MAX($I18*(1-Parâmetros!$B$3),$I18*(1+Parâmetros!$B$3)),$I18+Parâmetros!$B$4))) -> 13.89 | N18: 45.95 | O18: =IF(OR(N18="",$L18="",$M18=""),"",IF($E18="+",IF(N18>$M18,"Força",IF(N18<$L18,"Fraqueza","Neutro")),IF(N18<$L18,"Força",IF(N18>$M18,"Fraqueza","Neutro")))) -> Fraqueza | P18: 30.82 | Q18: =IF(OR(P18="",$L18="",$M18=""),"",IF($E18="+",IF(P18>$M18,"Força",IF(P18<$L18,"Fraqueza","Neutro")),IF(P18<$L18,"Força",IF(P18>$M18,"Fraqueza","Neutro")))) -> Fraqueza | R18: 29.61 | S18: =IF(OR(R18="",$L18="",$M18=""),"",IF($E18="+",IF(R18>$M18,"Força",IF(R18<$L18,"Fraqueza","Neutro")),IF(R18<$L18,"Força",IF(R18>$M18,"Fraqueza","Neutro")))) -> Fraqueza | T18: 26.83 | U18: =IF(OR(T18="",$L18="",$M18=""),"",IF($E18="+",IF(T18>$M18,"Força",IF(T18<$L18,"Fraqueza","Neutro")),IF(T18<$L18,"Força",IF(T18>$M18,"Fraqueza","Neutro")))) -> Fraqueza | V18: 5.88 | W18: =IF(OR(V18="",$L18="",$M18=""),"",IF($E18="+",IF(V18>$M18,"Força",IF(V18<$L18,"Fraqueza","Neutro")),IF(V18<$L18,"Força",IF(V18>$M18,"Fraqueza","Neutro")))) -> Força | X18: 16.77 | Y18: =IF(OR(X18="",$L18="",$M18=""),"",IF($E18="+",IF(X18>$M18,"Força",IF(X18<$L18,"Fraqueza","Neutro")),IF(X18<$L18,"Força",IF(X18>$M18,"Fraqueza","Neutro")))) -> Fraqueza | Z18: 18.67 | AA18: =IF(OR(Z18="",$L18="",$M18=""),"",IF($E18="+",IF(Z18>$M18,"Força",IF(Z18<$L18,"Fraqueza","Neutro")),IF(Z18<$L18,"Força",IF(Z18>$M18,"Fraqueza","Neutro")))) -> Fraqueza | AB18: 25.62 | AC18: =IF(OR(AB18="",$L18="",$M18=""),"",IF($E18="+",IF(AB18>$M18,"Força",IF(AB18<$L18,"Fraqueza","Neutro")),IF(AB18<$L18,"Força",IF(AB18>$M18,"Fraqueza","Neutro")))) -> Fraqueza | AD18: 24.97 | AE18: =IF(OR(AD18="",$L18="",$M18=""),"",IF($E18="+",IF(AD18>$M18,"Força",IF(AD18<$L18,"Fraqueza","Neutro")),IF(AD18<$L18,"Força",IF(AD18>$M18,"Fraqueza","Neutro")))) -> Fraqueza | AF18: 33.23 | AG18: =IF(OR(AF18="",$L18="",$M18=""),"",IF($E18="+",IF(AF18>$M18,"Força",IF(AF18<$L18,"Fraqueza","Neutro")),IF(AF18<$L18,"Força",IF(AF18>$M18,"Fraqueza","Neutro")))) -> Fraqueza | AH18: 28.79 | AI18: =IF(OR(AH18="",$L18="",$M18=""),"",IF($E18="+",IF(AH18>$M18,"Força",IF(AH18<$L18,"Fraqueza","Neutro")),IF(AH18<$L18,"Força",IF(AH18>$M18,"Fraqueza","Neutro")))) -> Fraqueza | AJ18: 11.66 | AK18: =IF(OR(AJ18="",$L18="",$M18=""),"",IF($E18="+",IF(AJ18>$M18,"Força",IF(AJ18<$L18,"Fraqueza","Neutro")),IF(AJ18<$L18,"Força",IF(AJ18>$M18,"Fraqueza","Neutro")))) -> Neutro | AL18: 15.78 | AM18: =IF(OR(AL18="",$L18="",$M18=""),"",IF($E18="+",IF(AL18>$M18,"Força",IF(AL18<$L18,"Fraqueza","Neutro")),IF(AL18<$L18,"Força",IF(AL18>$M18,"Fraqueza","Neutro")))) -> Fraqueza
A19: EST-03 | B19: Estrutura Econômica e Fiscal | C19: Vínculos formais por 100 habitantes | D19: vínculos/100 hab. | E19: + | F19: RAIS + IBGE (população) | G19: 2024 | H19: Razão MT | I19: 31.51 | L19: =IF($H19="Absoluto",IF($J19="","",$J19),IF($I19="","",IF($H19="Razão MT",MIN($I19*(1-Parâmetros!$B$3),$I19*(1+Parâmetros!$B$3)),$I19-Parâmetros!$B$4))) -> 28.359 | M19: =IF($H19="Absoluto",IF($K19="","",$K19),IF($I19="","",IF($H19="Razão MT",MAX($I19*(1-Parâmetros!$B$3),$I19*(1+Parâmetros!$B$3)),$I19+Parâmetros!$B$4))) -> 34.661 | N19: 8.4 | O19: =IF(OR(N19="",$L19="",$M19=""),"",IF($E19="+",IF(N19>$M19,"Força",IF(N19<$L19,"Fraqueza","Neutro")),IF(N19<$L19,"Força",IF(N19>$M19,"Fraqueza","Neutro")))) -> Fraqueza | P19: 18.4 | Q19: =IF(OR(P19="",$L19="",$M19=""),"",IF($E19="+",IF(P19>$M19,"Força",IF(P19<$L19,"Fraqueza","Neutro")),IF(P19<$L19,"Força",IF(P19>$M19,"Fraqueza","Neutro")))) -> Fraqueza | R19: 11.88 | S19: =IF(OR(R19="",$L19="",$M19=""),"",IF($E19="+",IF(R19>$M19,"Força",IF(R19<$L19,"Fraqueza","Neutro")),IF(R19<$L19,"Força",IF(R19>$M19,"Fraqueza","Neutro")))) -> Fraqueza | T19: 14.32 | U19: =IF(OR(T19="",$L19="",$M19=""),"",IF($E19="+",IF(T19>$M19,"Força",IF(T19<$L19,"Fraqueza","Neutro")),IF(T19<$L19,"Força",IF(T19>$M19,"Fraqueza","Neutro")))) -> Fraqueza | V19: 37.5 | W19: =IF(OR(V19="",$L19="",$M19=""),"",IF($E19="+",IF(V19>$M19,"Força",IF(V19<$L19,"Fraqueza","Neutro")),IF(V19<$L19,"Força",IF(V19>$M19,"Fraqueza","Neutro")))) -> Força | X19: 17.31 | Y19: =IF(OR(X19="",$L19="",$M19=""),"",IF($E19="+",IF(X19>$M19,"Força",IF(X19<$L19,"Fraqueza","Neutro")),IF(X19<$L19,"Força",IF(X19>$M19,"Fraqueza","Neutro")))) -> Fraqueza | Z19: 30.4 | AA19: =IF(OR(Z19="",$L19="",$M19=""),"",IF($E19="+",IF(Z19>$M19,"Força",IF(Z19<$L19,"Fraqueza","Neutro")),IF(Z19<$L19,"Força",IF(Z19>$M19,"Fraqueza","Neutro")))) -> Neutro | AB19: 22.66 | AC19: =IF(OR(AB19="",$L19="",$M19=""),"",IF($E19="+",IF(AB19>$M19,"Força",IF(AB19<$L19,"Fraqueza","Neutro")),IF(AB19<$L19,"Força",IF(AB19>$M19,"Fraqueza","Neutro")))) -> Fraqueza | AD19: 24.35 | AE19: =IF(OR(AD19="",$L19="",$M19=""),"",IF($E19="+",IF(AD19>$M19,"Força",IF(AD19<$L19,"Fraqueza","Neutro")),IF(AD19<$L19,"Força",IF(AD19>$M19,"Fraqueza","Neutro")))) -> Fraqueza | AF19: 15.75 | AG19: =IF(OR(AF19="",$L19="",$M19=""),"",IF($E19="+",IF(AF19>$M19,"Força",IF(AF19<$L19,"Fraqueza","Neutro")),IF(AF19<$L19,"Força",IF(AF19>$M19,"Fraqueza","Neutro")))) -> Fraqueza | AH19: 16.43 | AI19: =IF(OR(AH19="",$L19="",$M19=""),"",IF($E19="+",IF(AH19>$M19,"Força",IF(AH19<$L19,"Fraqueza","Neutro")),IF(AH19<$L19,"Força",IF(AH19>$M19,"Fraqueza","Neutro")))) -> Fraqueza | AJ19: 32.01 | AK19: =IF(OR(AJ19="",$L19="",$M19=""),"",IF($E19="+",IF(AJ19>$M19,"Força",IF(AJ19<$L19,"Fraqueza","Neutro")),IF(AJ19<$L19,"Força",IF(AJ19>$M19,"Fraqueza","Neutro")))) -> Neutro | AL19: 19.67 | AM19: =IF(OR(AL19="",$L19="",$M19=""),"",IF($E19="+",IF(AL19>$M19,"Força",IF(AL19<$L19,"Fraqueza","Neutro")),IF(AL19<$L19,"Força",IF(AL19>$M19,"Fraqueza","Neutro")))) -> Fraqueza
A20: EST-04 | B20: Estrutura Econômica e Fiscal | C20: Concentração setorial do emprego formal (HHI por seção CNAE) | D20: índice 0–1 | E20: - | F20: RAIS (MTE) | G20: 2024 | H20: Razão MT | I20: 0.1254 | L20: =IF($H20="Absoluto",IF($J20="","",$J20),IF($I20="","",IF($H20="Razão MT",MIN($I20*(1-Parâmetros!$B$3),$I20*(1+Parâmetros!$B$3)),$I20-Parâmetros!$B$4))) -> 0.11286 | M20: =IF($H20="Absoluto",IF($K20="","",$K20),IF($I20="","",IF($H20="Razão MT",MAX($I20*(1-Parâmetros!$B$3),$I20*(1+Parâmetros!$B$3)),$I20+Parâmetros!$B$4))) -> 0.13794 | N20: 0.2519 | O20: =IF(OR(N20="",$L20="",$M20=""),"",IF($E20="+",IF(N20>$M20,"Força",IF(N20<$L20,"Fraqueza","Neutro")),IF(N20<$L20,"Força",IF(N20>$M20,"Fraqueza","Neutro")))) -> Fraqueza | P20: 0.1286 | Q20: =IF(OR(P20="",$L20="",$M20=""),"",IF($E20="+",IF(P20>$M20,"Força",IF(P20<$L20,"Fraqueza","Neutro")),IF(P20<$L20,"Força",IF(P20>$M20,"Fraqueza","Neutro")))) -> Neutro | R20: 0.1849 | S20: =IF(OR(R20="",$L20="",$M20=""),"",IF($E20="+",IF(R20>$M20,"Força",IF(R20<$L20,"Fraqueza","Neutro")),IF(R20<$L20,"Força",IF(R20>$M20,"Fraqueza","Neutro")))) -> Fraqueza | T20: 0.3147 | U20: =IF(OR(T20="",$L20="",$M20=""),"",IF($E20="+",IF(T20>$M20,"Força",IF(T20<$L20,"Fraqueza","Neutro")),IF(T20<$L20,"Força",IF(T20>$M20,"Fraqueza","Neutro")))) -> Fraqueza | V20: 0.363 | W20: =IF(OR(V20="",$L20="",$M20=""),"",IF($E20="+",IF(V20>$M20,"Força",IF(V20<$L20,"Fraqueza","Neutro")),IF(V20<$L20,"Força",IF(V20>$M20,"Fraqueza","Neutro")))) -> Fraqueza | X20: 0.2275 | Y20: =IF(OR(X20="",$L20="",$M20=""),"",IF($E20="+",IF(X20>$M20,"Força",IF(X20<$L20,"Fraqueza","Neutro")),IF(X20<$L20,"Força",IF(X20>$M20,"Fraqueza","Neutro")))) -> Fraqueza | Z20: 0.3954 | AA20: =IF(OR(Z20="",$L20="",$M20=""),"",IF($E20="+",IF(Z20>$M20,"Força",IF(Z20<$L20,"Fraqueza","Neutro")),IF(Z20<$L20,"Força",IF(Z20>$M20,"Fraqueza","Neutro")))) -> Fraqueza | AB20: 0.1288 | AC20: =IF(OR(AB20="",$L20="",$M20=""),"",IF($E20="+",IF(AB20>$M20,"Força",IF(AB20<$L20,"Fraqueza","Neutro")),IF(AB20<$L20,"Força",IF(AB20>$M20,"Fraqueza","Neutro")))) -> Neutro | AD20: 0.2738 | AE20: =IF(OR(AD20="",$L20="",$M20=""),"",IF($E20="+",IF(AD20>$M20,"Força",IF(AD20<$L20,"Fraqueza","Neutro")),IF(AD20<$L20,"Força",IF(AD20>$M20,"Fraqueza","Neutro")))) -> Fraqueza | AF20: 0.1845 | AG20: =IF(OR(AF20="",$L20="",$M20=""),"",IF($E20="+",IF(AF20>$M20,"Força",IF(AF20<$L20,"Fraqueza","Neutro")),IF(AF20<$L20,"Força",IF(AF20>$M20,"Fraqueza","Neutro")))) -> Fraqueza | AH20: 0.3713 | AI20: =IF(OR(AH20="",$L20="",$M20=""),"",IF($E20="+",IF(AH20>$M20,"Força",IF(AH20<$L20,"Fraqueza","Neutro")),IF(AH20<$L20,"Força",IF(AH20>$M20,"Fraqueza","Neutro")))) -> Fraqueza | AJ20: 0.1166 | AK20: =IF(OR(AJ20="",$L20="",$M20=""),"",IF($E20="+",IF(AJ20>$M20,"Força",IF(AJ20<$L20,"Fraqueza","Neutro")),IF(AJ20<$L20,"Força",IF(AJ20>$M20,"Fraqueza","Neutro")))) -> Neutro | AL20: 0.2362 | AM20: =IF(OR(AL20="",$L20="",$M20=""),"",IF($E20="+",IF(AL20>$M20,"Força",IF(AL20<$L20,"Fraqueza","Neutro")),IF(AL20<$L20,"Força",IF(AL20>$M20,"Fraqueza","Neutro")))) -> Fraqueza
A21: EST-05 | B21: Estrutura Econômica e Fiscal | C21: Receitas próprias / receita corrente | D21: % | E21: + | F21: Siconfi / FINBRA (STN) | G21: 2022 | H21: Dif. MT (p.p.) | I21: 18.24 | L21: =IF($H21="Absoluto",IF($J21="","",$J21),IF($I21="","",IF($H21="Razão MT",MIN($I21*(1-Parâmetros!$B$3),$I21*(1+Parâmetros!$B$3)),$I21-Parâmetros!$B$4))) -> 16.24 | M21: =IF($H21="Absoluto",IF($K21="","",$K21),IF($I21="","",IF($H21="Razão MT",MAX($I21*(1-Parâmetros!$B$3),$I21*(1+Parâmetros!$B$3)),$I21+Parâmetros!$B$4))) -> 20.24 | N21: 6.34 | O21: =IF(OR(N21="",$L21="",$M21=""),"",IF($E21="+",IF(N21>$M21,"Força",IF(N21<$L21,"Fraqueza","Neutro")),IF(N21<$L21,"Força",IF(N21>$M21,"Fraqueza","Neutro")))) -> Fraqueza | P21: 17.68 | Q21: =IF(OR(P21="",$L21="",$M21=""),"",IF($E21="+",IF(P21>$M21,"Força",IF(P21<$L21,"Fraqueza","Neutro")),IF(P21<$L21,"Força",IF(P21>$M21,"Fraqueza","Neutro")))) -> Neutro | R21: 5.5 | S21: =IF(OR(R21="",$L21="",$M21=""),"",IF($E21="+",IF(R21>$M21,"Força",IF(R21<$L21,"Fraqueza","Neutro")),IF(R21<$L21,"Força",IF(R21>$M21,"Fraqueza","Neutro")))) -> Fraqueza | T21: 5.76 | U21: =IF(OR(T21="",$L21="",$M21=""),"",IF($E21="+",IF(T21>$M21,"Força",IF(T21<$L21,"Fraqueza","Neutro")),IF(T21<$L21,"Força",IF(T21>$M21,"Fraqueza","Neutro")))) -> Fraqueza | V21: 11.87 | W21: =IF(OR(V21="",$L21="",$M21=""),"",IF($E21="+",IF(V21>$M21,"Força",IF(V21<$L21,"Fraqueza","Neutro")),IF(V21<$L21,"Força",IF(V21>$M21,"Fraqueza","Neutro")))) -> Fraqueza | X21: 11.71 | Y21: =IF(OR(X21="",$L21="",$M21=""),"",IF($E21="+",IF(X21>$M21,"Força",IF(X21<$L21,"Fraqueza","Neutro")),IF(X21<$L21,"Força",IF(X21>$M21,"Fraqueza","Neutro")))) -> Fraqueza | Z21: 7.14 | AA21: =IF(OR(Z21="",$L21="",$M21=""),"",IF($E21="+",IF(Z21>$M21,"Força",IF(Z21<$L21,"Fraqueza","Neutro")),IF(Z21<$L21,"Força",IF(Z21>$M21,"Fraqueza","Neutro")))) -> Fraqueza | AB21: 14.35 | AC21: =IF(OR(AB21="",$L21="",$M21=""),"",IF($E21="+",IF(AB21>$M21,"Força",IF(AB21<$L21,"Fraqueza","Neutro")),IF(AB21<$L21,"Força",IF(AB21>$M21,"Fraqueza","Neutro")))) -> Fraqueza | AD21: 5.15 | AE21: =IF(OR(AD21="",$L21="",$M21=""),"",IF($E21="+",IF(AD21>$M21,"Força",IF(AD21<$L21,"Fraqueza","Neutro")),IF(AD21<$L21,"Força",IF(AD21>$M21,"Fraqueza","Neutro")))) -> Fraqueza | AF21: 9.51 | AG21: =IF(OR(AF21="",$L21="",$M21=""),"",IF($E21="+",IF(AF21>$M21,"Força",IF(AF21<$L21,"Fraqueza","Neutro")),IF(AF21<$L21,"Força",IF(AF21>$M21,"Fraqueza","Neutro")))) -> Fraqueza | AH21: 6.54 | AI21: =IF(OR(AH21="",$L21="",$M21=""),"",IF($E21="+",IF(AH21>$M21,"Força",IF(AH21<$L21,"Fraqueza","Neutro")),IF(AH21<$L21,"Força",IF(AH21>$M21,"Fraqueza","Neutro")))) -> Fraqueza | AJ21: 21.61 | AK21: =IF(OR(AJ21="",$L21="",$M21=""),"",IF($E21="+",IF(AJ21>$M21,"Força",IF(AJ21<$L21,"Fraqueza","Neutro")),IF(AJ21<$L21,"Força",IF(AJ21>$M21,"Fraqueza","Neutro")))) -> Força | AL21: 9.96 | AM21: =IF(OR(AL21="",$L21="",$M21=""),"",IF($E21="+",IF(AL21>$M21,"Força",IF(AL21<$L21,"Fraqueza","Neutro")),IF(AL21<$L21,"Força",IF(AL21>$M21,"Fraqueza","Neutro")))) -> Fraqueza
A23: Notas: 'Ano ref.' deve ser igual para todos os municípios no mesmo indicador. QL com base MT: valor do estado = 1 por definição. Limiares absolutos dos QLs (0,8/1,2) são proposta inicial a validar.

Sheet Fatores Externos (O-A)
A1: FATORES EXTERNOS — OPORTUNIDADES E AMEAÇAS
A2: Intensidade por município: 0 = não se aplica | 1 = baixa | 2 = média | 3 = alta. Registrar a evidência na coluna E ou em comentário. Notas preenchidas em 25/09/2026 por pesquisa web-based (preliminares; validar por consenso de dois pesquisadores e com a pesquisa de campo).
A4: Cód. | B4: Tipo | C4: Área-chave | D4: Fator externo | E4: Evidências / fontes sugeridas | F4: Barão de Melgaço | G4: Cáceres | H4: Curvelândia | I4: Glória D'Oeste | J4: Itiquira | K4: Juscimeira | L4: Lambari D'Oeste | M4: Mirassol D'Oeste | N4: Nossa Senhora do Livramento | O4: Poconé | P4: Porto Esperidião | Q4: Rondonópolis | R4: Santo Antônio do Leverger
A5: Intensidade (0–3) →
A6: OP-01 | B6: Oportunidade | C6: Agropecuária | D6: Demanda externa por carne bovina e proteína animal | E6: Comex Stat; IMEA; Cepea. Evidências: MT tem o maior rebanho do país (≈34 mi cab., 14,2% do BR – IBGE/PPM 2023); Cáceres é o maior rebanho de MT (≈1,4 mi cab., 4º do Brasil). Nota maior onde o QL agro e o rebanho são altos (Cáceres, Porto Esperidião, Sto. Antônio do Leverger). | F6: 1 | G6: 3 | H6: 2 | I6: 2 | J6: 2 | K6: 2 | L6: 2 | M6: 2 | N6: 2 | O6: 2 | P6: 3 | Q6: 2 | R6: 3
A7: OP-02 | B7: Oportunidade | C7: Agropecuária | D7: Mercados para produtos diferenciados e certificados (carne sustentável/orgânica, origem Pantanal) | E7: Pesquisa web-based; pesquisa de campo. Evidências: municípios da planície pantaneira (Cáceres, Poconé, Barão de Melgaço, Sto. Antônio do Leverger) podem usar a origem 'Pantanal' e a pecuária extensiva tradicional como diferencial; Embrapa Pantanal (Com. Técnico 122) mapeia o rebanho da planície. | F7: 3 | G7: 3 | H7: 1 | I7: 1 | J7: 2 | K7: 1 | L7: 1 | M7: 1 | N7: 2 | O7: 3 | P7: 1 | Q7: 1 | R7: 3
A8: OP-03 | B8: Oportunidade | C8: Comércio e Serviços | D8: Expansão do turismo de natureza, pesca esportiva e ecoturismo | E8: SEDEC-MT; Cadastur; pesquisa de campo. Evidências: Transpantaneira (Poconé), Festival Internacional de Pesca e hidrovia (Cáceres), pesca esportiva e pousadas no rio Cuiabá (Barão de Melgaço, Sto. Antônio do Leverger); águas termais (Juscimeira); turismo de negócios e Cidade de Pedra (Rondonópolis). | F8: 3 | G8: 3 | H8: 0 | I8: 1 | J8: 1 | K8: 2 | L8: 1 | M8: 1 | N8: 1 | O8: 3 | P8: 1 | Q8: 2 | R8: 2
A9: OP-04 | B9: Oportunidade | C9: Indústria | D9: Agroindustrialização e verticalização (frigoríficos, laticínios, sucroenergético) | E9: RAIS; notícias de investimentos; pesquisa de campo. Evidências: Cooperb/Destilarias Novo Milênio com unidades em Lambari D'Oeste e Mirassol D'Oeste (etanol, exportação aos EUA – NovaCana); frigorífico e laticínio em Mirassol D'Oeste; polo de esmagamento de soja e fertilizantes em Rondonópolis; ZPE de Cáceres. | F9: 0 | G9: 2 | H9: 1 | I9: 1 | J9: 2 | K9: 2 | L9: 3 | M9: 3 | N9: 1 | O9: 1 | P9: 1 | Q9: 3 | R9: 1
A10: OP-05 | B10: Oportunidade | C10: Estrutura Econômica e Fiscal | D10: Corredores logísticos (rodovias federais, ferrovia, hidrovia do Paraguai) | E10: DNIT; ANTT; ANTAQ; pesquisa web-based. Evidências: Ferrovia Estadual Rondonópolis–Lucas do Rio Verde (Rumo; R$ 2 bi em 2025, trecho até Campo Verde previsto p/ 2026 – Rumo/BNDES); Porto de Cáceres reformado e terminal Paratudal em licenciamento (hidrovia Paraguai–Paraná); BR-163/364 (Rondonópolis, Itiquira, Juscimeira) e BR-070/174 (Cáceres, Livramento, Mirassol, Porto Esperidião). | F10: 1 | G10: 3 | H10: 1 | I10: 1 | J10: 2 | K10: 2 | L10: 1 | M10: 2 | N10: 2 | O10: 1 | P10: 2 | Q10: 3 | R10: 2
A11: OP-06 | B11: Oportunidade | C11: Estrutura Econômica e Fiscal | D11: Instrumentos de fomento e financiamento (FCO, crédito rural, PSA, mercado de carbono) | E11: SUDECO; BCB – Matriz de Dados do Crédito Rural. Evidências: FCO (SUDECO) e crédito rural (BCB/SICOR) com maior volume onde há grãos e pecuária de escala (Itiquira, Rondonópolis, Cáceres, Sto. Antônio do Leverger); PSA e carbono com maior aderência nas áreas de Pantanal conservado. | F11: 2 | G11: 3 | H11: 2 | I11: 2 | J11: 3 | K11: 2 | L11: 2 | M11: 2 | N11: 2 | O11: 2 | P11: 2 | Q11: 3 | R11: 3
A12: AM-01 | B12: Ameaça | C12: Agropecuária | D12: Eventos climáticos extremos: secas prolongadas e incêndios no Pantanal | E12: INPE – BDQueimadas; MapBiomas; Cemaden. Evidências: incêndios de 2024 – Cáceres ≈87 mil ha, Poconé ≈61,5 mil ha, Barão de Melgaço ≈2,6 mil ha (Bombeiros-MT/INPE); 2020 foi o pior ano da série no Pantanal; ≈95% dos focos de 2024 começaram em propriedades privadas. Planície pantaneira = exposição alta. | F12: 3 | G12: 3 | H12: 1 | I12: 1 | J12: 2 | K12: 1 | L12: 1 | M12: 1 | N12: 2 | O12: 3 | P12: 2 | Q12: 1 | R12: 3
A13: AM-02 | B13: Ameaça | C13: Agropecuária | D13: Volatilidade de preços de commodities (boi gordo, soja, milho) | E13: Cepea; IMEA; B3. Evidências: dependência de boi gordo (Cáceres, Porto Esperidião, Sto. Antônio do Leverger) e de soja/milho/algodão (Itiquira) – preços Cepea/IMEA com forte oscilação 2022–2025; Mirassol D'Oeste tem QL agro baixo (0,42). | F13: 2 | G13: 3 | H13: 2 | I13: 2 | J13: 3 | K13: 2 | L13: 2 | M13: 1 | N13: 2 | O13: 2 | P13: 3 | Q13: 2 | R13: 3
A14: AM-03 | B14: Ameaça | C14: Agropecuária | D14: Exigências ambientais de mercados importadores e barreiras ligadas a desmatamento (ex.: EUDR) | E14: Pesquisa web-based; Comex Stat. Evidências: Regulamento UE 2023/1115 (EUDR) exige rastreabilidade livre de desmatamento para carne e soja; maior exposição em municípios exportadores de grãos/carne (Itiquira, Rondonópolis, Cáceres, Sto. Antônio do Leverger). | F14: 2 | G14: 3 | H14: 2 | I14: 2 | J14: 3 | K14: 2 | L14: 2 | M14: 1 | N14: 1 | O14: 2 | P14: 2 | Q14: 3 | R14: 3
A15: AM-04 | B15: Ameaça | C15: Estrutura Econômica e Fiscal | D15: Transição da Reforma Tributária (IBS/CBS) e efeitos sobre a repartição de receitas municipais | E15: EC 132/2023; LC 214/2025; SEFAZ-MT. Evidências: EC 132/2023 e LC 214/2025 levam o IBS ao destino; municípios com alta cota-parte de ICMS pela produção (Itiquira, Rondonópolis) tendem a perder mais na transição; municípios com peso alto da adm. pública (Barão de Melgaço) são menos expostos. | F15: 1 | G15: 2 | H15: 1 | I15: 1 | J15: 3 | K15: 2 | L15: 2 | M15: 2 | N15: 1 | O15: 1 | P15: 1 | Q15: 3 | R15: 2
A16: AM-05 | B16: Ameaça | C16: Comércio e Serviços | D16: Polarização regional por centros maiores (evasão de consumo, serviços e mão de obra) | E16: IBGE – REGIC; pesquisa de campo. Evidências: REGIC/IBGE – Cuiabá polariza Barão de Melgaço, Livramento e Sto. Antônio do Leverger; Rondonópolis (Capital Regional) polariza Juscimeira e Itiquira; Cáceres polariza Curvelândia, Glória D'Oeste, Porto Esperidião e Lambari D'Oeste. | F16: 3 | G16: 1 | H16: 3 | I16: 3 | J16: 2 | K16: 3 | L16: 2 | M16: 1 | N16: 3 | O16: 2 | P16: 2 | Q16: 0 | R16: 3
A18: Novos fatores podem ser inseridos antes da última linha da tabela para que as fórmulas das abas Aux e Painel os incluam.

Sheet Aux
A1: Município | B1: ='Matriz SWOT (seletor)'!$C$3 -> Cáceres
A2: Col. dado (interno) | B2: =IFERROR(MATCH($B$1,'Indicadores (F-W)'!$A$4:$AM$4,0),"") -> 16
A3: Col. (externo) | B3: =IFERROR(MATCH($B$1,'Fatores Externos (O-A)'!$A$4:$R$4,0),"") -> 7
A5: Cód. | B5: Rótulo | C5: Classificação | D5: Valor | E5: Ordem Força | F5: Ordem Fraqueza | H5: Cód. | I5: Rótulo | J5: Tipo | K5: Intensidade | L5: Flag O | M5: Ordem O | N5: Flag A | O5: Ordem A
A6: ='Indicadores (F-W)'!A6 -> AGR-01 | B6: ="["&'Indicadores (F-W)'!B6&"] "&'Indicadores (F-W)'!A6&" – "&'Indicadores (F-W)'!C6&" ("&'Indicadores (F-W)'!D6&")" -> [Agropecuária] AGR-01 – Quociente locacional do VAB agropecuário (base MT) (índice) | C6: =IF($B$2="","",INDEX('Indicadores (F-W)'!$A6:$AM6,1,$B$2+1)) -> Fraqueza | D6: =IF($B$2="","",INDEX('Indicadores (F-W)'!$A6:$AM6,1,$B$2)) -> 0.3713 | E6: =IF(C6="Força",COUNTIF(C$6:C6,"Força"),"") | F6: =IF(C6="Fraqueza",COUNTIF(C$6:C6,"Fraqueza"),"") -> 1 | H6: ='Fatores Externos (O-A)'!A6 -> OP-01 | I6: ="["&'Fatores Externos (O-A)'!C6&"] "&'Fatores Externos (O-A)'!A6&" – "&'Fatores Externos (O-A)'!D6 -> [Agropecuária] OP-01 – Demanda externa por carne bovina e proteína animal | J6: ='Fatores Externos (O-A)'!B6 -> Oportunidade | K6: =IF($B$3="","",INDEX('Fatores Externos (O-A)'!$A6:$R6,1,$B$3)) -> 3 | L6: =IF(AND(J6="Oportunidade",ISNUMBER(K6)),IF(K6>=Parâmetros!$B$5,1,0),0) -> 1 | M6: =IF(L6=1,SUM(L$6:L6),"") -> 1 | N6: =IF(AND(J6="Ameaça",ISNUMBER(K6)),IF(K6>=Parâmetros!$B$5,1,0),0) -> 0 | O6: =IF(N6=1,SUM(N$6:N6),"")
A7: ='Indicadores (F-W)'!A7 -> AGR-02 | B7: ="["&'Indicadores (F-W)'!B7&"] "&'Indicadores (F-W)'!A7&" – "&'Indicadores (F-W)'!C7&" ("&'Indicadores (F-W)'!D7&")" -> [Agropecuária] AGR-02 – Valor da produção das lavouras por área colhida (R$/ha) | C7: =IF($B$2="","",INDEX('Indicadores (F-W)'!$A7:$AM7,1,$B$2+1)) -> Neutro | D7: =IF($B$2="","",INDEX('Indicadores (F-W)'!$A7:$AM7,1,$B$2)) -> 5729.32 | E7: =IF(C7="Força",COUNTIF(C$6:C7,"Força"),"") | F7: =IF(C7="Fraqueza",COUNTIF(C$6:C7,"Fraqueza"),"") | H7: ='Fatores Externos (O-A)'!A7 -> OP-02 | I7: ="["&'Fatores Externos (O-A)'!C7&"] "&'Fatores Externos (O-A)'!A7&" – "&'Fatores Externos (O-A)'!D7 -> [Agropecuária] OP-02 – Mercados para produtos diferenciados e certificados (carne sustentável/orgânica, origem Pantanal) | J7: ='Fatores Externos (O-A)'!B7 -> Oportunidade | K7: =IF($B$3="","",INDEX('Fatores Externos (O-A)'!$A7:$R7,1,$B$3)) -> 3 | L7: =IF(AND(J7="Oportunidade",ISNUMBER(K7)),IF(K7>=Parâmetros!$B$5,1,0),0) -> 1 | M7: =IF(L7=1,SUM(L$6:L7),"") -> 2 | N7: =IF(AND(J7="Ameaça",ISNUMBER(K7)),IF(K7>=Parâmetros!$B$5,1,0),0) -> 0 | O7: =IF(N7=1,SUM(N$6:N7),"")
A8: ='Indicadores (F-W)'!A8 -> AGR-03 | B8: ="["&'Indicadores (F-W)'!B8&"] "&'Indicadores (F-W)'!A8&" – "&'Indicadores (F-W)'!C8&" ("&'Indicadores (F-W)'!D8&")" -> [Agropecuária] AGR-03 – Variação do efetivo bovino em 5 anos (%) | C8: =IF($B$2="","",INDEX('Indicadores (F-W)'!$A8:$AM8,1,$B$2+1)) -> Força | D8: =IF($B$2="","",INDEX('Indicadores (F-W)'!$A8:$AM8,1,$B$2)) -> 22.65 | E8: =IF(C8="Força",COUNTIF(C$6:C8,"Força"),"") -> 1 | F8: =IF(C8="Fraqueza",COUNTIF(C$6:C8,"Fraqueza"),"") | H8: ='Fatores Externos (O-A)'!A8 -> OP-03 | I8: ="["&'Fatores Externos (O-A)'!C8&"] "&'Fatores Externos (O-A)'!A8&" – "&'Fatores Externos (O-A)'!D8 -> [Comércio e Serviços] OP-03 – Expansão do turismo de natureza, pesca esportiva e ecoturismo | J8: ='Fatores Externos (O-A)'!B8 -> Oportunidade | K8: =IF($B$3="","",INDEX('Fatores Externos (O-A)'!$A8:$R8,1,$B$3)) -> 3 | L8: =IF(AND(J8="Oportunidade",ISNUMBER(K8)),IF(K8>=Parâmetros!$B$5,1,0),0) -> 1 | M8: =IF(L8=1,SUM(L$6:L8),"") -> 3 | N8: =IF(AND(J8="Ameaça",ISNUMBER(K8)),IF(K8>=Parâmetros!$B$5,1,0),0) -> 0 | O8: =IF(N8=1,SUM(N$6:N8),"")
A9: ='Indicadores (F-W)'!A9 -> AGR-04 | B9: ="["&'Indicadores (F-W)'!B9&"] "&'Indicadores (F-W)'!A9&" – "&'Indicadores (F-W)'!C9&" ("&'Indicadores (F-W)'!D9&")" -> [Agropecuária] AGR-04 – Estabelecimentos agropecuários que receberam assistência técnica (%) | C9: =IF($B$2="","",INDEX('Indicadores (F-W)'!$A9:$AM9,1,$B$2+1)) | D9: =IF($B$2="","",INDEX('Indicadores (F-W)'!$A9:$AM9,1,$B$2)) -> 0 | E9: =IF(C9="Força",COUNTIF(C$6:C9,"Força"),"") | F9: =IF(C9="Fraqueza",COUNTIF(C$6:C9,"Fraqueza"),"") | H9: ='Fatores Externos (O-A)'!A9 -> OP-04 | I9: ="["&'Fatores Externos (O-A)'!C9&"] "&'Fatores Externos (O-A)'!A9&" – "&'Fatores Externos (O-A)'!D9 -> [Indústria] OP-04 – Agroindustrialização e verticalização (frigoríficos, laticínios, sucroenergético) | J9: ='Fatores Externos (O-A)'!B9 -> Oportunidade | K9: =IF($B$3="","",INDEX('Fatores Externos (O-A)'!$A9:$R9,1,$B$3)) -> 2 | L9: =IF(AND(J9="Oportunidade",ISNUMBER(K9)),IF(K9>=Parâmetros!$B$5,1,0),0) -> 1 | M9: =IF(L9=1,SUM(L$6:L9),"") -> 4 | N9: =IF(AND(J9="Ameaça",ISNUMBER(K9)),IF(K9>=Parâmetros!$B$5,1,0),0) -> 0 | O9: =IF(N9=1,SUM(N$6:N9),"")
A10: ='Indicadores (F-W)'!A10 -> AGR-05 | B10: ="["&'Indicadores (F-W)'!B10&"] "&'Indicadores (F-W)'!A10&" – "&'Indicadores (F-W)'!C10&" ("&'Indicadores (F-W)'!D10&")" -> [Agropecuária] AGR-05 – Diversificação agrícola (1 − HHI do valor da produção das lavouras) (índice 0–1) | C10: =IF($B$2="","",INDEX('Indicadores (F-W)'!$A10:$AM10,1,$B$2+1)) | D10: =IF($B$2="","",INDEX('Indicadores (F-W)'!$A10:$AM10,1,$B$2)) -> 0 | E10: =IF(C10="Força",COUNTIF(C$6:C10,"Força"),"") | F10: =IF(C10="Fraqueza",COUNTIF(C$6:C10,"Fraqueza"),"") | H10: ='Fatores Externos (O-A)'!A10 -> OP-05 | I10: ="["&'Fatores Externos (O-A)'!C10&"] "&'Fatores Externos (O-A)'!A10&" – "&'Fatores Externos (O-A)'!D10 -> [Estrutura Econômica e Fiscal] OP-05 – Corredores logísticos (rodovias federais, ferrovia, hidrovia do Paraguai) | J10: ='Fatores Externos (O-A)'!B10 -> Oportunidade | K10: =IF($B$3="","",INDEX('Fatores Externos (O-A)'!$A10:$R10,1,$B$3)) -> 3 | L10: =IF(AND(J10="Oportunidade",ISNUMBER(K10)),IF(K10>=Parâmetros!$B$5,1,0),0) -> 1 | M10: =IF(L10=1,SUM(L$6:L10),"") -> 5 | N10: =IF(AND(J10="Ameaça",ISNUMBER(K10)),IF(K10>=Parâmetros!$B$5,1,0),0) -> 0 | O10: =IF(N10=1,SUM(N$6:N10),"")
A11: ='Indicadores (F-W)'!A11 -> IND-01 | B11: ="["&'Indicadores (F-W)'!B11&"] "&'Indicadores (F-W)'!A11&" – "&'Indicadores (F-W)'!C11&" ("&'Indicadores (F-W)'!D11&")" -> [Indústria] IND-01 – Quociente locacional do VAB industrial (base MT) (índice) | C11: =IF($B$2="","",INDEX('Indicadores (F-W)'!$A11:$AM11,1,$B$2+1)) -> Fraqueza | D11: =IF($B$2="","",INDEX('Indicadores (F-W)'!$A11:$AM11,1,$B$2)) -> 0.6374 | E11: =IF(C11="Força",COUNTIF(C$6:C11,"Força"),"") | F11: =IF(C11="Fraqueza",COUNTIF(C$6:C11,"Fraqueza"),"") -> 2 | H11: ='Fatores Externos (O-A)'!A11 -> OP-06 | I11: ="["&'Fatores Externos (O-A)'!C11&"] "&'Fatores Externos (O-A)'!A11&" – "&'Fatores Externos (O-A)'!D11 -> [Estrutura Econômica e Fiscal] OP-06 – Instrumentos de fomento e financiamento (FCO, crédito rural, PSA, mercado de carbono) | J11: ='Fatores Externos (O-A)'!B11 -> Oportunidade | K11: =IF($B$3="","",INDEX('Fatores Externos (O-A)'!$A11:$R11,1,$B$3)) -> 3 | L11: =IF(AND(J11="Oportunidade",ISNUMBER(K11)),IF(K11>=Parâmetros!$B$5,1,0),0) -> 1 | M11: =IF(L11=1,SUM(L$6:L11),"") -> 6 | N11: =IF(AND(J11="Ameaça",ISNUMBER(K11)),IF(K11>=Parâmetros!$B$5,1,0),0) -> 0 | O11: =IF(N11=1,SUM(N$6:N11),"")
A12: ='Indicadores (F-W)'!A12 -> IND-02 | B12: ="["&'Indicadores (F-W)'!B12&"] "&'Indicadores (F-W)'!A12&" – "&'Indicadores (F-W)'!C12&" ("&'Indicadores (F-W)'!D12&")" -> [Indústria] IND-02 – Variação do emprego formal na indústria em 5 anos (%) | C12: =IF($B$2="","",INDEX('Indicadores (F-W)'!$A12:$AM12,1,$B$2+1)) -> Força | D12: =IF($B$2="","",INDEX('Indicadores (F-W)'!$A12:$AM12,1,$B$2)) -> 58.91 | E12: =IF(C12="Força",COUNTIF(C$6:C12,"Força"),"") -> 2 | F12: =IF(C12="Fraqueza",COUNTIF(C$6:C12,"Fraqueza"),"") | H12: ='Fatores Externos (O-A)'!A12 -> AM-01 | I12: ="["&'Fatores Externos (O-A)'!C12&"] "&'Fatores Externos (O-A)'!A12&" – "&'Fatores Externos (O-A)'!D12 -> [Agropecuária] AM-01 – Eventos climáticos extremos: secas prolongadas e incêndios no Pantanal | J12: ='Fatores Externos (O-A)'!B12 -> Ameaça | K12: =IF($B$3="","",INDEX('Fatores Externos (O-A)'!$A12:$R12,1,$B$3)) -> 3 | L12: =IF(AND(J12="Oportunidade",ISNUMBER(K12)),IF(K12>=Parâmetros!$B$5,1,0),0) -> 0 | M12: =IF(L12=1,SUM(L$6:L12),"") | N12: =IF(AND(J12="Ameaça",ISNUMBER(K12)),IF(K12>=Parâmetros!$B$5,1,0),0) -> 1 | O12: =IF(N12=1,SUM(N$6:N12),"") -> 1
A13: ='Indicadores (F-W)'!A13 -> IND-03 | B13: ="["&'Indicadores (F-W)'!B13&"] "&'Indicadores (F-W)'!A13&" – "&'Indicadores (F-W)'!C13&" ("&'Indicadores (F-W)'!D13&")" -> [Indústria] IND-03 – Remuneração média do emprego formal industrial (R$) | C13: =IF($B$2="","",INDEX('Indicadores (F-W)'!$A13:$AM13,1,$B$2+1)) -> Fraqueza | D13: =IF($B$2="","",INDEX('Indicadores (F-W)'!$A13:$AM13,1,$B$2)) -> 2345.65 | E13: =IF(C13="Força",COUNTIF(C$6:C13,"Força"),"") | F13: =IF(C13="Fraqueza",COUNTIF(C$6:C13,"Fraqueza"),"") -> 3 | H13: ='Fatores Externos (O-A)'!A13 -> AM-02 | I13: ="["&'Fatores Externos (O-A)'!C13&"] "&'Fatores Externos (O-A)'!A13&" – "&'Fatores Externos (O-A)'!D13 -> [Agropecuária] AM-02 – Volatilidade de preços de commodities (boi gordo, soja, milho) | J13: ='Fatores Externos (O-A)'!B13 -> Ameaça | K13: =IF($B$3="","",INDEX('Fatores Externos (O-A)'!$A13:$R13,1,$B$3)) -> 3 | L13: =IF(AND(J13="Oportunidade",ISNUMBER(K13)),IF(K13>=Parâmetros!$B$5,1,0),0) -> 0 | M13: =IF(L13=1,SUM(L$6:L13),"") | N13: =IF(AND(J13="Ameaça",ISNUMBER(K13)),IF(K13>=Parâmetros!$B$5,1,0),0) -> 1 | O13: =IF(N13=1,SUM(N$6:N13),"") -> 2
A14: ='Indicadores (F-W)'!A14 -> CS-01 | B14: ="["&'Indicadores (F-W)'!B14&"] "&'Indicadores (F-W)'!A14&" – "&'Indicadores (F-W)'!C14&" ("&'Indicadores (F-W)'!D14&")" -> [Comércio e Serviços] CS-01 – Quociente locacional do VAB de serviços, exceto adm. pública (base MT) (índice) | C14: =IF($B$2="","",INDEX('Indicadores (F-W)'!$A14:$AM14,1,$B$2+1)) -> Força | D14: =IF($B$2="","",INDEX('Indicadores (F-W)'!$A14:$AM14,1,$B$2)) -> 1.3013 | E14: =IF(C14="Força",COUNTIF(C$6:C14,"Força"),"") -> 3 | F14: =IF(C14="Fraqueza",COUNTIF(C$6:C14,"Fraqueza"),"") | H14: ='Fatores Externos (O-A)'!A14 -> AM-03 | I14: ="["&'Fatores Externos (O-A)'!C14&"] "&'Fatores Externos (O-A)'!A14&" – "&'Fatores Externos (O-A)'!D14 -> [Agropecuária] AM-03 – Exigências ambientais de mercados importadores e barreiras ligadas a desmatamento (ex.: EUDR) | J14: ='Fatores Externos (O-A)'!B14 -> Ameaça | K14: =IF($B$3="","",INDEX('Fatores Externos (O-A)'!$A14:$R14,1,$B$3)) -> 3 | L14: =IF(AND(J14="Oportunidade",ISNUMBER(K14)),IF(K14>=Parâmetros!$B$5,1,0),0) -> 0 | M14: =IF(L14=1,SUM(L$6:L14),"") | N14: =IF(AND(J14="Ameaça",ISNUMBER(K14)),IF(K14>=Parâmetros!$B$5,1,0),0) -> 1 | O14: =IF(N14=1,SUM(N$6:N14),"") -> 3
A15: ='Indicadores (F-W)'!A15 -> CS-02 | B15: ="["&'Indicadores (F-W)'!B15&"] "&'Indicadores (F-W)'!A15&" – "&'Indicadores (F-W)'!C15&" ("&'Indicadores (F-W)'!D15&")" -> [Comércio e Serviços] CS-02 – Variação do emprego formal em comércio e serviços em 5 anos (%) | C15: =IF($B$2="","",INDEX('Indicadores (F-W)'!$A15:$AM15,1,$B$2+1)) -> Fraqueza | D15: =IF($B$2="","",INDEX('Indicadores (F-W)'!$A15:$AM15,1,$B$2)) -> 13.05 | E15: =IF(C15="Força",COUNTIF(C$6:C15,"Força"),"") | F15: =IF(C15="Fraqueza",COUNTIF(C$6:C15,"Fraqueza"),"") -> 4 | H15: ='Fatores Externos (O-A)'!A15 -> AM-04 | I15: ="["&'Fatores Externos (O-A)'!C15&"] "&'Fatores Externos (O-A)'!A15&" – "&'Fatores Externos (O-A)'!D15 -> [Estrutura Econômica e Fiscal] AM-04 – Transição da Reforma Tributária (IBS/CBS) e efeitos sobre a repartição de receitas municipais | J15: ='Fatores Externos (O-A)'!B15 -> Ameaça | K15: =IF($B$3="","",INDEX('Fatores Externos (O-A)'!$A15:$R15,1,$B$3)) -> 2 | L15: =IF(AND(J15="Oportunidade",ISNUMBER(K15)),IF(K15>=Parâmetros!$B$5,1,0),0) -> 0 | M15: =IF(L15=1,SUM(L$6:L15),"") | N15: =IF(AND(J15="Ameaça",ISNUMBER(K15)),IF(K15>=Parâmetros!$B$5,1,0),0) -> 1 | O15: =IF(N15=1,SUM(N$6:N15),"") -> 4
A16: ='Indicadores (F-W)'!A16 -> CS-03 | B16: ="["&'Indicadores (F-W)'!B16&"] "&'Indicadores (F-W)'!A16&" – "&'Indicadores (F-W)'!C16&" ("&'Indicadores (F-W)'!D16&")" -> [Comércio e Serviços] CS-03 – Empresas e outras organizações ativas por mil habitantes (un./mil hab.) | C16: =IF($B$2="","",INDEX('Indicadores (F-W)'!$A16:$AM16,1,$B$2+1)) -> Fraqueza | D16: =IF($B$2="","",INDEX('Indicadores (F-W)'!$A16:$AM16,1,$B$2)) -> 19.41 | E16: =IF(C16="Força",COUNTIF(C$6:C16,"Força"),"") | F16: =IF(C16="Fraqueza",COUNTIF(C$6:C16,"Fraqueza"),"") -> 5 | H16: ='Fatores Externos (O-A)'!A16 -> AM-05 | I16: ="["&'Fatores Externos (O-A)'!C16&"] "&'Fatores Externos (O-A)'!A16&" – "&'Fatores Externos (O-A)'!D16 -> [Comércio e Serviços] AM-05 – Polarização regional por centros maiores (evasão de consumo, serviços e mão de obra) | J16: ='Fatores Externos (O-A)'!B16 -> Ameaça | K16: =IF($B$3="","",INDEX('Fatores Externos (O-A)'!$A16:$R16,1,$B$3)) -> 1 | L16: =IF(AND(J16="Oportunidade",ISNUMBER(K16)),IF(K16>=Parâmetros!$B$5,1,0),0) -> 0 | M16: =IF(L16=1,SUM(L$6:L16),"") | N16: =IF(AND(J16="Ameaça",ISNUMBER(K16)),IF(K16>=Parâmetros!$B$5,1,0),0) -> 0 | O16: =IF(N16=1,SUM(N$6:N16),"")
A17: ='Indicadores (F-W)'!A17 -> EST-01 | B17: ="["&'Indicadores (F-W)'!B17&"] "&'Indicadores (F-W)'!A17&" – "&'Indicadores (F-W)'!C17&" ("&'Indicadores (F-W)'!D17&")" -> [Estrutura Econômica e Fiscal] EST-01 – PIB per capita (R$) | C17: =IF($B$2="","",INDEX('Indicadores (F-W)'!$A17:$AM17,1,$B$2+1)) -> Fraqueza | D17: =IF($B$2="","",INDEX('Indicadores (F-W)'!$A17:$AM17,1,$B$2)) -> 31174.15 | E17: =IF(C17="Força",COUNTIF(C$6:C17,"Força"),"") | F17: =IF(C17="Fraqueza",COUNTIF(C$6:C17,"Fraqueza"),"") -> 6
A18: ='Indicadores (F-W)'!A18 -> EST-02 | B18: ="["&'Indicadores (F-W)'!B18&"] "&'Indicadores (F-W)'!A18&" – "&'Indicadores (F-W)'!C18&" ("&'Indicadores (F-W)'!D18&")" -> [Estrutura Econômica e Fiscal] EST-02 – Participação da administração pública no VAB total (%) | C18: =IF($B$2="","",INDEX('Indicadores (F-W)'!$A18:$AM18,1,$B$2+1)) -> Fraqueza | D18: =IF($B$2="","",INDEX('Indicadores (F-W)'!$A18:$AM18,1,$B$2)) -> 30.82 | E18: =IF(C18="Força",COUNTIF(C$6:C18,"Força"),"") | F18: =IF(C18="Fraqueza",COUNTIF(C$6:C18,"Fraqueza"),"") -> 7
A19: ='Indicadores (F-W)'!A19 -> EST-03 | B19: ="["&'Indicadores (F-W)'!B19&"] "&'Indicadores (F-W)'!A19&" – "&'Indicadores (F-W)'!C19&" ("&'Indicadores (F-W)'!D19&")" -> [Estrutura Econômica e Fiscal] EST-03 – Vínculos formais por 100 habitantes (vínculos/100 hab.) | C19: =IF($B$2="","",INDEX('Indicadores (F-W)'!$A19:$AM19,1,$B$2+1)) -> Fraqueza | D19: =IF($B$2="","",INDEX('Indicadores (F-W)'!$A19:$AM19,1,$B$2)) -> 18.4 | E19: =IF(C19="Força",COUNTIF(C$6:C19,"Força"),"") | F19: =IF(C19="Fraqueza",COUNTIF(C$6:C19,"Fraqueza"),"") -> 8
A20: ='Indicadores (F-W)'!A20 -> EST-04 | B20: ="["&'Indicadores (F-W)'!B20&"] "&'Indicadores (F-W)'!A20&" – "&'Indicadores (F-W)'!C20&" ("&'Indicadores (F-W)'!D20&")" -> [Estrutura Econômica e Fiscal] EST-04 – Concentração setorial do emprego formal (HHI por seção CNAE) (índice 0–1) | C20: =IF($B$2="","",INDEX('Indicadores (F-W)'!$A20:$AM20,1,$B$2+1)) -> Neutro | D20: =IF($B$2="","",INDEX('Indicadores (F-W)'!$A20:$AM20,1,$B$2)) -> 0.1286 | E20: =IF(C20="Força",COUNTIF(C$6:C20,"Força"),"") | F20: =IF(C20="Fraqueza",COUNTIF(C$6:C20,"Fraqueza"),"")
A21: ='Indicadores (F-W)'!A21 -> EST-05 | B21: ="["&'Indicadores (F-W)'!B21&"] "&'Indicadores (F-W)'!A21&" – "&'Indicadores (F-W)'!C21&" ("&'Indicadores (F-W)'!D21&")" -> [Estrutura Econômica e Fiscal] EST-05 – Receitas próprias / receita corrente (%) | C21: =IF($B$2="","",INDEX('Indicadores (F-W)'!$A21:$AM21,1,$B$2+1)) -> Neutro | D21: =IF($B$2="","",INDEX('Indicadores (F-W)'!$A21:$AM21,1,$B$2)) -> 17.68 | E21: =IF(C21="Força",COUNTIF(C$6:C21,"Força"),"") | F21: =IF(C21="Fraqueza",COUNTIF(C$6:C21,"Fraqueza"),"")

Sheet SWOT - Barão de Melgaço
B1: MATRIZ SWOT — BARÃO DE MELGAÇO (MT)
B2: Perfil Econômico-Produtivo Setorial Municipal (PESM) | Projeto DSIP-MT – Meta 1 | Pantanal Norte
B3: ="Indicadores internos com dado: "&(COUNTA(L6:L21)-COUNTBLANK(L6:L21))&" de 16 | Neutros: "&COUNTIF(L6:L21,"Neutro")&" | Fatores externos pontuados: "&COUNT(S6:S16)&" de 11" -> Indicadores internos com dado: 14 de 16 | Neutros: 1 | Fatores externos pontuados: 11 de 11
B5: FAVORÁVEL | F5: DESFAVORÁVEL
B6: ="FORÇAS (S) — "&COUNTIF($L$6:$L$21,"Força")&" item(ns)" -> FORÇAS (S) — 3 item(ns) | F6: ="FRAQUEZAS (W) — "&COUNTIF($L$6:$L$21,"Fraqueza")&" item(ns)" -> FRAQUEZAS (W) — 10 item(ns) | K6: =Aux!B6 -> [Agropecuária] AGR-01 – Quociente locacional do VAB agropecuário (base MT) (índice) | L6: ='Indicadores (F-W)'!O6 -> Neutro | M6: =IF('Indicadores (F-W)'!N6="","",'Indicadores (F-W)'!N6) -> 0.9631 | N6: =IF(L6="Força",COUNTIF(L$6:L6,"Força"),"") | O6: =IF(L6="Fraqueza",COUNTIF(L$6:L6,"Fraqueza"),"") | Q6: =Aux!I6 -> [Agropecuária] OP-01 – Demanda externa por carne bovina e proteína animal | R6: =Aux!J6 -> Oportunidade | S6: =IF('Fatores Externos (O-A)'!F6="","",'Fatores Externos (O-A)'!F6) -> 1 | T6: =IF(AND(R6="Oportunidade",ISNUMBER(S6)),IF(S6>=Parâmetros!$B$5,1,0),0) -> 0 | U6: =IF(T6=1,SUM(T$6:T6),"") | V6: =IF(AND(R6="Ameaça",ISNUMBER(S6)),IF(S6>=Parâmetros!$B$5,1,0),0) -> 0 | W6: =IF(V6=1,SUM(V$6:V6),"")
B7: Nº | C7: Item (área-chave, código e descrição) | D7: Valor | F7: Nº | G7: Item (área-chave, código e descrição) | H7: Valor | K7: =Aux!B7 -> [Agropecuária] AGR-02 – Valor da produção das lavouras por área colhida (R$/ha) | L7: ='Indicadores (F-W)'!O7 -> Força | M7: =IF('Indicadores (F-W)'!N7="","",'Indicadores (F-W)'!N7) -> 19926.55 | N7: =IF(L7="Força",COUNTIF(L$6:L7,"Força"),"") -> 1 | O7: =IF(L7="Fraqueza",COUNTIF(L$6:L7,"Fraqueza"),"") | Q7: =Aux!I7 -> [Agropecuária] OP-02 – Mercados para produtos diferenciados e certificados (carne sustentável/orgânica, origem Pantanal) | R7: =Aux!J7 -> Oportunidade | S7: =IF('Fatores Externos (O-A)'!F7="","",'Fatores Externos (O-A)'!F7) -> 3 | T7: =IF(AND(R7="Oportunidade",ISNUMBER(S7)),IF(S7>=Parâmetros!$B$5,1,0),0) -> 1 | U7: =IF(T7=1,SUM(T$6:T7),"") -> 1 | V7: =IF(AND(R7="Ameaça",ISNUMBER(S7)),IF(S7>=Parâmetros!$B$5,1,0),0) -> 0 | W7: =IF(V7=1,SUM(V$6:V7),"")
A8: AMBIENTE INTERNO | B8: =IF(C8="","",1) -> 1 | C8: =IFERROR(INDEX($K$6:$K$21,MATCH(1,$N$6:$N$21,0)),"") -> [Agropecuária] AGR-02 – Valor da produção das lavouras por área colhida (R$/ha) | D8: =IFERROR(INDEX($M$6:$M$21,MATCH(1,$N$6:$N$21,0)),"") -> 19926.55 | F8: =IF(G8="","",1) -> 1 | G8: =IFERROR(INDEX($K$6:$K$21,MATCH(1,$O$6:$O$21,0)),"") -> [Indústria] IND-01 – Quociente locacional do VAB industrial (base MT) (índice) | H8: =IFERROR(INDEX($M$6:$M$21,MATCH(1,$O$6:$O$21,0)),"") -> 0.169 | K8: =Aux!B8 -> [Agropecuária] AGR-03 – Variação do efetivo bovino em 5 anos (%) | L8: ='Indicadores (F-W)'!O8 -> Força | M8: =IF('Indicadores (F-W)'!N8="","",'Indicadores (F-W)'!N8) -> 16.6 | N8: =IF(L8="Força",COUNTIF(L$6:L8,"Força"),"") -> 2 | O8: =IF(L8="Fraqueza",COUNTIF(L$6:L8,"Fraqueza"),"") | Q8: =Aux!I8 -> [Comércio e Serviços] OP-03 – Expansão do turismo de natureza, pesca esportiva e ecoturismo | R8: =Aux!J8 -> Oportunidade | S8: =IF('Fatores Externos (O-A)'!F8="","",'Fatores Externos (O-A)'!F8) -> 3 | T8: =IF(AND(R8="Oportunidade",ISNUMBER(S8)),IF(S8>=Parâmetros!$B$5,1,0),0) -> 1 | U8: =IF(T8=1,SUM(T$6:T8),"") -> 2 | V8: =IF(AND(R8="Ameaça",ISNUMBER(S8)),IF(S8>=Parâmetros!$B$5,1,0),0) -> 0 | W8: =IF(V8=1,SUM(V$6:V8),"")
B9: =IF(C9="","",2) -> 2 | C9: =IFERROR(INDEX($K$6:$K$21,MATCH(2,$N$6:$N$21,0)),"") -> [Agropecuária] AGR-03 – Variação do efetivo bovino em 5 anos (%) | D9: =IFERROR(INDEX($M$6:$M$21,MATCH(2,$N$6:$N$21,0)),"") -> 16.6 | F9: =IF(G9="","",2) -> 2 | G9: =IFERROR(INDEX($K$6:$K$21,MATCH(2,$O$6:$O$21,0)),"") -> [Indústria] IND-03 – Remuneração média do emprego formal industrial (R$) | H9: =IFERROR(INDEX($M$6:$M$21,MATCH(2,$O$6:$O$21,0)),"") -> 2624.01 | K9: =Aux!B9 -> [Agropecuária] AGR-04 – Estabelecimentos agropecuários que receberam assistência técnica (%) | L9: ='Indicadores (F-W)'!O9 | M9: =IF('Indicadores (F-W)'!N9="","",'Indicadores (F-W)'!N9) | N9: =IF(L9="Força",COUNTIF(L$6:L9,"Força"),"") | O9: =IF(L9="Fraqueza",COUNTIF(L$6:L9,"Fraqueza"),"") | Q9: =Aux!I9 -> [Indústria] OP-04 – Agroindustrialização e verticalização (frigoríficos, laticínios, sucroenergético) | R9: =Aux!J9 -> Oportunidade | S9: =IF('Fatores Externos (O-A)'!F9="","",'Fatores Externos (O-A)'!F9) -> 0 | T9: =IF(AND(R9="Oportunidade",ISNUMBER(S9)),IF(S9>=Parâmetros!$B$5,1,0),0) -> 0 | U9: =IF(T9=1,SUM(T$6:T9),"") | V9: =IF(AND(R9="Ameaça",ISNUMBER(S9)),IF(S9>=Parâmetros!$B$5,1,0),0) -> 0 | W9: =IF(V9=1,SUM(V$6:V9),"")
B10: =IF(C10="","",3) -> 3 | C10: =IFERROR(INDEX($K$6:$K$21,MATCH(3,$N$6:$N$21,0)),"") -> [Indústria] IND-02 – Variação do emprego formal na indústria em 5 anos (%) | D10: =IFERROR(INDEX($M$6:$M$21,MATCH(3,$N$6:$N$21,0)),"") -> 2299.57 | F10: =IF(G10="","",3) -> 3 | G10: =IFERROR(INDEX($K$6:$K$21,MATCH(3,$O$6:$O$21,0)),"") -> [Comércio e Serviços] CS-01 – Quociente locacional do VAB de serviços, exceto adm. pública (base MT) (índice) | H10: =IFERROR(INDEX($M$6:$M$21,MATCH(3,$O$6:$O$21,0)),"") -> 0.4274 | K10: =Aux!B10 -> [Agropecuária] AGR-05 – Diversificação agrícola (1 − HHI do valor da produção das lavouras) (índice 0–1) | L10: ='Indicadores (F-W)'!O10 | M10: =IF('Indicadores (F-W)'!N10="","",'Indicadores (F-W)'!N10) | N10: =IF(L10="Força",COUNTIF(L$6:L10,"Força"),"") | O10: =IF(L10="Fraqueza",COUNTIF(L$6:L10,"Fraqueza"),"") | Q10: =Aux!I10 -> [Estrutura Econômica e Fiscal] OP-05 – Corredores logísticos (rodovias federais, ferrovia, hidrovia do Paraguai) | R10: =Aux!J10 -> Oportunidade | S10: =IF('Fatores Externos (O-A)'!F10="","",'Fatores Externos (O-A)'!F10) -> 1 | T10: =IF(AND(R10="Oportunidade",ISNUMBER(S10)),IF(S10>=Parâmetros!$B$5,1,0),0) -> 0 | U10: =IF(T10=1,SUM(T$6:T10),"") | V10: =IF(AND(R10="Ameaça",ISNUMBER(S10)),IF(S10>=Parâmetros!$B$5,1,0),0) -> 0 | W10: =IF(V10=1,SUM(V$6:V10),"")
B11: =IF(C11="","",4) | C11: =IFERROR(INDEX($K$6:$K$21,MATCH(4,$N$6:$N$21,0)),"") | D11: =IFERROR(INDEX($M$6:$M$21,MATCH(4,$N$6:$N$21,0)),"") | F11: =IF(G11="","",4) -> 4 | G11: =IFERROR(INDEX($K$6:$K$21,MATCH(4,$O$6:$O$21,0)),"") -> [Comércio e Serviços] CS-02 – Variação do emprego formal em comércio e serviços em 5 anos (%) | H11: =IFERROR(INDEX($M$6:$M$21,MATCH(4,$O$6:$O$21,0)),"") -> 28.79 | K11: =Aux!B11 -> [Indústria] IND-01 – Quociente locacional do VAB industrial (base MT) (índice) | L11: ='Indicadores (F-W)'!O11 -> Fraqueza | M11: =IF('Indicadores (F-W)'!N11="","",'Indicadores (F-W)'!N11) -> 0.169 | N11: =IF(L11="Força",COUNTIF(L$6:L11,"Força"),"") | O11: =IF(L11="Fraqueza",COUNTIF(L$6:L11,"Fraqueza"),"") -> 1 | Q11: =Aux!I11 -> [Estrutura Econômica e Fiscal] OP-06 – Instrumentos de fomento e financiamento (FCO, crédito rural, PSA, mercado de carbono) | R11: =Aux!J11 -> Oportunidade | S11: =IF('Fatores Externos (O-A)'!F11="","",'Fatores Externos (O-A)'!F11) -> 2 | T11: =IF(AND(R11="Oportunidade",ISNUMBER(S11)),IF(S11>=Parâmetros!$B$5,1,0),0) -> 1 | U11: =IF(T11=1,SUM(T$6:T11),"") -> 3 | V11: =IF(AND(R11="Ameaça",ISNUMBER(S11)),IF(S11>=Parâmetros!$B$5,1,0),0) -> 0 | W11: =IF(V11=1,SUM(V$6:V11),"")
B12: =IF(C12="","",5) | C12: =IFERROR(INDEX($K$6:$K$21,MATCH(5,$N$6:$N$21,0)),"") | D12: =IFERROR(INDEX($M$6:$M$21,MATCH(5,$N$6:$N$21,0)),"") | F12: =IF(G12="","",5) -> 5 | G12: =IFERROR(INDEX($K$6:$K$21,MATCH(5,$O$6:$O$21,0)),"") -> [Comércio e Serviços] CS-03 – Empresas e outras organizações ativas por mil habitantes (un./mil hab.) | H12: =IFERROR(INDEX($M$6:$M$21,MATCH(5,$O$6:$O$21,0)),"") -> 9.06 | K12: =Aux!B12 -> [Indústria] IND-02 – Variação do emprego formal na indústria em 5 anos (%) | L12: ='Indicadores (F-W)'!O12 -> Força | M12: =IF('Indicadores (F-W)'!N12="","",'Indicadores (F-W)'!N12) -> 2299.57 | N12: =IF(L12="Força",COUNTIF(L$6:L12,"Força"),"") -> 3 | O12: =IF(L12="Fraqueza",COUNTIF(L$6:L12,"Fraqueza"),"") | Q12: =Aux!I12 -> [Agropecuária] AM-01 – Eventos climáticos extremos: secas prolongadas e incêndios no Pantanal | R12: =Aux!J12 -> Ameaça | S12: =IF('Fatores Externos (O-A)'!F12="","",'Fatores Externos (O-A)'!F12) -> 3 | T12: =IF(AND(R12="Oportunidade",ISNUMBER(S12)),IF(S12>=Parâmetros!$B$5,1,0),0) -> 0 | U12: =IF(T12=1,SUM(T$6:T12),"") | V12: =IF(AND(R12="Ameaça",ISNUMBER(S12)),IF(S12>=Parâmetros!$B$5,1,0),0) -> 1 | W12: =IF(V12=1,SUM(V$6:V12),"") -> 1
B13: =IF(C13="","",6) | C13: =IFERROR(INDEX($K$6:$K$21,MATCH(6,$N$6:$N$21,0)),"") | D13: =IFERROR(INDEX($M$6:$M$21,MATCH(6,$N$6:$N$21,0)),"") | F13: =IF(G13="","",6) -> 6 | G13: =IFERROR(INDEX($K$6:$K$21,MATCH(6,$O$6:$O$21,0)),"") -> [Estrutura Econômica e Fiscal] EST-01 – PIB per capita (R$) | H13: =IFERROR(INDEX($M$6:$M$21,MATCH(6,$O$6:$O$21,0)),"") -> 19806.58 | K13: =Aux!B13 -> [Indústria] IND-03 – Remuneração média do emprego formal industrial (R$) | L13: ='Indicadores (F-W)'!O13 -> Fraqueza | M13: =IF('Indicadores (F-W)'!N13="","",'Indicadores (F-W)'!N13) -> 2624.01 | N13: =IF(L13="Força",COUNTIF(L$6:L13,"Força"),"") | O13: =IF(L13="Fraqueza",COUNTIF(L$6:L13,"Fraqueza"),"") -> 2 | Q13: =Aux!I13 -> [Agropecuária] AM-02 – Volatilidade de preços de commodities (boi gordo, soja, milho) | R13: =Aux!J13 -> Ameaça | S13: =IF('Fatores Externos (O-A)'!F13="","",'Fatores Externos (O-A)'!F13) -> 2 | T13: =IF(AND(R13="Oportunidade",ISNUMBER(S13)),IF(S13>=Parâmetros!$B$5,1,0),0) -> 0 | U13: =IF(T13=1,SUM(T$6:T13),"") | V13: =IF(AND(R13="Ameaça",ISNUMBER(S13)),IF(S13>=Parâmetros!$B$5,1,0),0) -> 1 | W13: =IF(V13=1,SUM(V$6:V13),"") -> 2
B14: =IF(C14="","",7) | C14: =IFERROR(INDEX($K$6:$K$21,MATCH(7,$N$6:$N$21,0)),"") | D14: =IFERROR(INDEX($M$6:$M$21,MATCH(7,$N$6:$N$21,0)),"") | F14: =IF(G14="","",7) -> 7 | G14: =IFERROR(INDEX($K$6:$K$21,MATCH(7,$O$6:$O$21,0)),"") -> [Estrutura Econômica e Fiscal] EST-02 – Participação da administração pública no VAB total (%) | H14: =IFERROR(INDEX($M$6:$M$21,MATCH(7,$O$6:$O$21,0)),"") -> 45.95 | K14: =Aux!B14 -> [Comércio e Serviços] CS-01 – Quociente locacional do VAB de serviços, exceto adm. pública (base MT) (índice) | L14: ='Indicadores (F-W)'!O14 -> Fraqueza | M14: =IF('Indicadores (F-W)'!N14="","",'Indicadores (F-W)'!N14) -> 0.4274 | N14: =IF(L14="Força",COUNTIF(L$6:L14,"Força"),"") | O14: =IF(L14="Fraqueza",COUNTIF(L$6:L14,"Fraqueza"),"") -> 3 | Q14: =Aux!I14 -> [Agropecuária] AM-03 – Exigências ambientais de mercados importadores e barreiras ligadas a desmatamento (ex.: EUDR) | R14: =Aux!J14 -> Ameaça | S14: =IF('Fatores Externos (O-A)'!F14="","",'Fatores Externos (O-A)'!F14) -> 2 | T14: =IF(AND(R14="Oportunidade",ISNUMBER(S14)),IF(S14>=Parâmetros!$B$5,1,0),0) -> 0 | U14: =IF(T14=1,SUM(T$6:T14),"") | V14: =IF(AND(R14="Ameaça",ISNUMBER(S14)),IF(S14>=Parâmetros!$B$5,1,0),0) -> 1 | W14: =IF(V14=1,SUM(V$6:V14),"") -> 3
B15: =IF(C15="","",8) | C15: =IFERROR(INDEX($K$6:$K$21,MATCH(8,$N$6:$N$21,0)),"") | D15: =IFERROR(INDEX($M$6:$M$21,MATCH(8,$N$6:$N$21,0)),"") | F15: =IF(G15="","",8) -> 8 | G15: =IFERROR(INDEX($K$6:$K$21,MATCH(8,$O$6:$O$21,0)),"") -> [Estrutura Econômica e Fiscal] EST-03 – Vínculos formais por 100 habitantes (vínculos/100 hab.) | H15: =IFERROR(INDEX($M$6:$M$21,MATCH(8,$O$6:$O$21,0)),"") -> 8.4 | K15: =Aux!B15 -> [Comércio e Serviços] CS-02 – Variação do emprego formal em comércio e serviços em 5 anos (%) | L15: ='Indicadores (F-W)'!O15 -> Fraqueza | M15: =IF('Indicadores (F-W)'!N15="","",'Indicadores (F-W)'!N15) -> 28.79 | N15: =IF(L15="Força",COUNTIF(L$6:L15,"Força"),"") | O15: =IF(L15="Fraqueza",COUNTIF(L$6:L15,"Fraqueza"),"") -> 4 | Q15: =Aux!I15 -> [Estrutura Econômica e Fiscal] AM-04 – Transição da Reforma Tributária (IBS/CBS) e efeitos sobre a repartição de receitas municipais | R15: =Aux!J15 -> Ameaça | S15: =IF('Fatores Externos (O-A)'!F15="","",'Fatores Externos (O-A)'!F15) -> 1 | T15: =IF(AND(R15="Oportunidade",ISNUMBER(S15)),IF(S15>=Parâmetros!$B$5,1,0),0) -> 0 | U15: =IF(T15=1,SUM(T$6:T15),"") | V15: =IF(AND(R15="Ameaça",ISNUMBER(S15)),IF(S15>=Parâmetros!$B$5,1,0),0) -> 0 | W15: =IF(V15=1,SUM(V$6:V15),"")
B16: =IF(C16="","",9) | C16: =IFERROR(INDEX($K$6:$K$21,MATCH(9,$N$6:$N$21,0)),"") | D16: =IFERROR(INDEX($M$6:$M$21,MATCH(9,$N$6:$N$21,0)),"") | F16: =IF(G16="","",9) -> 9 | G16: =IFERROR(INDEX($K$6:$K$21,MATCH(9,$O$6:$O$21,0)),"") -> [Estrutura Econômica e Fiscal] EST-04 – Concentração setorial do emprego formal (HHI por seção CNAE) (índice 0–1) | H16: =IFERROR(INDEX($M$6:$M$21,MATCH(9,$O$6:$O$21,0)),"") -> 0.2519 | K16: =Aux!B16 -> [Comércio e Serviços] CS-03 – Empresas e outras organizações ativas por mil habitantes (un./mil hab.) | L16: ='Indicadores (F-W)'!O16 -> Fraqueza | M16: =IF('Indicadores (F-W)'!N16="","",'Indicadores (F-W)'!N16) -> 9.06 | N16: =IF(L16="Força",COUNTIF(L$6:L16,"Força"),"") | O16: =IF(L16="Fraqueza",COUNTIF(L$6:L16,"Fraqueza"),"") -> 5 | Q16: =Aux!I16 -> [Comércio e Serviços] AM-05 – Polarização regional por centros maiores (evasão de consumo, serviços e mão de obra) | R16: =Aux!J16 -> Ameaça | S16: =IF('Fatores Externos (O-A)'!F16="","",'Fatores Externos (O-A)'!F16) -> 3 | T16: =IF(AND(R16="Oportunidade",ISNUMBER(S16)),IF(S16>=Parâmetros!$B$5,1,0),0) -> 0 | U16: =IF(T16=1,SUM(T$6:T16),"") | V16: =IF(AND(R16="Ameaça",ISNUMBER(S16)),IF(S16>=Parâmetros!$B$5,1,0),0) -> 1 | W16: =IF(V16=1,SUM(V$6:V16),"") -> 4
B17: =IF(C17="","",10) | C17: =IFERROR(INDEX($K$6:$K$21,MATCH(10,$N$6:$N$21,0)),"") | D17: =IFERROR(INDEX($M$6:$M$21,MATCH(10,$N$6:$N$21,0)),"") | F17: =IF(G17="","",10) -> 10 | G17: =IFERROR(INDEX($K$6:$K$21,MATCH(10,$O$6:$O$21,0)),"") -> [Estrutura Econômica e Fiscal] EST-05 – Receitas próprias / receita corrente (%) | H17: =IFERROR(INDEX($M$6:$M$21,MATCH(10,$O$6:$O$21,0)),"") -> 6.34 | K17: =Aux!B17 -> [Estrutura Econômica e Fiscal] EST-01 – PIB per capita (R$) | L17: ='Indicadores (F-W)'!O17 -> Fraqueza | M17: =IF('Indicadores (F-W)'!N17="","",'Indicadores (F-W)'!N17) -> 19806.58 | N17: =IF(L17="Força",COUNTIF(L$6:L17,"Força"),"") | O17: =IF(L17="Fraqueza",COUNTIF(L$6:L17,"Fraqueza"),"") -> 6
B18: =IF(C18="","",11) | C18: =IFERROR(INDEX($K$6:$K$21,MATCH(11,$N$6:$N$21,0)),"") | D18: =IFERROR(INDEX($M$6:$M$21,MATCH(11,$N$6:$N$21,0)),"") | F18: =IF(G18="","",11) | G18: =IFERROR(INDEX($K$6:$K$21,MATCH(11,$O$6:$O$21,0)),"") | H18: =IFERROR(INDEX($M$6:$M$21,MATCH(11,$O$6:$O$21,0)),"") | K18: =Aux!B18 -> [Estrutura Econômica e Fiscal] EST-02 – Participação da administração pública no VAB total (%) | L18: ='Indicadores (F-W)'!O18 -> Fraqueza | M18: =IF('Indicadores (F-W)'!N18="","",'Indicadores (F-W)'!N18) -> 45.95 | N18: =IF(L18="Força",COUNTIF(L$6:L18,"Força"),"") | O18: =IF(L18="Fraqueza",COUNTIF(L$6:L18,"Fraqueza"),"") -> 7
B19: =IF(C19="","",12) | C19: =IFERROR(INDEX($K$6:$K$21,MATCH(12,$N$6:$N$21,0)),"") | D19: =IFERROR(INDEX($M$6:$M$21,MATCH(12,$N$6:$N$21,0)),"") | F19: =IF(G19="","",12) | G19: =IFERROR(INDEX($K$6:$K$21,MATCH(12,$O$6:$O$21,0)),"") | H19: =IFERROR(INDEX($M$6:$M$21,MATCH(12,$O$6:$O$21,0)),"") | K19: =Aux!B19 -> [Estrutura Econômica e Fiscal] EST-03 – Vínculos formais por 100 habitantes (vínculos/100 hab.) | L19: ='Indicadores (F-W)'!O19 -> Fraqueza | M19: =IF('Indicadores (F-W)'!N19="","",'Indicadores (F-W)'!N19) -> 8.4 | N19: =IF(L19="Força",COUNTIF(L$6:L19,"Força"),"") | O19: =IF(L19="Fraqueza",COUNTIF(L$6:L19,"Fraqueza"),"") -> 8
C20: =IF(COUNTIF($L$6:$L$21,"Força")>12,"+ "&(COUNTIF($L$6:$L$21,"Força")-12)&" item(ns) não exibido(s)","") | G20: =IF(COUNTIF($L$6:$L$21,"Fraqueza")>12,"+ "&(COUNTIF($L$6:$L$21,"Fraqueza")-12)&" item(ns) não exibido(s)","") | K20: =Aux!B20 -> [Estrutura Econômica e Fiscal] EST-04 – Concentração setorial do emprego formal (HHI por seção CNAE) (índice 0–1) | L20: ='Indicadores (F-W)'!O20 -> Fraqueza | M20: =IF('Indicadores (F-W)'!N20="","",'Indicadores (F-W)'!N20) -> 0.2519 | N20: =IF(L20="Força",COUNTIF(L$6:L20,"Força"),"") | O20: =IF(L20="Fraqueza",COUNTIF(L$6:L20,"Fraqueza"),"") -> 9
K21: =Aux!B21 -> [Estrutura Econômica e Fiscal] EST-05 – Receitas próprias / receita corrente (%) | L21: ='Indicadores (F-W)'!O21 -> Fraqueza | M21: =IF('Indicadores (F-W)'!N21="","",'Indicadores (F-W)'!N21) -> 6.34 | N21: =IF(L21="Força",COUNTIF(L$6:L21,"Força"),"") | O21: =IF(L21="Fraqueza",COUNTIF(L$6:L21,"Fraqueza"),"") -> 10
B22: ="OPORTUNIDADES (O) — "&SUM($T$6:$T$16)&" item(ns)" -> OPORTUNIDADES (O) — 3 item(ns) | F22: ="AMEAÇAS (T) — "&SUM($V$6:$V$16)&" item(ns)" -> AMEAÇAS (T) — 4 item(ns)
B23: Nº | C23: Item (área-chave, código e descrição) | D23: Intensidade | F23: Nº | G23: Item (área-chave, código e descrição) | H23: Intensidade
A24: AMBIENTE EXTERNO | B24: =IF(C24="","",1) -> 1 | C24: =IFERROR(INDEX($Q$6:$Q$16,MATCH(1,$U$6:$U$16,0)),"") -> [Agropecuária] OP-02 – Mercados para produtos diferenciados e certificados (carne sustentável/orgânica, origem Pantanal) | D24: =IFERROR(INDEX($S$6:$S$16,MATCH(1,$U$6:$U$16,0)),"") -> 3 | F24: =IF(G24="","",1) -> 1 | G24: =IFERROR(INDEX($Q$6:$Q$16,MATCH(1,$W$6:$W$16,0)),"") -> [Agropecuária] AM-01 – Eventos climáticos extremos: secas prolongadas e incêndios no Pantanal | H24: =IFERROR(INDEX($S$6:$S$16,MATCH(1,$W$6:$W$16,0)),"") -> 3
B25: =IF(C25="","",2) -> 2 | C25: =IFERROR(INDEX($Q$6:$Q$16,MATCH(2,$U$6:$U$16,0)),"") -> [Comércio e Serviços] OP-03 – Expansão do turismo de natureza, pesca esportiva e ecoturismo | D25: =IFERROR(INDEX($S$6:$S$16,MATCH(2,$U$6:$U$16,0)),"") -> 3 | F25: =IF(G25="","",2) -> 2 | G25: =IFERROR(INDEX($Q$6:$Q$16,MATCH(2,$W$6:$W$16,0)),"") -> [Agropecuária] AM-02 – Volatilidade de preços de commodities (boi gordo, soja, milho) | H25: =IFERROR(INDEX($S$6:$S$16,MATCH(2,$W$6:$W$16,0)),"") -> 2
B26: =IF(C26="","",3) -> 3 | C26: =IFERROR(INDEX($Q$6:$Q$16,MATCH(3,$U$6:$U$16,0)),"") -> [Estrutura Econômica e Fiscal] OP-06 – Instrumentos de fomento e financiamento (FCO, crédito rural, PSA, mercado de carbono) | D26: =IFERROR(INDEX($S$6:$S$16,MATCH(3,$U$6:$U$16,0)),"") -> 2 | F26: =IF(G26="","",3) -> 3 | G26: =IFERROR(INDEX($Q$6:$Q$16,MATCH(3,$W$6:$W$16,0)),"") -> [Agropecuária] AM-03 – Exigências ambientais de mercados importadores e barreiras ligadas a desmatamento (ex.: EUDR) | H26: =IFERROR(INDEX($S$6:$S$16,MATCH(3,$W$6:$W$16,0)),"") -> 2
B27: =IF(C27="","",4) | C27: =IFERROR(INDEX($Q$6:$Q$16,MATCH(4,$U$6:$U$16,0)),"") | D27: =IFERROR(INDEX($S$6:$S$16,MATCH(4,$U$6:$U$16,0)),"") | F27: =IF(G27="","",4) -> 4 | G27: =IFERROR(INDEX($Q$6:$Q$16,MATCH(4,$W$6:$W$16,0)),"") -> [Comércio e Serviços] AM-05 – Polarização regional por centros maiores (evasão de consumo, serviços e mão de obra) | H27: =IFERROR(INDEX($S$6:$S$16,MATCH(4,$W$6:$W$16,0)),"") -> 3
B28: =IF(C28="","",5) | C28: =IFERROR(INDEX($Q$6:$Q$16,MATCH(5,$U$6:$U$16,0)),"") | D28: =IFERROR(INDEX($S$6:$S$16,MATCH(5,$U$6:$U$16,0)),"") | F28: =IF(G28="","",5) | G28: =IFERROR(INDEX($Q$6:$Q$16,MATCH(5,$W$6:$W$16,0)),"") | H28: =IFERROR(INDEX($S$6:$S$16,MATCH(5,$W$6:$W$16,0)),"")
B29: =IF(C29="","",6) | C29: =IFERROR(INDEX($Q$6:$Q$16,MATCH(6,$U$6:$U$16,0)),"") | D29: =IFERROR(INDEX($S$6:$S$16,MATCH(6,$U$6:$U$16,0)),"") | F29: =IF(G29="","",6) | G29: =IFERROR(INDEX($Q$6:$Q$16,MATCH(6,$W$6:$W$16,0)),"") | H29: =IFERROR(INDEX($S$6:$S$16,MATCH(6,$W$6:$W$16,0)),"")
B30: =IF(C30="","",7) | C30: =IFERROR(INDEX($Q$6:$Q$16,MATCH(7,$U$6:$U$16,0)),"") | D30: =IFERROR(INDEX($S$6:$S$16,MATCH(7,$U$6:$U$16,0)),"") | F30: =IF(G30="","",7) | G30: =IFERROR(INDEX($Q$6:$Q$16,MATCH(7,$W$6:$W$16,0)),"") | H30: =IFERROR(INDEX($S$6:$S$16,MATCH(7,$W$6:$W$16,0)),"")
B31: =IF(C31="","",8) | C31: =IFERROR(INDEX($Q$6:$Q$16,MATCH(8,$U$6:$U$16,0)),"") | D31: =IFERROR(INDEX($S$6:$S$16,MATCH(8,$U$6:$U$16,0)),"") | F31: =IF(G31="","",8) | G31: =IFERROR(INDEX($Q$6:$Q$16,MATCH(8,$W$6:$W$16,0)),"") | H31: =IFERROR(INDEX($S$6:$S$16,MATCH(8,$W$6:$W$16,0)),"")
B32: =IF(C32="","",9) | C32: =IFERROR(INDEX($Q$6:$Q$16,MATCH(9,$U$6:$U$16,0)),"") | D32: =IFERROR(INDEX($S$6:$S$16,MATCH(9,$U$6:$U$16,0)),"") | F32: =IF(G32="","",9) | G32: =IFERROR(INDEX($Q$6:$Q$16,MATCH(9,$W$6:$W$16,0)),"") | H32: =IFERROR(INDEX($S$6:$S$16,MATCH(9,$W$6:$W$16,0)),"")
B33: =IF(C33="","",10) | C33: =IFERROR(INDEX($Q$6:$Q$16,MATCH(10,$U$6:$U$16,0)),"") | D33: =IFERROR(INDEX($S$6:$S$16,MATCH(10,$U$6:$U$16,0)),"") | F33: =IF(G33="","",10) | G33: =IFERROR(INDEX($Q$6:$Q$16,MATCH(10,$W$6:$W$16,0)),"") | H33: =IFERROR(INDEX($S$6:$S$16,MATCH(10,$W$6:$W$16,0)),"")
B34: =IF(C34="","",11) | C34: =IFERROR(INDEX($Q$6:$Q$16,MATCH(11,$U$6:$U$16,0)),"") | D34: =IFERROR(INDEX($S$6:$S$16,MATCH(11,$U$6:$U$16,0)),"") | F34: =IF(G34="","",11) | G34: =IFERROR(INDEX($Q$6:$Q$16,MATCH(11,$W$6:$W$16,0)),"") | H34: =IFERROR(INDEX($S$6:$S$16,MATCH(11,$W$6:$W$16,0)),"")
B35: =IF(C35="","",12) | C35: =IFERROR(INDEX($Q$6:$Q$16,MATCH(12,$U$6:$U$16,0)),"") | D35: =IFERROR(INDEX($S$6:$S$16,MATCH(12,$U$6:$U$16,0)),"") | F35: =IF(G35="","",12) | G35: =IFERROR(INDEX($Q$6:$Q$16,MATCH(12,$W$6:$W$16,0)),"") | H35: =IFERROR(INDEX($S$6:$S$16,MATCH(12,$W$6:$W$16,0)),"")
C36: =IF(SUM($T$6:$T$16)>12,"+ "&(SUM($T$6:$T$16)-12)&" item(ns) não exibido(s)","") | G36: =IF(SUM($V$6:$V$16)>12,"+ "&(SUM($V$6:$V$16)-12)&" item(ns) não exibido(s)","")
B38: Forças/Fraquezas: classificação automática (aba 'Indicadores (F-W)'). Oportunidades/Ameaças: intensidade ≥ corte definido em 'Parâmetros' (aba 'Fatores Externos (O-A)'). Fontes na aba 'Fontes e Notas'.

Sheet SWOT - Cáceres
B1: MATRIZ SWOT — CÁCERES (MT)
B2: Perfil Econômico-Produtivo Setorial Municipal (PESM) | Projeto DSIP-MT – Meta 1 | Pantanal Norte
B3: ="Indicadores internos com dado: "&(COUNTA(L6:L21)-COUNTBLANK(L6:L21))&" de 16 | Neutros: "&COUNTIF(L6:L21,"Neutro")&" | Fatores externos pontuados: "&COUNT(S6:S16)&" de 11" -> Indicadores internos com dado: 14 de 16 | Neutros: 3 | Fatores externos pontuados: 11 de 11
B5: FAVORÁVEL | F5: DESFAVORÁVEL
B6: ="FORÇAS (S) — "&COUNTIF($L$6:$L$21,"Força")&" item(ns)" -> FORÇAS (S) — 3 item(ns) | F6: ="FRAQUEZAS (W) — "&COUNTIF($L$6:$L$21,"Fraqueza")&" item(ns)" -> FRAQUEZAS (W) — 8 item(ns) | K6: =Aux!B6 -> [Agropecuária] AGR-01 – Quociente locacional do VAB agropecuário (base MT) (índice) | L6: ='Indicadores (F-W)'!Q6 -> Fraqueza | M6: =IF('Indicadores (F-W)'!P6="","",'Indicadores (F-W)'!P6) -> 0.3713 | N6: =IF(L6="Força",COUNTIF(L$6:L6,"Força"),"") | O6: =IF(L6="Fraqueza",COUNTIF(L$6:L6,"Fraqueza"),"") -> 1 | Q6: =Aux!I6 -> [Agropecuária] OP-01 – Demanda externa por carne bovina e proteína animal | R6: =Aux!J6 -> Oportunidade | S6: =IF('Fatores Externos (O-A)'!G6="","",'Fatores Externos (O-A)'!G6) -> 3 | T6: =IF(AND(R6="Oportunidade",ISNUMBER(S6)),IF(S6>=Parâmetros!$B$5,1,0),0) -> 1 | U6: =IF(T6=1,SUM(T$6:T6),"") -> 1 | V6: =IF(AND(R6="Ameaça",ISNUMBER(S6)),IF(S6>=Parâmetros!$B$5,1,0),0) -> 0 | W6: =IF(V6=1,SUM(V$6:V6),"")
B7: Nº | C7: Item (área-chave, código e descrição) | D7: Valor | F7: Nº | G7: Item (área-chave, código e descrição) | H7: Valor | K7: =Aux!B7 -> [Agropecuária] AGR-02 – Valor da produção das lavouras por área colhida (R$/ha) | L7: ='Indicadores (F-W)'!Q7 -> Neutro | M7: =IF('Indicadores (F-W)'!P7="","",'Indicadores (F-W)'!P7) -> 5729.32 | N7: =IF(L7="Força",COUNTIF(L$6:L7,"Força"),"") | O7: =IF(L7="Fraqueza",COUNTIF(L$6:L7,"Fraqueza"),"") | Q7: =Aux!I7 -> [Agropecuária] OP-02 – Mercados para produtos diferenciados e certificados (carne sustentável/orgânica, origem Pantanal) | R7: =Aux!J7 -> Oportunidade | S7: =IF('Fatores Externos (O-A)'!G7="","",'Fatores Externos (O-A)'!G7) -> 3 | T7: =IF(AND(R7="Oportunidade",ISNUMBER(S7)),IF(S7>=Parâmetros!$B$5,1,0),0) -> 1 | U7: =IF(T7=1,SUM(T$6:T7),"") -> 2 | V7: =IF(AND(R7="Ameaça",ISNUMBER(S7)),IF(S7>=Parâmetros!$B$5,1,0),0) -> 0 | W7: =IF(V7=1,SUM(V$6:V7),"")
A8: AMBIENTE INTERNO | B8: =IF(C8="","",1) -> 1 | C8: =IFERROR(INDEX($K$6:$K$21,MATCH(1,$N$6:$N$21,0)),"") -> [Agropecuária] AGR-03 – Variação do efetivo bovino em 5 anos (%) | D8: =IFERROR(INDEX($M$6:$M$21,MATCH(1,$N$6:$N$21,0)),"") -> 22.65 | F8: =IF(G8="","",1) -> 1 | G8: =IFERROR(INDEX($K$6:$K$21,MATCH(1,$O$6:$O$21,0)),"") -> [Agropecuária] AGR-01 – Quociente locacional do VAB agropecuário (base MT) (índice) | H8: =IFERROR(INDEX($M$6:$M$21,MATCH(1,$O$6:$O$21,0)),"") -> 0.3713 | K8: =Aux!B8 -> [Agropecuária] AGR-03 – Variação do efetivo bovino em 5 anos (%) | L8: ='Indicadores (F-W)'!Q8 -> Força | M8: =IF('Indicadores (F-W)'!P8="","",'Indicadores (F-W)'!P8) -> 22.65 | N8: =IF(L8="Força",COUNTIF(L$6:L8,"Força"),"") -> 1 | O8: =IF(L8="Fraqueza",COUNTIF(L$6:L8,"Fraqueza"),"") | Q8: =Aux!I8 -> [Comércio e Serviços] OP-03 – Expansão do turismo de natureza, pesca esportiva e ecoturismo | R8: =Aux!J8 -> Oportunidade | S8: =IF('Fatores Externos (O-A)'!G8="","",'Fatores Externos (O-A)'!G8) -> 3 | T8: =IF(AND(R8="Oportunidade",ISNUMBER(S8)),IF(S8>=Parâmetros!$B$5,1,0),0) -> 1 | U8: =IF(T8=1,SUM(T$6:T8),"") -> 3 | V8: =IF(AND(R8="Ameaça",ISNUMBER(S8)),IF(S8>=Parâmetros!$B$5,1,0),0) -> 0 | W8: =IF(V8=1,SUM(V$6:V8),"")
B9: =IF(C9="","",2) -> 2 | C9: =IFERROR(INDEX($K$6:$K$21,MATCH(2,$N$6:$N$21,0)),"") -> [Indústria] IND-02 – Variação do emprego formal na indústria em 5 anos (%) | D9: =IFERROR(INDEX($M$6:$M$21,MATCH(2,$N$6:$N$21,0)),"") -> 58.91 | F9: =IF(G9="","",2) -> 2 | G9: =IFERROR(INDEX($K$6:$K$21,MATCH(2,$O$6:$O$21,0)),"") -> [Indústria] IND-01 – Quociente locacional do VAB industrial (base MT) (índice) | H9: =IFERROR(INDEX($M$6:$M$21,MATCH(2,$O$6:$O$21,0)),"") -> 0.6374 | K9: =Aux!B9 -> [Agropecuária] AGR-04 – Estabelecimentos agropecuários que receberam assistência técnica (%) | L9: ='Indicadores (F-W)'!Q9 | M9: =IF('Indicadores (F-W)'!P9="","",'Indicadores (F-W)'!P9) | N9: =IF(L9="Força",COUNTIF(L$6:L9,"Força"),"") | O9: =IF(L9="Fraqueza",COUNTIF(L$6:L9,"Fraqueza"),"") | Q9: =Aux!I9 -> [Indústria] OP-04 – Agroindustrialização e verticalização (frigoríficos, laticínios, sucroenergético) | R9: =Aux!J9 -> Oportunidade | S9: =IF('Fatores Externos (O-A)'!G9="","",'Fatores Externos (O-A)'!G9) -> 2 | T9: =IF(AND(R9="Oportunidade",ISNUMBER(S9)),IF(S9>=Parâmetros!$B$5,1,0),0) -> 1 | U9: =IF(T9=1,SUM(T$6:T9),"") -> 4 | V9: =IF(AND(R9="Ameaça",ISNUMBER(S9)),IF(S9>=Parâmetros!$B$5,1,0),0) -> 0 | W9: =IF(V9=1,SUM(V$6:V9),"")
B10: =IF(C10="","",3) -> 3 | C10: =IFERROR(INDEX($K$6:$K$21,MATCH(3,$N$6:$N$21,0)),"") -> [Comércio e Serviços] CS-01 – Quociente locacional do VAB de serviços, exceto adm. pública (base MT) (índice) | D10: =IFERROR(INDEX($M$6:$M$21,MATCH(3,$N$6:$N$21,0)),"") -> 1.3013 | F10: =IF(G10="","",3) -> 3 | G10: =IFERROR(INDEX($K$6:$K$21,MATCH(3,$O$6:$O$21,0)),"") -> [Indústria] IND-03 – Remuneração média do emprego formal industrial (R$) | H10: =IFERROR(INDEX($M$6:$M$21,MATCH(3,$O$6:$O$21,0)),"") -> 2345.65 | K10: =Aux!B10 -> [Agropecuária] AGR-05 – Diversificação agrícola (1 − HHI do valor da produção das lavouras) (índice 0–1) | L10: ='Indicadores (F-W)'!Q10 | M10: =IF('Indicadores (F-W)'!P10="","",'Indicadores (F-W)'!P10) | N10: =IF(L10="Força",COUNTIF(L$6:L10,"Força"),"") | O10: =IF(L10="Fraqueza",COUNTIF(L$6:L10,"Fraqueza"),"") | Q10: =Aux!I10 -> [Estrutura Econômica e Fiscal] OP-05 – Corredores logísticos (rodovias federais, ferrovia, hidrovia do Paraguai) | R10: =Aux!J10 -> Oportunidade | S10: =IF('Fatores Externos (O-A)'!G10="","",'Fatores Externos (O-A)'!G10) -> 3 | T10: =IF(AND(R10="Oportunidade",ISNUMBER(S10)),IF(S10>=Parâmetros!$B$5,1,0),0) -> 1 | U10: =IF(T10=1,SUM(T$6:T10),"") -> 5 | V10: =IF(AND(R10="Ameaça",ISNUMBER(S10)),IF(S10>=Parâmetros!$B$5,1,0),0) -> 0 | W10: =IF(V10=1,SUM(V$6:V10),"")
B11: =IF(C11="","",4) | C11: =IFERROR(INDEX($K$6:$K$21,MATCH(4,$N$6:$N$21,0)),"") | D11: =IFERROR(INDEX($M$6:$M$21,MATCH(4,$N$6:$N$21,0)),"") | F11: =IF(G11="","",4) -> 4 | G11: =IFERROR(INDEX($K$6:$K$21,MATCH(4,$O$6:$O$21,0)),"") -> [Comércio e Serviços] CS-02 – Variação do emprego formal em comércio e serviços em 5 anos (%) | H11: =IFERROR(INDEX($M$6:$M$21,MATCH(4,$O$6:$O$21,0)),"") -> 13.05 | K11: =Aux!B11 -> [Indústria] IND-01 – Quociente locacional do VAB industrial (base MT) (índice) | L11: ='Indicadores (F-W)'!Q11 -> Fraqueza | M11: =IF('Indicadores (F-W)'!P11="","",'Indicadores (F-W)'!P11) -> 0.6374 | N11: =IF(L11="Força",COUNTIF(L$6:L11,"Força"),"") | O11: =IF(L11="Fraqueza",COUNTIF(L$6:L11,"Fraqueza"),"") -> 2 | Q11: =Aux!I11 -> [Estrutura Econômica e Fiscal] OP-06 – Instrumentos de fomento e financiamento (FCO, crédito rural, PSA, mercado de carbono) | R11: =Aux!J11 -> Oportunidade | S11: =IF('Fatores Externos (O-A)'!G11="","",'Fatores Externos (O-A)'!G11) -> 3 | T11: =IF(AND(R11="Oportunidade",ISNUMBER(S11)),IF(S11>=Parâmetros!$B$5,1,0),0) -> 1 | U11: =IF(T11=1,SUM(T$6:T11),"") -> 6 | V11: =IF(AND(R11="Ameaça",ISNUMBER(S11)),IF(S11>=Parâmetros!$B$5,1,0),0) -> 0 | W11: =IF(V11=1,SUM(V$6:V11),"")
B12: =IF(C12="","",5) | C12: =IFERROR(INDEX($K$6:$K$21,MATCH(5,$N$6:$N$21,0)),"") | D12: =IFERROR(INDEX($M$6:$M$21,MATCH(5,$N$6:$N$21,0)),"") | F12: =IF(G12="","",5) -> 5 | G12: =IFERROR(INDEX($K$6:$K$21,MATCH(5,$O$6:$O$21,0)),"") -> [Comércio e Serviços] CS-03 – Empresas e outras organizações ativas por mil habitantes (un./mil hab.) | H12: =IFERROR(INDEX($M$6:$M$21,MATCH(5,$O$6:$O$21,0)),"") -> 19.41 | K12: =Aux!B12 -> [Indústria] IND-02 – Variação do emprego formal na indústria em 5 anos (%) | L12: ='Indicadores (F-W)'!Q12 -> Força | M12: =IF('Indicadores (F-W)'!P12="","",'Indicadores (F-W)'!P12) -> 58.91 | N12: =IF(L12="Força",COUNTIF(L$6:L12,"Força"),"") -> 2 | O12: =IF(L12="Fraqueza",COUNTIF(L$6:L12,"Fraqueza"),"") | Q12: =Aux!I12 -> [Agropecuária] AM-01 – Eventos climáticos extremos: secas prolongadas e incêndios no Pantanal | R12: =Aux!J12 -> Ameaça | S12: =IF('Fatores Externos (O-A)'!G12="","",'Fatores Externos (O-A)'!G12) -> 3 | T12: =IF(AND(R12="Oportunidade",ISNUMBER(S12)),IF(S12>=Parâmetros!$B$5,1,0),0) -> 0 | U12: =IF(T12=1,SUM(T$6:T12),"") | V12: =IF(AND(R12="Ameaça",ISNUMBER(S12)),IF(S12>=Parâmetros!$B$5,1,0),0) -> 1 | W12: =IF(V12=1,SUM(V$6:V12),"") -> 1
B13: =IF(C13="","",6) | C13: =IFERROR(INDEX($K$6:$K$21,MATCH(6,$N$6:$N$21,0)),"") | D13: =IFERROR(INDEX($M$6:$M$21,MATCH(6,$N$6:$N$21,0)),"") | F13: =IF(G13="","",6) -> 6 | G13: =IFERROR(INDEX($K$6:$K$21,MATCH(6,$O$6:$O$21,0)),"") -> [Estrutura Econômica e Fiscal] EST-01 – PIB per capita (R$) | H13: =IFERROR(INDEX($M$6:$M$21,MATCH(6,$O$6:$O$21,0)),"") -> 31174.15 | K13: =Aux!B13 -> [Indústria] IND-03 – Remuneração média do emprego formal industrial (R$) | L13: ='Indicadores (F-W)'!Q13 -> Fraqueza | M13: =IF('Indicadores (F-W)'!P13="","",'Indicadores (F-W)'!P13) -> 2345.65 | N13: =IF(L13="Força",COUNTIF(L$6:L13,"Força"),"") | O13: =IF(L13="Fraqueza",COUNTIF(L$6:L13,"Fraqueza"),"") -> 3 | Q13: =Aux!I13 -> [Agropecuária] AM-02 – Volatilidade de preços de commodities (boi gordo, soja, milho) | R13: =Aux!J13 -> Ameaça | S13: =IF('Fatores Externos (O-A)'!G13="","",'Fatores Externos (O-A)'!G13) -> 3 | T13: =IF(AND(R13="Oportunidade",ISNUMBER(S13)),IF(S13>=Parâmetros!$B$5,1,0),0) -> 0 | U13: =IF(T13=1,SUM(T$6:T13),"") | V13: =IF(AND(R13="Ameaça",ISNUMBER(S13)),IF(S13>=Parâmetros!$B$5,1,0),0) -> 1 | W13: =IF(V13=1,SUM(V$6:V13),"") -> 2
B14: =IF(C14="","",7) | C14: =IFERROR(INDEX($K$6:$K$21,MATCH(7,$N$6:$N$21,0)),"") | D14: =IFERROR(INDEX($M$6:$M$21,MATCH(7,$N$6:$N$21,0)),"") | F14: =IF(G14="","",7) -> 7 | G14: =IFERROR(INDEX($K$6:$K$21,MATCH(7,$O$6:$O$21,0)),"") -> [Estrutura Econômica e Fiscal] EST-02 – Participação da administração pública no VAB total (%) | H14: =IFERROR(INDEX($M$6:$M$21,MATCH(7,$O$6:$O$21,0)),"") -> 30.82 | K14: =Aux!B14 -> [Comércio e Serviços] CS-01 – Quociente locacional do VAB de serviços, exceto adm. pública (base MT) (índice) | L14: ='Indicadores (F-W)'!Q14 -> Força | M14: =IF('Indicadores (F-W)'!P14="","",'Indicadores (F-W)'!P14) -> 1.3013 | N14: =IF(L14="Força",COUNTIF(L$6:L14,"Força"),"") -> 3 | O14: =IF(L14="Fraqueza",COUNTIF(L$6:L14,"Fraqueza"),"") | Q14: =Aux!I14 -> [Agropecuária] AM-03 – Exigências ambientais de mercados importadores e barreiras ligadas a desmatamento (ex.: EUDR) | R14: =Aux!J14 -> Ameaça | S14: =IF('Fatores Externos (O-A)'!G14="","",'Fatores Externos (O-A)'!G14) -> 3 | T14: =IF(AND(R14="Oportunidade",ISNUMBER(S14)),IF(S14>=Parâmetros!$B$5,1,0),0) -> 0 | U14: =IF(T14=1,SUM(T$6:T14),"") | V14: =IF(AND(R14="Ameaça",ISNUMBER(S14)),IF(S14>=Parâmetros!$B$5,1,0),0) -> 1 | W14: =IF(V14=1,SUM(V$6:V14),"") -> 3
B15: =IF(C15="","",8) | C15: =IFERROR(INDEX($K$6:$K$21,MATCH(8,$N$6:$N$21,0)),"") | D15: =IFERROR(INDEX($M$6:$M$21,MATCH(8,$N$6:$N$21,0)),"") | F15: =IF(G15="","",8) -> 8 | G15: =IFERROR(INDEX($K$6:$K$21,MATCH(8,$O$6:$O$21,0)),"") -> [Estrutura Econômica e Fiscal] EST-03 – Vínculos formais por 100 habitantes (vínculos/100 hab.) | H15: =IFERROR(INDEX($M$6:$M$21,MATCH(8,$O$6:$O$21,0)),"") -> 18.4 | K15: =Aux!B15 -> [Comércio e Serviços] CS-02 – Variação do emprego formal em comércio e serviços em 5 anos (%) | L15: ='Indicadores (F-W)'!Q15 -> Fraqueza | M15: =IF('Indicadores (F-W)'!P15="","",'Indicadores (F-W)'!P15) -> 13.05 | N15: =IF(L15="Força",COUNTIF(L$6:L15,"Força"),"") | O15: =IF(L15="Fraqueza",COUNTIF(L$6:L15,"Fraqueza"),"") -> 4 | Q15: =Aux!I15 -> [Estrutura Econômica e Fiscal] AM-04 – Transição da Reforma Tributária (IBS/CBS) e efeitos sobre a repartição de receitas municipais | R15: =Aux!J15 -> Ameaça | S15: =IF('Fatores Externos (O-A)'!G15="","",'Fatores Externos (O-A)'!G15) -> 2 | T15: =IF(AND(R15="Oportunidade",ISNUMBER(S15)),IF(S15>=Parâmetros!$B$5,1,0),0) -> 0 | U15: =IF(T15=1,SUM(T$6:T15),"") | V15: =IF(AND(R15="Ameaça",ISNUMBER(S15)),IF(S15>=Parâmetros!$B$5,1,0),0) -> 1 | W15: =IF(V15=1,SUM(V$6:V15),"") -> 4
B16: =IF(C16="","",9) | C16: =IFERROR(INDEX($K$6:$K$21,MATCH(9,$N$6:$N$21,0)),"") | D16: =IFERROR(INDEX($M$6:$M$21,MATCH(9,$N$6:$N$21,0)),"") | F16: =IF(G16="","",9) | G16: =IFERROR(INDEX($K$6:$K$21,MATCH(9,$O$6:$O$21,0)),"") | H16: =IFERROR(INDEX($M$6:$M$21,MATCH(9,$O$6:$O$21,0)),"") | K16: =Aux!B16 -> [Comércio e Serviços] CS-03 – Empresas e outras organizações ativas por mil habitantes (un./mil hab.) | L16: ='Indicadores (F-W)'!Q16 -> Fraqueza | M16: =IF('Indicadores (F-W)'!P16="","",'Indicadores (F-W)'!P16) -> 19.41 | N16: =IF(L16="Força",COUNTIF(L$6:L16,"Força"),"") | O16: =IF(L16="Fraqueza",COUNTIF(L$6:L16,"Fraqueza"),"") -> 5 | Q16: =Aux!I16 -> [Comércio e Serviços] AM-05 – Polarização regional por centros maiores (evasão de consumo, serviços e mão de obra) | R16: =Aux!J16 -> Ameaça | S16: =IF('Fatores Externos (O-A)'!G16="","",'Fatores Externos (O-A)'!G16) -> 1 | T16: =IF(AND(R16="Oportunidade",ISNUMBER(S16)),IF(S16>=Parâmetros!$B$5,1,0),0) -> 0 | U16: =IF(T16=1,SUM(T$6:T16),"") | V16: =IF(AND(R16="Ameaça",ISNUMBER(S16)),IF(S16>=Parâmetros!$B$5,1,0),0) -> 0 | W16: =IF(V16=1,SUM(V$6:V16),"")
B17: =IF(C17="","",10) | C17: =IFERROR(INDEX($K$6:$K$21,MATCH(10,$N$6:$N$21,0)),"") | D17: =IFERROR(INDEX($M$6:$M$21,MATCH(10,$N$6:$N$21,0)),"") | F17: =IF(G17="","",10) | G17: =IFERROR(INDEX($K$6:$K$21,MATCH(10,$O$6:$O$21,0)),"") | H17: =IFERROR(INDEX($M$6:$M$21,MATCH(10,$O$6:$O$21,0)),"") | K17: =Aux!B17 -> [Estrutura Econômica e Fiscal] EST-01 – PIB per capita (R$) | L17: ='Indicadores (F-W)'!Q17 -> Fraqueza | M17: =IF('Indicadores (F-W)'!P17="","",'Indicadores (F-W)'!P17) -> 31174.15 | N17: =IF(L17="Força",COUNTIF(L$6:L17,"Força"),"") | O17: =IF(L17="Fraqueza",COUNTIF(L$6:L17,"Fraqueza"),"") -> 6
B18: =IF(C18="","",11) | C18: =IFERROR(INDEX($K$6:$K$21,MATCH(11,$N$6:$N$21,0)),"") | D18: =IFERROR(INDEX($M$6:$M$21,MATCH(11,$N$6:$N$21,0)),"") | F18: =IF(G18="","",11) | G18: =IFERROR(INDEX($K$6:$K$21,MATCH(11,$O$6:$O$21,0)),"") | H18: =IFERROR(INDEX($M$6:$M$21,MATCH(11,$O$6:$O$21,0)),"") | K18: =Aux!B18 -> [Estrutura Econômica e Fiscal] EST-02 – Participação da administração pública no VAB total (%) | L18: ='Indicadores (F-W)'!Q18 -> Fraqueza | M18: =IF('Indicadores (F-W)'!P18="","",'Indicadores (F-W)'!P18) -> 30.82 | N18: =IF(L18="Força",COUNTIF(L$6:L18,"Força"),"") | O18: =IF(L18="Fraqueza",COUNTIF(L$6:L18,"Fraqueza"),"") -> 7
B19: =IF(C19="","",12) | C19: =IFERROR(INDEX($K$6:$K$21,MATCH(12,$N$6:$N$21,0)),"") | D19: =IFERROR(INDEX($M$6:$M$21,MATCH(12,$N$6:$N$21,0)),"") | F19: =IF(G19="","",12) | G19: =IFERROR(INDEX($K$6:$K$21,MATCH(12,$O$6:$O$21,0)),"") | H19: =IFERROR(INDEX($M$6:$M$21,MATCH(12,$O$6:$O$21,0)),"") | K19: =Aux!B19 -> [Estrutura Econômica e Fiscal] EST-03 – Vínculos formais por 100 habitantes (vínculos/100 hab.) | L19: ='Indicadores (F-W)'!Q19 -> Fraqueza | M19: =IF('Indicadores (F-W)'!P19="","",'Indicadores (F-W)'!P19) -> 18.4 | N19: =IF(L19="Força",COUNTIF(L$6:L19,"Força"),"") | O19: =IF(L19="Fraqueza",COUNTIF(L$6:L19,"Fraqueza"),"") -> 8
C20: =IF(COUNTIF($L$6:$L$21,"Força")>12,"+ "&(COUNTIF($L$6:$L$21,"Força")-12)&" item(ns) não exibido(s)","") | G20: =IF(COUNTIF($L$6:$L$21,"Fraqueza")>12,"+ "&(COUNTIF($L$6:$L$21,"Fraqueza")-12)&" item(ns) não exibido(s)","") | K20: =Aux!B20 -> [Estrutura Econômica e Fiscal] EST-04 – Concentração setorial do emprego formal (HHI por seção CNAE) (índice 0–1) | L20: ='Indicadores (F-W)'!Q20 -> Neutro | M20: =IF('Indicadores (F-W)'!P20="","",'Indicadores (F-W)'!P20) -> 0.1286 | N20: =IF(L20="Força",COUNTIF(L$6:L20,"Força"),"") | O20: =IF(L20="Fraqueza",COUNTIF(L$6:L20,"Fraqueza"),"")
K21: =Aux!B21 -> [Estrutura Econômica e Fiscal] EST-05 – Receitas próprias / receita corrente (%) | L21: ='Indicadores (F-W)'!Q21 -> Neutro | M21: =IF('Indicadores (F-W)'!P21="","",'Indicadores (F-W)'!P21) -> 17.68 | N21: =IF(L21="Força",COUNTIF(L$6:L21,"Força"),"") | O21: =IF(L21="Fraqueza",COUNTIF(L$6:L21,"Fraqueza"),"")
